Workbook

Sheet Portfolio
A1: Portfolio Size | B1: 5000 | C1: Maximum budget per stock | D1: 1000 | E1: Min Entry Size | F1: 300 | G1: No ETFs/Reits | H1: 5 Stocks | I1: Amount Invested | J1: =sum(H:H) -> #N/A | K1: Invested Value | L1: =sum(I:I) -> #N/A | M1: Portfolio Return | N1: =(L1-J1)/B1 -> #N/A | O1: Portfolio Cash | P1: =B1-J1 -> #N/A | Q1: =L1-J1+B1 -> #N/A | R1: Look out for Big red number in this column
A2: Master Watchlist | B2: 300 | C2: 300 | D2: 400 | E2: <=== How to spend the £1000 HL | H2: 100 | I2: 150 | J2: 250 | K2: <=== How to spend the £500
A3: Ticker | B3: Name | C3: Reason for Entry | D3: Current Price | E3: Trading 212/Freetrade entry price | F3: Average Entry Price | G3: Number of Shares | H3: Current Cost | I3: Current Value | J3: % Weight of Portfolio | K3: Current Return (%) | L3: 30 Day Trend Chart | M3: Ccy | N3: Daily Change (%) | O3: Daily Change | P3: Daily High | Q3: Daily Low | R3: Range/ yest close | S3: Price/ year low | T3: Target Entry for Averaging | U3: Target Exit | V3: Trade Alert | W3: TRADE ALERT | X3: beta | Y3: low52 | Z3: high52 | AA3: volume avg | AB3: pe | AC3: datadelay | AD3: marketcap | AE3: Closeyest
A4: SPCE | B4: =IFERROR(__xludf.DUMMYFUNCTION("GOOGLEFINANCE(A4,""name"")"),"Virgin Galactic Holdings Inc") -> Virgin Galactic Holdings Inc | D4: =IFERROR(__xludf.DUMMYFUNCTION("GOOGLEFINANCE(A4)"),2.52) -> 2.52 | F4: =IF(M4="USD",E4/1.21,E4) -> 0 | H4: =IFERROR(__xludf.DUMMYFUNCTION("if(isblank(A4)=TRUE,0,if(M4=""GBX"",F4*G4/100,IF(M4=""EUR"",F4*G4/GOOGLEFINANCE(""CURRENCY:GBPEUR""),F4*G4/GOOGLEFINANCE(""CURRENCY:GBPUSD""))))"),0.0) -> 0 | I4: =IFERROR(__xludf.DUMMYFUNCTION("if(isblank(A4)=TRUE,0,if(M4=""GBX"",D4*G4/100,IF(M4=""EUR"",D4*G4/GOOGLEFINANCE(""CURRENCY:GBPEUR""),D4*G4/GOOGLEFINANCE(""CURRENCY:GBPUSD""))))"),0.0) -> 0 | J4: =H4/$B$1 -> 0 | K4: =I4/H4-1 -> #DIV/0! | L4: =IFERROR(__xludf.DUMMYFUNCTION("SPARKLINE(GoogleFinance(A4, ""price"", TODAY()-30, TODAY()),{""color"",""blue"";""linewidth"",2}) "),"") | M4: =IFERROR(__xludf.DUMMYFUNCTION("GOOGLEFINANCE(A4,""currency"")"),"USD") -> USD | N4: =round(D4/AE4-1,4) -> -0.0156 | O4: =IFERROR(__xludf.DUMMYFUNCTION("GOOGLEFINANCE(A4,""Change"")"),-0.04) -> -0.04 | P4: =IFERROR(__xludf.DUMMYFUNCTION("GOOGLEFINANCE(A4,""High"")"),2.54) -> 2.54 | Q4: =IFERROR(__xludf.DUMMYFUNCTION("GOOGLEFINANCE(A4,""low"")"),2.46) -> 2.46 | R4: =IFERROR(__xludf.DUMMYFUNCTION("abs(P4-Q4)/GOOGLEFINANCE(A4,""closeyest"")"),0.03125000000000003) -> 0.03125 | S4: =D4/Y4-1 -> 0.1559633 | T4: 43 | W4: =IF(ISERROR(if(or(AND(Q4<=T4,T4<=P4),AND(Q4<=U4, U4<=P4)),"TRADE ALERT","")),"DATA UNAVAILABLE",if(or(AND(Q4<=T4,T4<=P4),T4>P4,AND(Q4<=U4, U4<=P4)),"TRADE ALERT"&" - Price level hit for "&A4&" currently at "&D4&" "&B4,"")) -> TRADE ALERT - Price level hit for SPCE currently at 2.52 Virgin Galactic Holdings Inc | X4: =IFERROR(__xludf.DUMMYFUNCTION("GOOGLEFINANCE($A4,X$3)"),2.21) -> 2.21 | Y4: =IFERROR(__xludf.DUMMYFUNCTION("GOOGLEFINANCE($A4,Y$3)"),2.18) -> 2.18 | Z4: =IFERROR(__xludf.DUMMYFUNCTION("GOOGLEFINANCE($A4,Z$3)"),6.64) -> 6.64 | AA4: =IFERROR(__xludf.DUMMYFUNCTION("GOOGLEFINANCE($A4,AA$3)"),"#N/A") -> #N/A | AB4: =IFERROR(__xludf.DUMMYFUNCTION("GOOGLEFINANCE($A4,AB$3)"),"#N/A") -> #N/A | AC4: =IFERROR(__xludf.DUMMYFUNCTION("GOOGLEFINANCE($A4,AC$3)"),0.0) -> 0 | AD4: =IFERROR(__xludf.DUMMYFUNCTION("GOOGLEFINANCE($A4,AD$3)"),1.8428591E8) -> 184285910 | AE4: =IFERROR(__xludf.DUMMYFUNCTION("GOOGLEFINANCE($A4,AE$3)"),2.56) -> 2.56
A5: JMIA | B5: =IFERROR(__xludf.DUMMYFUNCTION("GOOGLEFINANCE(A5,""name"")"),"Jumia Technologies AG - ADR") -> Jumia Technologies AG - ADR | D5: =IFERROR(__xludf.DUMMYFUNCTION("GOOGLEFINANCE(A5)"),9.34) -> 9.34 | F5: =IF(M5="USD",E5/1.21,E5) -> 0 | H5: =IFERROR(__xludf.DUMMYFUNCTION("if(isblank(A5)=TRUE,0,if(M5=""GBX"",F5*G5/100,IF(M5=""EUR"",F5*G5/GOOGLEFINANCE(""CURRENCY:GBPEUR""),F5*G5/GOOGLEFINANCE(""CURRENCY:GBPUSD""))))"),0.0) -> 0 | I5: =IFERROR(__xludf.DUMMYFUNCTION("if(isblank(A5)=TRUE,0,if(M5=""GBX"",D5*G5/100,IF(M5=""EUR"",D5*G5/GOOGLEFINANCE(""CURRENCY:GBPEUR""),D5*G5/GOOGLEFINANCE(""CURRENCY:GBPUSD""))))"),0.0) -> 0 | J5: =H5/$B$1 -> 0 | K5: =I5/H5-1 -> #DIV/0! | L5: =IFERROR(__xludf.DUMMYFUNCTION("SPARKLINE(GoogleFinance(A5, ""price"", TODAY()-30, TODAY()),{""color"",""blue"";""linewidth"",2}) "),"") | M5: =IFERROR(__xludf.DUMMYFUNCTION("GOOGLEFINANCE(A5,""currency"")"),"USD") -> USD | N5: =round(D5/AE5-1,4) -> 0.0021 | O5: =IFERROR(__xludf.DUMMYFUNCTION("GOOGLEFINANCE(A5,""Change"")"),0.02) -> 0.02 | P5: =IFERROR(__xludf.DUMMYFUNCTION("GOOGLEFINANCE(A5,""High"")"),9.34) -> 9.34 | Q5: =IFERROR(__xludf.DUMMYFUNCTION("GOOGLEFINANCE(A5,""low"")"),9.01) -> 9.01 | R5: =IFERROR(__xludf.DUMMYFUNCTION("abs(P5-Q5)/GOOGLEFINANCE(A5,""closeyest"")"),0.03540772532188842) -> 0.035407725 | S5: =D5/Y5-1 -> 4.8375 | T5: 39 | W5: =IF(ISERROR(if(or(AND(Q5<=T5,T5<=P5),AND(Q5<=U5, U5<=P5)),"TRADE ALERT","")),"DATA UNAVAILABLE",if(or(AND(Q5<=T5,T5<=P5),T5>P5,AND(Q5<=U5, U5<=P5)),"TRADE ALERT"&" - Price level hit for "&A5&" currently at "&D5&" "&B5,"")) -> TRADE ALERT - Price level hit for JMIA currently at 9.34 Jumia Technologies AG - ADR | X5: =IFERROR(__xludf.DUMMYFUNCTION("GOOGLEFINANCE($A5,X$3)"),2.34) -> 2.34 | Y5: =IFERROR(__xludf.DUMMYFUNCTION("GOOGLEFINANCE($A5,Y$3)"),1.6) -> 1.6 | Z5: =IFERROR(__xludf.DUMMYFUNCTION("GOOGLEFINANCE($A5,Z$3)"),14.72) -> 14.72 | AA5: =IFERROR(__xludf.DUMMYFUNCTION("GOOGLEFINANCE($A5,AA$3)"),"#N/A") -> #N/A | AB5: =IFERROR(__xludf.DUMMYFUNCTION("GOOGLEFINANCE($A5,AB$3)"),"#N/A") -> #N/A | AC5: =IFERROR(__xludf.DUMMYFUNCTION("GOOGLEFINANCE($A5,AC$3)"),0.0) -> 0 | AD5: =IFERROR(__xludf.DUMMYFUNCTION("GOOGLEFINANCE($A5,AD$3)"),1.142577914E9) -> 1142577914 | AE5: =IFERROR(__xludf.DUMMYFUNCTION("GOOGLEFINANCE($A5,AE$3)"),9.32) -> 9.32
A6: TOOP | B6: =IFERROR(__xludf.DUMMYFUNCTION("GOOGLEFINANCE(A6,""name"")"),"#N/A") -> #N/A | D6: =IFERROR(__xludf.DUMMYFUNCTION("GOOGLEFINANCE(A6)"),"#N/A") -> #N/A | F6: =IF(M6="USD",E6/1.21,E6) -> #N/A | H6: =IFERROR(__xludf.DUMMYFUNCTION("if(isblank(A6)=TRUE,0,if(M6=""GBX"",F6*G6/100,IF(M6=""EUR"",F6*G6/GOOGLEFINANCE(""CURRENCY:GBPEUR""),F6*G6/GOOGLEFINANCE(""CURRENCY:GBPUSD""))))"),"#N/A") -> #N/A | I6: =IFERROR(__xludf.DUMMYFUNCTION("if(isblank(A6)=TRUE,0,if(M6=""GBX"",D6*G6/100,IF(M6=""EUR"",D6*G6/GOOGLEFINANCE(""CURRENCY:GBPEUR""),D6*G6/GOOGLEFINANCE(""CURRENCY:GBPUSD""))))"),"#N/A") -> #N/A | J6: =H6/$B$1 -> #N/A | K6: =I6/H6-1 -> #N/A | L6: =IFERROR(__xludf.DUMMYFUNCTION("SPARKLINE(GoogleFinance(A6, ""price"", TODAY()-30, TODAY()),{""color"",""blue"";""linewidth"",2}) "),"#N/A") -> #N/A | M6: =IFERROR(__xludf.DUMMYFUNCTION("GOOGLEFINANCE(A6,""currency"")"),"#N/A") -> #N/A | N6: =round(D6/AE6-1,4) -> #N/A | O6: =IFERROR(__xludf.DUMMYFUNCTION("GOOGLEFINANCE(A6,""Change"")"),"#N/A") -> #N/A | P6: =IFERROR(__xludf.DUMMYFUNCTION("GOOGLEFINANCE(A6,""High"")"),"#N/A") -> #N/A | Q6: =IFERROR(__xludf.DUMMYFUNCTION("GOOGLEFINANCE(A6,""low"")"),"#N/A") -> #N/A | R6: =IFERROR(__xludf.DUMMYFUNCTION("abs(P6-Q6)/GOOGLEFINANCE(A6,""closeyest"")"),"#N/A") -> #N/A | S6: =D6/Y6-1 -> #N/A | T6: 1.95 | W6: =IF(ISERROR(if(or(AND(Q6<=T6,T6<=P6),AND(Q6<=U6, U6<=P6)),"TRADE ALERT","")),"DATA UNAVAILABLE",if(or(AND(Q6<=T6,T6<=P6),T6>P6,AND(Q6<=U6, U6<=P6)),"TRADE ALERT"&" - Price level hit for "&A6&" currently at "&D6&" "&B6,"")) -> DATA UNAVAILABLE | X6: =IFERROR(__xludf.DUMMYFUNCTION("GOOGLEFINANCE($A6,X$3)"),"#N/A") -> #N/A | Y6: =IFERROR(__xludf.DUMMYFUNCTION("GOOGLEFINANCE($A6,Y$3)"),"#N/A") -> #N/A | Z6: =IFERROR(__xludf.DUMMYFUNCTION("GOOGLEFINANCE($A6,Z$3)"),"#N/A") -> #N/A | AA6: =IFERROR(__xludf.DUMMYFUNCTION("GOOGLEFINANCE($A6,AA$3)"),"#N/A") -> #N/A | AB6: =IFERROR(__xludf.DUMMYFUNCTION("GOOGLEFINANCE($A6,AB$3)"),"#N/A") -> #N/A | AC6: =IFERROR(__xludf.DUMMYFUNCTION("GOOGLEFINANCE($A6,AC$3)"),"#N/A") -> #N/A | AD6: =IFERROR(__xludf.DUMMYFUNCTION("GOOGLEFINANCE($A6,AD$3)"),"#N/A") -> #N/A | AE6: =IFERROR(__xludf.DUMMYFUNCTION("GOOGLEFINANCE($A6,AE$3)"),"#N/A") -> #N/A
A7: RGB | B7: =IFERROR(__xludf.DUMMYFUNCTION("GOOGLEFINANCE(A7,""name"")"),"Russell Inv Australian Government Bond ETF") -> Russell Inv Australian Government Bond ETF | D7: =IFERROR(__xludf.DUMMYFUNCTION("GOOGLEFINANCE(A7)"),19.02) -> 19.02 | F7: =IF(M7="USD",E7/1.21,E7) | H7: =IFERROR(__xludf.DUMMYFUNCTION("if(isblank(A7)=TRUE,0,if(M7=""GBX"",F7*G7/100,IF(M7=""EUR"",F7*G7/GOOGLEFINANCE(""CURRENCY:GBPEUR""),F7*G7/GOOGLEFINANCE(""CURRENCY:GBPUSD""))))"),0.0) -> 0 | I7: =IFERROR(__xludf.DUMMYFUNCTION("if(isblank(A7)=TRUE,0,if(M7=""GBX"",D7*G7/100,IF(M7=""EUR"",D7*G7/GOOGLEFINANCE(""CURRENCY:GBPEUR""),D7*G7/GOOGLEFINANCE(""CURRENCY:GBPUSD""))))"),0.0) -> 0 | J7: =H7/$B$1 -> 0 | K7: =I7/H7-1 -> #DIV/0! | L7: =IFERROR(__xludf.DUMMYFUNCTION("SPARKLINE(GoogleFinance(A7, ""price"", TODAY()-30, TODAY()),{""color"",""blue"";""linewidth"",2}) "),"") | M7: =IFERROR(__xludf.DUMMYFUNCTION("GOOGLEFINANCE(A7,""currency"")"),"AUD") -> AUD | N7: =round(D7/AE7-1,4) -> 0.0016 | O7: =IFERROR(__xludf.DUMMYFUNCTION("GOOGLEFINANCE(A7,""Change"")"),0.03) -> 0.03 | P7: =IFERROR(__xludf.DUMMYFUNCTION("GOOGLEFINANCE(A7,""High"")"),19.02) -> 19.02 | Q7: =IFERROR(__xludf.DUMMYFUNCTION("GOOGLEFINANCE(A7,""low"")"),18.95) -> 18.95 | R7: =IFERROR(__xludf.DUMMYFUNCTION("abs(P7-Q7)/GOOGLEFINANCE(A7,""closeyest"")"),0.0036861506055819006) -> 0.0036861506 | S7: =D7/Y7-1 -> 0.017112299 | T7: 115 | W7: =IF(ISERROR(if(or(AND(Q7<=T7,T7<=P7),AND(Q7<=U7, U7<=P7)),"TRADE ALERT","")),"DATA UNAVAILABLE",if(or(AND(Q7<=T7,T7<=P7),T7>P7,AND(Q7<=U7, U7<=P7)),"TRADE ALERT"&" - Price level hit for "&A7&" currently at "&D7&" "&B7,"")) -> TRADE ALERT - Price level hit for RGB currently at 19.02 Russell Inv Australian Government Bond ETF | X7: =IFERROR(__xludf.DUMMYFUNCTION("GOOGLEFINANCE($A7,X$3)"),"#N/A") -> #N/A | Y7: =IFERROR(__xludf.DUMMYFUNCTION("GOOGLEFINANCE($A7,Y$3)"),18.7) -> 18.7 | Z7: =IFERROR(__xludf.DUMMYFUNCTION("GOOGLEFINANCE($A7,Z$3)"),20.02) -> 20.02 | AA7: =IFERROR(__xludf.DUMMYFUNCTION("GOOGLEFINANCE($A7,AA$3)"),"#N/A") -> #N/A | AB7: =IFERROR(__xludf.DUMMYFUNCTION("GOOGLEFINANCE($A7,AB$3)"),"#N/A") -> #N/A | AC7: =IFERROR(__xludf.DUMMYFUNCTION("GOOGLEFINANCE($A7,AC$3)"),20.0) -> 20 | AD7: =IFERROR(__xludf.DUMMYFUNCTION("GOOGLEFINANCE($A7,AD$3)"),"#N/A") -> #N/A | AE7: =IFERROR(__xludf.DUMMYFUNCTION("GOOGLEFINANCE($A7,AE$3)"),18.99) -> 18.99
A8: KODK | B8: =IFERROR(__xludf.DUMMYFUNCTION("GOOGLEFINANCE(A8,""name"")"),"Eastman Kodak Co") -> Eastman Kodak Co | D8: =IFERROR(__xludf.DUMMYFUNCTION("GOOGLEFINANCE(A8)"),7.73) -> 7.73 | F8: =IF(M8="USD",E8/1.21,E8) -> 0 | H8: =IFERROR(__xludf.DUMMYFUNCTION("if(isblank(A8)=TRUE,0,if(M8=""GBX"",F8*G8/100,IF(M8=""EUR"",F8*G8/GOOGLEFINANCE(""CURRENCY:GBPEUR""),F8*G8/GOOGLEFINANCE(""CURRENCY:GBPUSD""))))"),0.0) -> 0 | I8: =IFERROR(__xludf.DUMMYFUNCTION("if(isblank(A8)=TRUE,0,if(M8=""GBX"",D8*G8/100,IF(M8=""EUR"",D8*G8/GOOGLEFINANCE(""CURRENCY:GBPEUR""),D8*G8/GOOGLEFINANCE(""CURRENCY:GBPUSD""))))"),0.0) -> 0 | J8: =H8/$B$1 -> 0 | K8: =I8/H8-1 -> #DIV/0! | L8: =IFERROR(__xludf.DUMMYFUNCTION("SPARKLINE(GoogleFinance(A8, ""price"", TODAY()-30, TODAY()),{""color"",""blue"";""linewidth"",2}) "),"") | M8: =IFERROR(__xludf.DUMMYFUNCTION("GOOGLEFINANCE(A8,""currency"")"),"USD") -> USD | N8: =round(D8/AE8-1,4) -> 0.0078 | O8: =IFERROR(__xludf.DUMMYFUNCTION("GOOGLEFINANCE(A8,""Change"")"),0.05) -> 0.05 | P8: =IFERROR(__xludf.DUMMYFUNCTION("GOOGLEFINANCE(A8,""High"")"),7.8) -> 7.8 | Q8: =IFERROR(__xludf.DUMMYFUNCTION("GOOGLEFINANCE(A8,""low"")"),7.52) -> 7.52 | R8: =IFERROR(__xludf.DUMMYFUNCTION("abs(P8-Q8)/GOOGLEFINANCE(A8,""closeyest"")"),0.03650586701434162) -> 0.036505867 | S8: =D8/Y8-1 -> 0.56795132 | T8: 76 | W8: =IF(ISERROR(if(or(AND(Q8<=T8,T8<=P8),AND(Q8<=U8, U8<=P8)),"TRADE ALERT","")),"DATA UNAVAILABLE",if(or(AND(Q8<=T8,T8<=P8),T8>P8,AND(Q8<=U8, U8<=P8)),"TRADE ALERT"&" - Price level hit for "&A8&" currently at "&D8&" "&B8,"")) -> TRADE ALERT - Price level hit for KODK currently at 7.73 Eastman Kodak Co | X8: =IFERROR(__xludf.DUMMYFUNCTION("GOOGLEFINANCE($A8,X$3)"),1.47) -> 1.47 | Y8: =IFERROR(__xludf.DUMMYFUNCTION("GOOGLEFINANCE($A8,Y$3)"),4.93) -> 4.93 | Z8: =IFERROR(__xludf.DUMMYFUNCTION("GOOGLEFINANCE($A8,Z$3)"),9.96) -> 9.96 | AA8: =IFERROR(__xludf.DUMMYFUNCTION("GOOGLEFINANCE($A8,AA$3)"),"#N/A") -> #N/A | AB8: =IFERROR(__xludf.DUMMYFUNCTION("GOOGLEFINANCE($A8,AB$3)"),"#N/A") -> #N/A | AC8: =IFERROR(__xludf.DUMMYFUNCTION("GOOGLEFINANCE($A8,AC$3)"),0.0) -> 0 | AD8: =IFERROR(__xludf.DUMMYFUNCTION("GOOGLEFINANCE($A8,AD$3)"),7.4468999E8) -> 744689990 | AE8: =IFERROR(__xludf.DUMMYFUNCTION("GOOGLEFINANCE($A8,AE$3)"),7.67) -> 7.67
B9: =IFERROR(__xludf.DUMMYFUNCTION("GOOGLEFINANCE(A9,""name"")"),"#N/A") -> #N/A | D9: =IFERROR(__xludf.DUMMYFUNCTION("GOOGLEFINANCE(A9)"),"#N/A") -> #N/A | F9: =IF(M9="USD",E9/1.21,E9) -> #N/A | H9: =IFERROR(__xludf.DUMMYFUNCTION("if(isblank(A9)=TRUE,0,if(M9=""GBX"",F9*G9/100,IF(M9=""EUR"",F9*G9/GOOGLEFINANCE(""CURRENCY:GBPEUR""),F9*G9/GOOGLEFINANCE(""CURRENCY:GBPUSD""))))"),0.0) -> 0 | I9: =IFERROR(__xludf.DUMMYFUNCTION("if(isblank(A9)=TRUE,0,if(M9=""GBX"",D9*G9/100,IF(M9=""EUR"",D9*G9/GOOGLEFINANCE(""CURRENCY:GBPEUR""),D9*G9/GOOGLEFINANCE(""CURRENCY:GBPUSD""))))"),0.0) -> 0 | J9: =H9/$B$1 -> 0 | K9: =I9/H9-1 -> #DIV/0! | L9: =IFERROR(__xludf.DUMMYFUNCTION("SPARKLINE(GoogleFinance(A9, ""price"", TODAY()-30, TODAY()),{""color"",""blue"";""linewidth"",2}) "),"#N/A") -> #N/A | M9: =IFERROR(__xludf.DUMMYFUNCTION("GOOGLEFINANCE(A9,""currency"")"),"#N/A") -> #N/A | N9: =round(D9/AE9-1,4) -> #N/A | O9: =IFERROR(__xludf.DUMMYFUNCTION("GOOGLEFINANCE(A9,""Change"")"),"#N/A") -> #N/A | P9: =IFERROR(__xludf.DUMMYFUNCTION("GOOGLEFINANCE(A9,""High"")"),"#N/A") -> #N/A | Q9: =IFERROR(__xludf.DUMMYFUNCTION("GOOGLEFINANCE(A9,""low"")"),"#N/A") -> #N/A | R9: =IFERROR(__xludf.DUMMYFUNCTION("abs(P9-Q9)/GOOGLEFINANCE(A9,""closeyest"")"),"#N/A") -> #N/A | S9: =D9/Y9-1 -> #N/A | T9: 15 | W9: =IF(ISERROR(if(or(AND(Q9<=T9,T9<=P9),AND(Q9<=U9, U9<=P9)),"TRADE ALERT","")),"DATA UNAVAILABLE",if(or(AND(Q9<=T9,T9<=P9),T9>P9,AND(Q9<=U9, U9<=P9)),"TRADE ALERT"&" - Price level hit for "&A9&" currently at "&D9&" "&B9,"")) -> DATA UNAVAILABLE | X9: =IFERROR(__xludf.DUMMYFUNCTION("GOOGLEFINANCE($A9,X$3)"),"#N/A") -> #N/A | Y9: =IFERROR(__xludf.DUMMYFUNCTION("GOOGLEFINANCE($A9,Y$3)"),"#N/A") -> #N/A | Z9: =IFERROR(__xludf.DUMMYFUNCTION("GOOGLEFINANCE($A9,Z$3)"),"#N/A") -> #N/A | AA9: =IFERROR(__xludf.DUMMYFUNCTION("GOOGLEFINANCE($A9,AA$3)"),"#N/A") -> #N/A | AB9: =IFERROR(__xludf.DUMMYFUNCTION("GOOGLEFINANCE($A9,AB$3)"),"#N/A") -> #N/A | AC9: =IFERROR(__xludf.DUMMYFUNCTION("GOOGLEFINANCE($A9,AC$3)"),"#N/A") -> #N/A | AD9: =IFERROR(__xludf.DUMMYFUNCTION("GOOGLEFINANCE($A9,AD$3)"),"#N/A") -> #N/A | AE9: =IFERROR(__xludf.DUMMYFUNCTION("GOOGLEFINANCE($A9,AE$3)"),"#N/A") -> #N/A
B10: =IFERROR(__xludf.DUMMYFUNCTION("GOOGLEFINANCE(A10,""name"")"),"#N/A") -> #N/A | D10: =IFERROR(__xludf.DUMMYFUNCTION("GOOGLEFINANCE(A10)"),"#N/A") -> #N/A | F10: =IF(M10="USD",E10/1.21,E10) -> #N/A | H10: =IFERROR(__xludf.DUMMYFUNCTION("if(isblank(A10)=TRUE,0,if(M10=""GBX"",F10*G10/100,IF(M10=""EUR"",F10*G10/GOOGLEFINANCE(""CURRENCY:GBPEUR""),F10*G10/GOOGLEFINANCE(""CURRENCY:GBPUSD""))))"),0.0) -> 0 | I10: =IFERROR(__xludf.DUMMYFUNCTION("if(isblank(A10)=TRUE,0,if(M10=""GBX"",D10*G10/100,IF(M10=""EUR"",D10*G10/GOOGLEFINANCE(""CURRENCY:GBPEUR""),D10*G10/GOOGLEFINANCE(""CURRENCY:GBPUSD""))))"),0.0) -> 0 | J10: =H10/$B$1 -> 0 | K10: =I10/H10-1 -> #DIV/0! | L10: =IFERROR(__xludf.DUMMYFUNCTION("SPARKLINE(GoogleFinance(A10, ""price"", TODAY()-30, TODAY()),{""color"",""blue"";""linewidth"",2}) "),"#N/A") -> #N/A | M10: =IFERROR(__xludf.DUMMYFUNCTION("GOOGLEFINANCE(A10,""currency"")"),"#N/A") -> #N/A | N10: =round(D10/AE10-1,4) -> #N/A | O10: =IFERROR(__xludf.DUMMYFUNCTION("GOOGLEFINANCE(A10,""Change"")"),"#N/A") -> #N/A | P10: =IFERROR(__xludf.DUMMYFUNCTION("GOOGLEFINANCE(A10,""High"")"),"#N/A") -> #N/A | Q10: =IFERROR(__xludf.DUMMYFUNCTION("GOOGLEFINANCE(A10,""low"")"),"#N/A") -> #N/A | R10: =IFERROR(__xludf.DUMMYFUNCTION("abs(P10-Q10)/GOOGLEFINANCE(A10,""closeyest"")"),"#N/A") -> #N/A | S10: =D10/Y10-1 -> #N/A | T10: 6 | W10: =IF(ISERROR(if(or(AND(Q10<=T10,T10<=P10),AND(Q10<=U10, U10<=P10)),"TRADE ALERT","")),"DATA UNAVAILABLE",if(or(AND(Q10<=T10,T10<=P10),T10>P10,AND(Q10<=U10, U10<=P10)),"TRADE ALERT"&" - Price level hit for "&A10&" currently at "&D10&" "&B10,"")) -> DATA UNAVAILABLE | X10: =IFERROR(__xludf.DUMMYFUNCTION("GOOGLEFINANCE($A10,X$3)"),"#N/A") -> #N/A | Y10: =IFERROR(__xludf.DUMMYFUNCTION("GOOGLEFINANCE($A10,Y$3)"),"#N/A") -> #N/A | Z10: =IFERROR(__xludf.DUMMYFUNCTION("GOOGLEFINANCE($A10,Z$3)"),"#N/A") -> #N/A | AA10: =IFERROR(__xludf.DUMMYFUNCTION("GOOGLEFINANCE($A10,AA$3)"),"#N/A") -> #N/A | AB10: =IFERROR(__xludf.DUMMYFUNCTION("GOOGLEFINANCE($A10,AB$3)"),"#N/A") -> #N/A | AC10: =IFERROR(__xludf.DUMMYFUNCTION("GOOGLEFINANCE($A10,AC$3)"),"#N/A") -> #N/A | AD10: =IFERROR(__xludf.DUMMYFUNCTION("GOOGLEFINANCE($A10,AD$3)"),"#N/A") -> #N/A | AE10: =IFERROR(__xludf.DUMMYFUNCTION("GOOGLEFINANCE($A10,AE$3)"),"#N/A") -> #N/A
B11: =IFERROR(__xludf.DUMMYFUNCTION("GOOGLEFINANCE(A11,""name"")"),"#N/A") -> #N/A | D11: =IFERROR(__xludf.DUMMYFUNCTION("GOOGLEFINANCE(A11)"),"#N/A") -> #N/A | F11: =IF(M11="USD",E11/1.21,E11) -> #N/A | H11: =IFERROR(__xludf.DUMMYFUNCTION("if(isblank(A11)=TRUE,0,if(M11=""GBX"",F11*G11/100,IF(M11=""EUR"",F11*G11/GOOGLEFINANCE(""CURRENCY:GBPEUR""),F11*G11/GOOGLEFINANCE(""CURRENCY:GBPUSD""))))"),0.0) -> 0 | I11: =IFERROR(__xludf.DUMMYFUNCTION("if(isblank(A11)=TRUE,0,if(M11=""GBX"",D11*G11/100,IF(M11=""EUR"",D11*G11/GOOGLEFINANCE(""CURRENCY:GBPEUR""),D11*G11/GOOGLEFINANCE(""CURRENCY:GBPUSD""))))"),0.0) -> 0 | J11: =H11/$B$1 -> 0 | K11: =I11/H11-1 -> #DIV/0! | L11: =IFERROR(__xludf.DUMMYFUNCTION("SPARKLINE(GoogleFinance(A11, ""price"", TODAY()-30, TODAY()),{""color"",""blue"";""linewidth"",2}) "),"#N/A") -> #N/A | M11: =IFERROR(__xludf.DUMMYFUNCTION("GOOGLEFINANCE(A11,""currency"")"),"#N/A") -> #N/A | N11: =round(D11/AE11-1,4) -> #N/A | O11: =IFERROR(__xludf.DUMMYFUNCTION("GOOGLEFINANCE(A11,""Change"")"),"#N/A") -> #N/A | P11: =IFERROR(__xludf.DUMMYFUNCTION("GOOGLEFINANCE(A11,""High"")"),"#N/A") -> #N/A | Q11: =IFERROR(__xludf.DUMMYFUNCTION("GOOGLEFINANCE(A11,""low"")"),"#N/A") -> #N/A | R11: =IFERROR(__xludf.DUMMYFUNCTION("abs(P11-Q11)/GOOGLEFINANCE(A11,""closeyest"")"),"#N/A") -> #N/A | S11: =D11/Y11-1 -> #N/A | T11: 36 | W11: =IF(ISERROR(if(or(AND(Q11<=T11,T11<=P11),AND(Q11<=U11, U11<=P11)),"TRADE ALERT","")),"DATA UNAVAILABLE",if(or(AND(Q11<=T11,T11<=P11),T11>P11,AND(Q11<=U11, U11<=P11)),"TRADE ALERT"&" - Price level hit for "&A11&" currently at "&D11&" "&B11,"")) -> DATA UNAVAILABLE | X11: =IFERROR(__xludf.DUMMYFUNCTION("GOOGLEFINANCE($A11,X$3)"),"#N/A") -> #N/A | Y11: =IFERROR(__xludf.DUMMYFUNCTION("GOOGLEFINANCE($A11,Y$3)"),"#N/A") -> #N/A | Z11: =IFERROR(__xludf.DUMMYFUNCTION("GOOGLEFINANCE($A11,Z$3)"),"#N/A") -> #N/A | AA11: =IFERROR(__xludf.DUMMYFUNCTION("GOOGLEFINANCE($A11,AA$3)"),"#N/A") -> #N/A | AB11: =IFERROR(__xludf.DUMMYFUNCTION("GOOGLEFINANCE($A11,AB$3)"),"#N/A") -> #N/A | AC11: =IFERROR(__xludf.DUMMYFUNCTION("GOOGLEFINANCE($A11,AC$3)"),"#N/A") -> #N/A | AD11: =IFERROR(__xludf.DUMMYFUNCTION("GOOGLEFINANCE($A11,AD$3)"),"#N/A") -> #N/A | AE11: =IFERROR(__xludf.DUMMYFUNCTION("GOOGLEFINANCE($A11,AE$3)"),"#N/A") -> #N/A
B12: =IFERROR(__xludf.DUMMYFUNCTION("GOOGLEFINANCE(A12,""name"")"),"#N/A") -> #N/A | D12: =IFERROR(__xludf.DUMMYFUNCTION("GOOGLEFINANCE(A12)"),"#N/A") -> #N/A | F12: =IF(M12="USD",E12/1.21,E12) -> #N/A | H12: =IFERROR(__xludf.DUMMYFUNCTION("if(isblank(A12)=TRUE,0,if(M12=""GBX"",F12*G12/100,IF(M12=""EUR"",F12*G12/GOOGLEFINANCE(""CURRENCY:GBPEUR""),F12*G12/GOOGLEFINANCE(""CURRENCY:GBPUSD""))))"),0.0) -> 0 | I12: =IFERROR(__xludf.DUMMYFUNCTION("if(isblank(A12)=TRUE,0,if(M12=""GBX"",D12*G12/100,IF(M12=""EUR"",D12*G12/GOOGLEFINANCE(""CURRENCY:GBPEUR""),D12*G12/GOOGLEFINANCE(""CURRENCY:GBPUSD""))))"),0.0) -> 0 | J12: =H12/$B$1 -> 0 | K12: =I12/H12-1 -> #DIV/0! | L12: =IFERROR(__xludf.DUMMYFUNCTION("SPARKLINE(GoogleFinance(A12, ""price"", TODAY()-30, TODAY()),{""color"",""blue"";""linewidth"",2}) "),"#N/A") -> #N/A | M12: =IFERROR(__xludf.DUMMYFUNCTION("GOOGLEFINANCE(A12,""currency"")"),"#N/A") -> #N/A | N12: =round(D12/AE12-1,4) -> #N/A | O12: =IFERROR(__xludf.DUMMYFUNCTION("GOOGLEFINANCE(A12,""Change"")"),"#N/A") -> #N/A | P12: =IFERROR(__xludf.DUMMYFUNCTION("GOOGLEFINANCE(A12,""High"")"),"#N/A") -> #N/A | Q12: =IFERROR(__xludf.DUMMYFUNCTION("GOOGLEFINANCE(A12,""low"")"),"#N/A") -> #N/A | R12: =IFERROR(__xludf.DUMMYFUNCTION("abs(P12-Q12)/GOOGLEFINANCE(A12,""closeyest"")"),"#N/A") -> #N/A | S12: =D12/Y12-1 -> #N/A | T12: 31.28 | W12: =IF(ISERROR(if(or(AND(Q12<=T12,T12<=P12),AND(Q12<=U12, U12<=P12)),"TRADE ALERT","")),"DATA UNAVAILABLE",if(or(AND(Q12<=T12,T12<=P12),T12>P12,AND(Q12<=U12, U12<=P12)),"TRADE ALERT"&" - Price level hit for "&A12&" currently at "&D12&" "&B12,"")) -> DATA UNAVAILABLE | X12: =IFERROR(__xludf.DUMMYFUNCTION("GOOGLEFINANCE($A12,X$3)"),"#N/A") -> #N/A | Y12: =IFERROR(__xludf.DUMMYFUNCTION("GOOGLEFINANCE($A12,Y$3)"),"#N/A") -> #N/A | Z12: =IFERROR(__xludf.DUMMYFUNCTION("GOOGLEFINANCE($A12,Z$3)"),"#N/A") -> #N/A | AA12: =IFERROR(__xludf.DUMMYFUNCTION("GOOGLEFINANCE($A12,AA$3)"),"#N/A") -> #N/A | AB12: =IFERROR(__xludf.DUMMYFUNCTION("GOOGLEFINANCE($A12,AB$3)"),"#N/A") -> #N/A | AC12: =IFERROR(__xludf.DUMMYFUNCTION("GOOGLEFINANCE($A12,AC$3)"),"#N/A") -> #N/A | AD12: =IFERROR(__xludf.DUMMYFUNCTION("GOOGLEFINANCE($A12,AD$3)"),"#N/A") -> #N/A | AE12: =IFERROR(__xludf.DUMMYFUNCTION("GOOGLEFINANCE($A12,AE$3)"),"#N/A") -> #N/A
B13: =IFERROR(__xludf.DUMMYFUNCTION("GOOGLEFINANCE(A13,""name"")"),"#N/A") -> #N/A | D13: =IFERROR(__xludf.DUMMYFUNCTION("GOOGLEFINANCE(A13)"),"#N/A") -> #N/A | F13: =IF(M13="USD",E13/1.21,E13) -> #N/A | H13: =IFERROR(__xludf.DUMMYFUNCTION("if(isblank(A13)=TRUE,0,if(M13=""GBX"",F13*G13/100,IF(M13=""EUR"",F13*G13/GOOGLEFINANCE(""CURRENCY:GBPEUR""),F13*G13/GOOGLEFINANCE(""CURRENCY:GBPUSD""))))"),0.0) -> 0 | I13: =IFERROR(__xludf.DUMMYFUNCTION("if(isblank(A13)=TRUE,0,if(M13=""GBX"",D13*G13/100,IF(M13=""EUR"",D13*G13/GOOGLEFINANCE(""CURRENCY:GBPEUR""),D13*G13/GOOGLEFINANCE(""CURRENCY:GBPUSD""))))"),0.0) -> 0 | J13: =H13/$B$1 -> 0 | K13: =I13/H13-1 -> #DIV/0! | L13: =IFERROR(__xludf.DUMMYFUNCTION("SPARKLINE(GoogleFinance(A13, ""price"", TODAY()-30, TODAY()),{""color"",""blue"";""linewidth"",2}) "),"#N/A") -> #N/A | M13: =IFERROR(__xludf.DUMMYFUNCTION("GOOGLEFINANCE(A13,""currency"")"),"#N/A") -> #N/A | N13: =round(D13/AE13-1,4) -> #N/A | O13: =IFERROR(__xludf.DUMMYFUNCTION("GOOGLEFINANCE(A13,""Change"")"),"#N/A") -> #N/A | P13: =IFERROR(__xludf.DUMMYFUNCTION("GOOGLEFINANCE(A13,""High"")"),"#N/A") -> #N/A | Q13: =IFERROR(__xludf.DUMMYFUNCTION("GOOGLEFINANCE(A13,""low"")"),"#N/A") -> #N/A | R13: =IFERROR(__xludf.DUMMYFUNCTION("abs(P13-Q13)/GOOGLEFINANCE(A13,""closeyest"")"),"#N/A") -> #N/A | S13: =D13/Y13-1 -> #N/A | T13: 1.39 | W13: =IF(ISERROR(if(or(AND(Q13<=T13,T13<=P13),AND(Q13<=U13, U13<=P13)),"TRADE ALERT","")),"DATA UNAVAILABLE",if(or(AND(Q13<=T13,T13<=P13),T13>P13,AND(Q13<=U13, U13<=P13)),"TRADE ALERT"&" - Price level hit for "&A13&" currently at "&D13&" "&B13,"")) -> DATA UNAVAILABLE | X13: =IFERROR(__xludf.DUMMYFUNCTION("GOOGLEFINANCE($A13,X$3)"),"#N/A") -> #N/A | Y13: =IFERROR(__xludf.DUMMYFUNCTION("GOOGLEFINANCE($A13,Y$3)"),"#N/A") -> #N/A | Z13: =IFERROR(__xludf.DUMMYFUNCTION("GOOGLEFINANCE($A13,Z$3)"),"#N/A") -> #N/A | AA13: =IFERROR(__xludf.DUMMYFUNCTION("GOOGLEFINANCE($A13,AA$3)"),"#N/A") -> #N/A | AB13: =IFERROR(__xludf.DUMMYFUNCTION("GOOGLEFINANCE($A13,AB$3)"),"#N/A") -> #N/A | AC13: =IFERROR(__xludf.DUMMYFUNCTION("GOOGLEFINANCE($A13,AC$3)"),"#N/A") -> #N/A | AD13: =IFERROR(__xludf.DUMMYFUNCTION("GOOGLEFINANCE($A13,AD$3)"),"#N/A") -> #N/A | AE13: =IFERROR(__xludf.DUMMYFUNCTION("GOOGLEFINANCE($A13,AE$3)"),"#N/A") -> #N/A
B14: =IFERROR(__xludf.DUMMYFUNCTION("GOOGLEFINANCE(A14,""name"")"),"#N/A") -> #N/A | D14: =IFERROR(__xludf.DUMMYFUNCTION("GOOGLEFINANCE(A14)"),"#N/A") -> #N/A | F14: =IF(M14="USD",E14/1.21,E14) -> #N/A | H14: =IFERROR(__xludf.DUMMYFUNCTION("if(isblank(A14)=TRUE,0,if(M14=""GBX"",F14*G14/100,IF(M14=""EUR"",F14*G14/GOOGLEFINANCE(""CURRENCY:GBPEUR""),F14*G14/GOOGLEFINANCE(""CURRENCY:GBPUSD""))))"),0.0) -> 0 | I14: =IFERROR(__xludf.DUMMYFUNCTION("if(isblank(A14)=TRUE,0,if(M14=""GBX"",D14*G14/100,IF(M14=""EUR"",D14*G14/GOOGLEFINANCE(""CURRENCY:GBPEUR""),D14*G14/GOOGLEFINANCE(""CURRENCY:GBPUSD""))))"),0.0) -> 0 | J14: =H14/$B$1 -> 0 | K14: =I14/H14-1 -> #DIV/0! | L14: =IFERROR(__xludf.DUMMYFUNCTION("SPARKLINE(GoogleFinance(A14, ""price"", TODAY()-30, TODAY()),{""color"",""blue"";""linewidth"",2}) "),"#N/A") -> #N/A | M14: =IFERROR(__xludf.DUMMYFUNCTION("GOOGLEFINANCE(A14,""currency"")"),"#N/A") -> #N/A | N14: =round(D14/AE14-1,4) -> #N/A | O14: =IFERROR(__xludf.DUMMYFUNCTION("GOOGLEFINANCE(A14,""Change"")"),"#N/A") -> #N/A | P14: =IFERROR(__xludf.DUMMYFUNCTION("GOOGLEFINANCE(A14,""High"")"),"#N/A") -> #N/A | Q14: =IFERROR(__xludf.DUMMYFUNCTION("GOOGLEFINANCE(A14,""low"")"),"#N/A") -> #N/A | R14: =IFERROR(__xludf.DUMMYFUNCTION("abs(P14-Q14)/GOOGLEFINANCE(A14,""closeyest"")"),"#N/A") -> #N/A | S14: =D14/Y14-1 -> #N/A | T14: 380 | W14: =IF(ISERROR(if(or(AND(Q14<=T14,T14<=P14),AND(Q14<=U14, U14<=P14)),"TRADE ALERT","")),"DATA UNAVAILABLE",if(or(AND(Q14<=T14,T14<=P14),T14>P14,AND(Q14<=U14, U14<=P14)),"TRADE ALERT"&" - Price level hit for "&A14&" currently at "&D14&" "&B14,"")) -> DATA UNAVAILABLE | X14: =IFERROR(__xludf.DUMMYFUNCTION("GOOGLEFINANCE($A14,X$3)"),"#N/A") -> #N/A | Y14: =IFERROR(__xludf.DUMMYFUNCTION("GOOGLEFINANCE($A14,Y$3)"),"#N/A") -> #N/A | Z14: =IFERROR(__xludf.DUMMYFUNCTION("GOOGLEFINANCE($A14,Z$3)"),"#N/A") -> #N/A | AA14: =IFERROR(__xludf.DUMMYFUNCTION("GOOGLEFINANCE($A14,AA$3)"),"#N/A") -> #N/A | AB14: =IFERROR(__xludf.DUMMYFUNCTION("GOOGLEFINANCE($A14,AB$3)"),"#N/A") -> #N/A | AC14: =IFERROR(__xludf.DUMMYFUNCTION("GOOGLEFINANCE($A14,AC$3)"),"#N/A") -> #N/A | AD14: =IFERROR(__xludf.DUMMYFUNCTION("GOOGLEFINANCE($A14,AD$3)"),"#N/A") -> #N/A | AE14: =IFERROR(__xludf.DUMMYFUNCTION("GOOGLEFINANCE($A14,AE$3)"),"#N/A") -> #N/A
B15: =IFERROR(__xludf.DUMMYFUNCTION("GOOGLEFINANCE(A15,""name"")"),"#N/A") -> #N/A | D15: =IFERROR(__xludf.DUMMYFUNCTION("GOOGLEFINANCE(A15)"),"#N/A") -> #N/A | F15: =IF(M15="USD",E15/1.21,E15) -> #N/A | H15: =IFERROR(__xludf.DUMMYFUNCTION("if(isblank(A15)=TRUE,0,if(M15=""GBX"",F15*G15/100,IF(M15=""EUR"",F15*G15/GOOGLEFINANCE(""CURRENCY:GBPEUR""),F15*G15/GOOGLEFINANCE(""CURRENCY:GBPUSD""))))"),0.0) -> 0 | I15: =IFERROR(__xludf.DUMMYFUNCTION("if(isblank(A15)=TRUE,0,if(M15=""GBX"",D15*G15/100,IF(M15=""EUR"",D15*G15/GOOGLEFINANCE(""CURRENCY:GBPEUR""),D15*G15/GOOGLEFINANCE(""CURRENCY:GBPUSD""))))"),0.0) -> 0 | J15: =H15/$B$1 -> 0 | K15: =I15/H15-1 -> #DIV/0! | L15: =IFERROR(__xludf.DUMMYFUNCTION("SPARKLINE(GoogleFinance(A15, ""price"", TODAY()-30, TODAY()),{""color"",""blue"";""linewidth"",2}) "),"#N/A") -> #N/A | M15: =IFERROR(__xludf.DUMMYFUNCTION("GOOGLEFINANCE(A15,""currency"")"),"#N/A") -> #N/A | N15: =round(D15/AE15-1,4) -> #N/A | O15: =IFERROR(__xludf.DUMMYFUNCTION("GOOGLEFINANCE(A15,""Change"")"),"#N/A") -> #N/A | P15: =IFERROR(__xludf.DUMMYFUNCTION("GOOGLEFINANCE(A15,""High"")"),"#N/A") -> #N/A | Q15: =IFERROR(__xludf.DUMMYFUNCTION("GOOGLEFINANCE(A15,""low"")"),"#N/A") -> #N/A | R15: =IFERROR(__xludf.DUMMYFUNCTION("abs(P15-Q15)/GOOGLEFINANCE(A15,""closeyest"")"),"#N/A") -> #N/A | S15: =D15/Y15-1 -> #N/A | W15: =IF(ISERROR(if(or(AND(Q15<=T15,T15<=P15),AND(Q15<=U15, U15<=P15)),"TRADE ALERT","")),"DATA UNAVAILABLE",if(or(AND(Q15<=T15,T15<=P15),T15>P15,AND(Q15<=U15, U15<=P15)),"TRADE ALERT"&" - Price level hit for "&A15&" currently at "&D15&" "&B15,"")) -> DATA UNAVAILABLE | X15: =IFERROR(__xludf.DUMMYFUNCTION("GOOGLEFINANCE($A15,X$3)"),"#N/A") -> #N/A | Y15: =IFERROR(__xludf.DUMMYFUNCTION("GOOGLEFINANCE($A15,Y$3)"),"#N/A") -> #N/A | Z15: =IFERROR(__xludf.DUMMYFUNCTION("GOOGLEFINANCE($A15,Z$3)"),"#N/A") -> #N/A | AA15: =IFERROR(__xludf.DUMMYFUNCTION("GOOGLEFINANCE($A15,AA$3)"),"#N/A") -> #N/A | AB15: =IFERROR(__xludf.DUMMYFUNCTION("GOOGLEFINANCE($A15,AB$3)"),"#N/A") -> #N/A | AC15: =IFERROR(__xludf.DUMMYFUNCTION("GOOGLEFINANCE($A15,AC$3)"),"#N/A") -> #N/A | AD15: =IFERROR(__xludf.DUMMYFUNCTION("GOOGLEFINANCE($A15,AD$3)"),"#N/A") -> #N/A | AE15: =IFERROR(__xludf.DUMMYFUNCTION("GOOGLEFINANCE($A15,AE$3)"),"#N/A") -> #N/A
B16: =IFERROR(__xludf.DUMMYFUNCTION("GOOGLEFINANCE(A16,""name"")"),"#N/A") -> #N/A | D16: =IFERROR(__xludf.DUMMYFUNCTION("GOOGLEFINANCE(A16)"),"#N/A") -> #N/A | F16: =IF(M16="USD",E16/1.21,E16) -> #N/A | H16: =IFERROR(__xludf.DUMMYFUNCTION("if(isblank(A16)=TRUE,0,if(M16=""GBX"",F16*G16/100,IF(M16=""EUR"",F16*G16/GOOGLEFINANCE(""CURRENCY:GBPEUR""),F16*G16/GOOGLEFINANCE(""CURRENCY:GBPUSD""))))"),0.0) -> 0 | I16: =IFERROR(__xludf.DUMMYFUNCTION("if(isblank(A16)=TRUE,0,if(M16=""GBX"",D16*G16/100,IF(M16=""EUR"",D16*G16/GOOGLEFINANCE(""CURRENCY:GBPEUR""),D16*G16/GOOGLEFINANCE(""CURRENCY:GBPUSD""))))"),0.0) -> 0 | J16: =H16/$B$1 -> 0 | K16: =I16/H16-1 -> #DIV/0! | L16: =IFERROR(__xludf.DUMMYFUNCTION("SPARKLINE(GoogleFinance(A16, ""price"", TODAY()-30, TODAY()),{""color"",""blue"";""linewidth"",2}) "),"#N/A") -> #N/A | M16: =IFERROR(__xludf.DUMMYFUNCTION("GOOGLEFINANCE(A16,""currency"")"),"#N/A") -> #N/A | N16: =round(D16/AE16-1,4) -> #N/A | O16: =IFERROR(__xludf.DUMMYFUNCTION("GOOGLEFINANCE(A16,""Change"")"),"#N/A") -> #N/A | P16: =IFERROR(__xludf.DUMMYFUNCTION("GOOGLEFINANCE(A16,""High"")"),"#N/A") -> #N/A | Q16: =IFERROR(__xludf.DUMMYFUNCTION("GOOGLEFINANCE(A16,""low"")"),"#N/A") -> #N/A | R16: =IFERROR(__xludf.DUMMYFUNCTION("abs(P16-Q16)/GOOGLEFINANCE(A16,""closeyest"")"),"#N/A") -> #N/A | S16: =D16/Y16-1 -> #N/A | W16: =IF(ISERROR(if(or(AND(Q16<=T16,T16<=P16),AND(Q16<=U16, U16<=P16)),"TRADE ALERT","")),"DATA UNAVAILABLE",if(or(AND(Q16<=T16,T16<=P16),T16>P16,AND(Q16<=U16, U16<=P16)),"TRADE ALERT"&" - Price level hit for "&A16&" currently at "&D16&" "&B16,"")) -> DATA UNAVAILABLE | X16: =IFERROR(__xludf.DUMMYFUNCTION("GOOGLEFINANCE($A16,X$3)"),"#N/A") -> #N/A | Y16: =IFERROR(__xludf.DUMMYFUNCTION("GOOGLEFINANCE($A16,Y$3)"),"#N/A") -> #N/A | Z16: =IFERROR(__xludf.DUMMYFUNCTION("GOOGLEFINANCE($A16,Z$3)"),"#N/A") -> #N/A | AA16: =IFERROR(__xludf.DUMMYFUNCTION("GOOGLEFINANCE($A16,AA$3)"),"#N/A") -> #N/A | AB16: =IFERROR(__xludf.DUMMYFUNCTION("GOOGLEFINANCE($A16,AB$3)"),"#N/A") -> #N/A | AC16: =IFERROR(__xludf.DUMMYFUNCTION("GOOGLEFINANCE($A16,AC$3)"),"#N/A") -> #N/A | AD16: =IFERROR(__xludf.DUMMYFUNCTION("GOOGLEFINANCE($A16,AD$3)"),"#N/A") -> #N/A | AE16: =IFERROR(__xludf.DUMMYFUNCTION("GOOGLEFINANCE($A16,AE$3)"),"#N/A") -> #N/A
B17: =IFERROR(__xludf.DUMMYFUNCTION("GOOGLEFINANCE(A17,""name"")"),"#N/A") -> #N/A | D17: =IFERROR(__xludf.DUMMYFUNCTION("GOOGLEFINANCE(A17)"),"#N/A") -> #N/A | F17: =IF(M17="USD",E17/1.21,E17) -> #N/A | H17: =IFERROR(__xludf.DUMMYFUNCTION("if(isblank(A17)=TRUE,0,if(M17=""GBX"",F17*G17/100,IF(M17=""EUR"",F17*G17/GOOGLEFINANCE(""CURRENCY:GBPEUR""),F17*G17/GOOGLEFINANCE(""CURRENCY:GBPUSD""))))"),0.0) -> 0 | I17: =IFERROR(__xludf.DUMMYFUNCTION("if(isblank(A17)=TRUE,0,if(M17=""GBX"",D17*G17/100,IF(M17=""EUR"",D17*G17/GOOGLEFINANCE(""CURRENCY:GBPEUR""),D17*G17/GOOGLEFINANCE(""CURRENCY:GBPUSD""))))"),0.0) -> 0 | J17: =H17/$B$1 -> 0 | K17: =I17/H17-1 -> #DIV/0! | L17: =IFERROR(__xludf.DUMMYFUNCTION("SPARKLINE(GoogleFinance(A17, ""price"", TODAY()-30, TODAY()),{""color"",""blue"";""linewidth"",2}) "),"#N/A") -> #N/A | M17: =IFERROR(__xludf.DUMMYFUNCTION("GOOGLEFINANCE(A17,""currency"")"),"#N/A") -> #N/A | N17: =round(D17/AE17-1,4) -> #N/A | O17: =IFERROR(__xludf.DUMMYFUNCTION("GOOGLEFINANCE(A17,""Change"")"),"#N/A") -> #N/A | P17: =IFERROR(__xludf.DUMMYFUNCTION("GOOGLEFINANCE(A17,""High"")"),"#N/A") -> #N/A | Q17: =IFERROR(__xludf.DUMMYFUNCTION("GOOGLEFINANCE(A17,""low"")"),"#N/A") -> #N/A | R17: =IFERROR(__xludf.DUMMYFUNCTION("abs(P17-Q17)/GOOGLEFINANCE(A17,""closeyest"")"),"#N/A") -> #N/A | S17: =D17/Y17-1 -> #N/A | W17: =IF(ISERROR(if(or(AND(Q17<=T17,T17<=P17),AND(Q17<=U17, U17<=P17)),"TRADE ALERT","")),"DATA UNAVAILABLE",if(or(AND(Q17<=T17,T17<=P17),T17>P17,AND(Q17<=U17, U17<=P17)),"TRADE ALERT"&" - Price level hit for "&A17&" currently at "&D17&" "&B17,"")) -> DATA UNAVAILABLE | X17: =IFERROR(__xludf.DUMMYFUNCTION("GOOGLEFINANCE($A17,X$3)"),"#N/A") -> #N/A | Y17: =IFERROR(__xludf.DUMMYFUNCTION("GOOGLEFINANCE($A17,Y$3)"),"#N/A") -> #N/A | Z17: =IFERROR(__xludf.DUMMYFUNCTION("GOOGLEFINANCE($A17,Z$3)"),"#N/A") -> #N/A | AA17: =IFERROR(__xludf.DUMMYFUNCTION("GOOGLEFINANCE($A17,AA$3)"),"#N/A") -> #N/A | AB17: =IFERROR(__xludf.DUMMYFUNCTION("GOOGLEFINANCE($A17,AB$3)"),"#N/A") -> #N/A | AC17: =IFERROR(__xludf.DUMMYFUNCTION("GOOGLEFINANCE($A17,AC$3)"),"#N/A") -> #N/A | AD17: =IFERROR(__xludf.DUMMYFUNCTION("GOOGLEFINANCE($A17,AD$3)"),"#N/A") -> #N/A | AE17: =IFERROR(__xludf.DUMMYFUNCTION("GOOGLEFINANCE($A17,AE$3)"),"#N/A") -> #N/A
B18: =IFERROR(__xludf.DUMMYFUNCTION("GOOGLEFINANCE(A18,""name"")"),"#N/A") -> #N/A | D18: =IFERROR(__xludf.DUMMYFUNCTION("GOOGLEFINANCE(A18)"),"#N/A") -> #N/A | F18: =IF(M18="USD",E18/1.21,E18) -> #N/A | H18: =IFERROR(__xludf.DUMMYFUNCTION("if(isblank(A18)=TRUE,0,if(M18=""GBX"",F18*G18/100,IF(M18=""EUR"",F18*G18/GOOGLEFINANCE(""CURRENCY:GBPEUR""),F18*G18/GOOGLEFINANCE(""CURRENCY:GBPUSD""))))"),0.0) -> 0 | I18: =IFERROR(__xludf.DUMMYFUNCTION("if(isblank(A18)=TRUE,0,if(M18=""GBX"",D18*G18/100,IF(M18=""EUR"",D18*G18/GOOGLEFINANCE(""CURRENCY:GBPEUR""),D18*G18/GOOGLEFINANCE(""CURRENCY:GBPUSD""))))"),0.0) -> 0 | J18: =H18/$B$1 -> 0 | K18: =I18/H18-1 -> #DIV/0! | L18: =IFERROR(__xludf.DUMMYFUNCTION("SPARKLINE(GoogleFinance(A18, ""price"", TODAY()-30, TODAY()),{""color"",""blue"";""linewidth"",2}) "),"#N/A") -> #N/A | M18: =IFERROR(__xludf.DUMMYFUNCTION("GOOGLEFINANCE(A18,""currency"")"),"#N/A") -> #N/A | N18: =round(D18/AE18-1,4) -> #N/A | O18: =IFERROR(__xludf.DUMMYFUNCTION("GOOGLEFINANCE(A18,""Change"")"),"#N/A") -> #N/A | P18: =IFERROR(__xludf.DUMMYFUNCTION("GOOGLEFINANCE(A18,""High"")"),"#N/A") -> #N/A | Q18: =IFERROR(__xludf.DUMMYFUNCTION("GOOGLEFINANCE(A18,""low"")"),"#N/A") -> #N/A | R18: =IFERROR(__xludf.DUMMYFUNCTION("abs(P18-Q18)/GOOGLEFINANCE(A18,""closeyest"")"),"#N/A") -> #N/A | S18: =D18/Y18-1 -> #N/A | W18: =IF(ISERROR(if(or(AND(Q18<=T18,T18<=P18),AND(Q18<=U18, U18<=P18)),"TRADE ALERT","")),"DATA UNAVAILABLE",if(or(AND(Q18<=T18,T18<=P18),T18>P18,AND(Q18<=U18, U18<=P18)),"TRADE ALERT"&" - Price level hit for "&A18&" currently at "&D18&" "&B18,"")) -> DATA UNAVAILABLE | X18: =IFERROR(__xludf.DUMMYFUNCTION("GOOGLEFINANCE($A18,X$3)"),"#N/A") -> #N/A | Y18: =IFERROR(__xludf.DUMMYFUNCTION("GOOGLEFINANCE($A18,Y$3)"),"#N/A") -> #N/A | Z18: =IFERROR(__xludf.DUMMYFUNCTION("GOOGLEFINANCE($A18,Z$3)"),"#N/A") -> #N/A | AA18: =IFERROR(__xludf.DUMMYFUNCTION("GOOGLEFINANCE($A18,AA$3)"),"#N/A") -> #N/A | AB18: =IFERROR(__xludf.DUMMYFUNCTION("GOOGLEFINANCE($A18,AB$3)"),"#N/A") -> #N/A | AC18: =IFERROR(__xludf.DUMMYFUNCTION("GOOGLEFINANCE($A18,AC$3)"),"#N/A") -> #N/A | AD18: =IFERROR(__xludf.DUMMYFUNCTION("GOOGLEFINANCE($A18,AD$3)"),"#N/A") -> #N/A | AE18: =IFERROR(__xludf.DUMMYFUNCTION("GOOGLEFINANCE($A18,AE$3)"),"#N/A") -> #N/A
B19: =IFERROR(__xludf.DUMMYFUNCTION("GOOGLEFINANCE(A19,""name"")"),"#N/A") -> #N/A | D19: =IFERROR(__xludf.DUMMYFUNCTION("GOOGLEFINANCE(A19)"),"#N/A") -> #N/A | F19: =IF(M19="USD",E19/1.21,E19) -> #N/A | H19: =IFERROR(__xludf.DUMMYFUNCTION("if(isblank(A19)=TRUE,0,if(M19=""GBX"",F19*G19/100,IF(M19=""EUR"",F19*G19/GOOGLEFINANCE(""CURRENCY:GBPEUR""),F19*G19/GOOGLEFINANCE(""CURRENCY:GBPUSD""))))"),0.0) -> 0 | I19: =IFERROR(__xludf.DUMMYFUNCTION("if(isblank(A19)=TRUE,0,if(M19=""GBX"",D19*G19/100,IF(M19=""EUR"",D19*G19/GOOGLEFINANCE(""CURRENCY:GBPEUR""),D19*G19/GOOGLEFINANCE(""CURRENCY:GBPUSD""))))"),0.0) -> 0 | J19: =H19/$B$1 -> 0 | K19: =I19/H19-1 -> #DIV/0! | L19: =IFERROR(__xludf.DUMMYFUNCTION("SPARKLINE(GoogleFinance(A19, ""price"", TODAY()-30, TODAY()),{""color"",""blue"";""linewidth"",2}) "),"#N/A") -> #N/A | M19: =IFERROR(__xludf.DUMMYFUNCTION("GOOGLEFINANCE(A19,""currency"")"),"#N/A") -> #N/A | N19: =round(D19/AE19-1,4) -> #N/A | O19: =IFERROR(__xludf.DUMMYFUNCTION("GOOGLEFINANCE(A19,""Change"")"),"#N/A") -> #N/A | P19: =IFERROR(__xludf.DUMMYFUNCTION("GOOGLEFINANCE(A19,""High"")"),"#N/A") -> #N/A | Q19: =IFERROR(__xludf.DUMMYFUNCTION("GOOGLEFINANCE(A19,""low"")"),"#N/A") -> #N/A | R19: =IFERROR(__xludf.DUMMYFUNCTION("abs(P19-Q19)/GOOGLEFINANCE(A19,""closeyest"")"),"#N/A") -> #N/A | S19: =D19/Y19-1 -> #N/A | W19: =IF(ISERROR(if(or(AND(Q19<=T19,T19<=P19),AND(Q19<=U19, U19<=P19)),"TRADE ALERT","")),"DATA UNAVAILABLE",if(or(AND(Q19<=T19,T19<=P19),T19>P19,AND(Q19<=U19, U19<=P19)),"TRADE ALERT"&" - Price level hit for "&A19&" currently at "&D19&" "&B19,"")) -> DATA UNAVAILABLE | X19: =IFERROR(__xludf.DUMMYFUNCTION("GOOGLEFINANCE($A19,X$3)"),"#N/A") -> #N/A | Y19: =IFERROR(__xludf.DUMMYFUNCTION("GOOGLEFINANCE($A19,Y$3)"),"#N/A") -> #N/A | Z19: =IFERROR(__xludf.DUMMYFUNCTION("GOOGLEFINANCE($A19,Z$3)"),"#N/A") -> #N/A | AA19: =IFERROR(__xludf.DUMMYFUNCTION("GOOGLEFINANCE($A19,AA$3)"),"#N/A") -> #N/A | AB19: =IFERROR(__xludf.DUMMYFUNCTION("GOOGLEFINANCE($A19,AB$3)"),"#N/A") -> #N/A | AC19: =IFERROR(__xludf.DUMMYFUNCTION("GOOGLEFINANCE($A19,AC$3)"),"#N/A") -> #N/A | AD19: =IFERROR(__xludf.DUMMYFUNCTION("GOOGLEFINANCE($A19,AD$3)"),"#N/A") -> #N/A | AE19: =IFERROR(__xludf.DUMMYFUNCTION("GOOGLEFINANCE($A19,AE$3)"),"#N/A") -> #N/A
B20: =IFERROR(__xludf.DUMMYFUNCTION("GOOGLEFINANCE(A20,""name"")"),"#N/A") -> #N/A | D20: =IFERROR(__xludf.DUMMYFUNCTION("GOOGLEFINANCE(A20)"),"#N/A") -> #N/A | F20: =IF(M20="USD",E20/1.21,E20) -> #N/A | H20: =IFERROR(__xludf.DUMMYFUNCTION("if(isblank(A20)=TRUE,0,if(M20=""GBX"",F20*G20/100,IF(M20=""EUR"",F20*G20/GOOGLEFINANCE(""CURRENCY:GBPEUR""),F20*G20/GOOGLEFINANCE(""CURRENCY:GBPUSD""))))"),0.0) -> 0 | I20: =IFERROR(__xludf.DUMMYFUNCTION("if(isblank(A20)=TRUE,0,if(M20=""GBX"",D20*G20/100,IF(M20=""EUR"",D20*G20/GOOGLEFINANCE(""CURRENCY:GBPEUR""),D20*G20/GOOGLEFINANCE(""CURRENCY:GBPUSD""))))"),0.0) -> 0 | J20: =H20/$B$1 -> 0 | K20: =I20/H20-1 -> #DIV/0! | L20: =IFERROR(__xludf.DUMMYFUNCTION("SPARKLINE(GoogleFinance(A20, ""price"", TODAY()-30, TODAY()),{""color"",""blue"";""linewidth"",2}) "),"#N/A") -> #N/A | M20: =IFERROR(__xludf.DUMMYFUNCTION("GOOGLEFINANCE(A20,""currency"")"),"#N/A") -> #N/A | N20: =round(D20/AE20-1,4) -> #N/A | O20: =IFERROR(__xludf.DUMMYFUNCTION("GOOGLEFINANCE(A20,""Change"")"),"#N/A") -> #N/A | P20: =IFERROR(__xludf.DUMMYFUNCTION("GOOGLEFINANCE(A20,""High"")"),"#N/A") -> #N/A | Q20: =IFERROR(__xludf.DUMMYFUNCTION("GOOGLEFINANCE(A20,""low"")"),"#N/A") -> #N/A | R20: =IFERROR(__xludf.DUMMYFUNCTION("abs(P20-Q20)/GOOGLEFINANCE(A20,""closeyest"")"),"#N/A") -> #N/A | S20: =D20/Y20-1 -> #N/A | W20: =IF(ISERROR(if(or(AND(Q20<=T20,T20<=P20),AND(Q20<=U20, U20<=P20)),"TRADE ALERT","")),"DATA UNAVAILABLE",if(or(AND(Q20<=T20,T20<=P20),T20>P20,AND(Q20<=U20, U20<=P20)),"TRADE ALERT"&" - Price level hit for "&A20&" currently at "&D20&" "&B20,"")) -> DATA UNAVAILABLE | X20: =IFERROR(__xludf.DUMMYFUNCTION("GOOGLEFINANCE($A20,X$3)"),"#N/A") -> #N/A | Y20: =IFERROR(__xludf.DUMMYFUNCTION("GOOGLEFINANCE($A20,Y$3)"),"#N/A") -> #N/A | Z20: =IFERROR(__xludf.DUMMYFUNCTION("GOOGLEFINANCE($A20,Z$3)"),"#N/A") -> #N/A | AA20: =IFERROR(__xludf.DUMMYFUNCTION("GOOGLEFINANCE($A20,AA$3)"),"#N/A") -> #N/A | AB20: =IFERROR(__xludf.DUMMYFUNCTION("GOOGLEFINANCE($A20,AB$3)"),"#N/A") -> #N/A | AC20: =IFERROR(__xludf.DUMMYFUNCTION("GOOGLEFINANCE($A20,AC$3)"),"#N/A") -> #N/A | AD20: =IFERROR(__xludf.DUMMYFUNCTION("GOOGLEFINANCE($A20,AD$3)"),"#N/A") -> #N/A | AE20: =IFERROR(__xludf.DUMMYFUNCTION("GOOGLEFINANCE($A20,AE$3)"),"#N/A") -> #N/A
B21: =IFERROR(__xludf.DUMMYFUNCTION("GOOGLEFINANCE(A21,""name"")"),"#N/A") -> #N/A | D21: =IFERROR(__xludf.DUMMYFUNCTION("GOOGLEFINANCE(A21)"),"#N/A") -> #N/A | F21: =IF(M21="USD",E21/1.21,E21) -> #N/A | H21: =IFERROR(__xludf.DUMMYFUNCTION("if(isblank(A21)=TRUE,0,if(M21=""GBX"",F21*G21/100,IF(M21=""EUR"",F21*G21/GOOGLEFINANCE(""CURRENCY:GBPEUR""),F21*G21/GOOGLEFINANCE(""CURRENCY:GBPUSD""))))"),0.0) -> 0 | I21: =IFERROR(__xludf.DUMMYFUNCTION("if(isblank(A21)=TRUE,0,if(M21=""GBX"",D21*G21/100,IF(M21=""EUR"",D21*G21/GOOGLEFINANCE(""CURRENCY:GBPEUR""),D21*G21/GOOGLEFINANCE(""CURRENCY:GBPUSD""))))"),0.0) -> 0 | J21: =H21/$B$1 -> 0 | K21: =I21/H21-1 -> #DIV/0! | L21: =IFERROR(__xludf.DUMMYFUNCTION("SPARKLINE(GoogleFinance(A21, ""price"", TODAY()-30, TODAY()),{""color"",""blue"";""linewidth"",2}) "),"#N/A") -> #N/A | M21: =IFERROR(__xludf.DUMMYFUNCTION("GOOGLEFINANCE(A21,""currency"")"),"#N/A") -> #N/A | N21: =round(D21/AE21-1,4) -> #N/A | O21: =IFERROR(__xludf.DUMMYFUNCTION("GOOGLEFINANCE(A21,""Change"")"),"#N/A") -> #N/A | P21: =IFERROR(__xludf.DUMMYFUNCTION("GOOGLEFINANCE(A21,""High"")"),"#N/A") -> #N/A | Q21: =IFERROR(__xludf.DUMMYFUNCTION("GOOGLEFINANCE(A21,""low"")"),"#N/A") -> #N/A | R21: =IFERROR(__xludf.DUMMYFUNCTION("abs(P21-Q21)/GOOGLEFINANCE(A21,""closeyest"")"),"#N/A") -> #N/A | S21: =D21/Y21-1 -> #N/A | W21: =IF(ISERROR(if(or(AND(Q21<=T21,T21<=P21),AND(Q21<=U21, U21<=P21)),"TRADE ALERT","")),"DATA UNAVAILABLE",if(or(AND(Q21<=T21,T21<=P21),T21>P21,AND(Q21<=U21, U21<=P21)),"TRADE ALERT"&" - Price level hit for "&A21&" currently at "&D21&" "&B21,"")) -> DATA UNAVAILABLE | X21: =IFERROR(__xludf.DUMMYFUNCTION("GOOGLEFINANCE($A21,X$3)"),"#N/A") -> #N/A | Y21: =IFERROR(__xludf.DUMMYFUNCTION("GOOGLEFINANCE($A21,Y$3)"),"#N/A") -> #N/A | Z21: =IFERROR(__xludf.DUMMYFUNCTION("GOOGLEFINANCE($A21,Z$3)"),"#N/A") -> #N/A | AA21: =IFERROR(__xludf.DUMMYFUNCTION("GOOGLEFINANCE($A21,AA$3)"),"#N/A") -> #N/A | AB21: =IFERROR(__xludf.DUMMYFUNCTION("GOOGLEFINANCE($A21,AB$3)"),"#N/A") -> #N/A | AC21: =IFERROR(__xludf.DUMMYFUNCTION("GOOGLEFINANCE($A21,AC$3)"),"#N/A") -> #N/A | AD21: =IFERROR(__xludf.DUMMYFUNCTION("GOOGLEFINANCE($A21,AD$3)"),"#N/A") -> #N/A | AE21: =IFERROR(__xludf.DUMMYFUNCTION("GOOGLEFINANCE($A21,AE$3)"),"#N/A") -> #N/A
B22: =IFERROR(__xludf.DUMMYFUNCTION("GOOGLEFINANCE(A22,""name"")"),"#N/A") -> #N/A | D22: =IFERROR(__xludf.DUMMYFUNCTION("GOOGLEFINANCE(A22)"),"#N/A") -> #N/A | F22: =IF(M22="USD",E22/1.21,E22) -> #N/A | H22: =IFERROR(__xludf.DUMMYFUNCTION("if(isblank(A22)=TRUE,0,if(M22=""GBX"",F22*G22/100,IF(M22=""EUR"",F22*G22/GOOGLEFINANCE(""CURRENCY:GBPEUR""),F22*G22/GOOGLEFINANCE(""CURRENCY:GBPUSD""))))"),0.0) -> 0 | I22: =IFERROR(__xludf.DUMMYFUNCTION("if(isblank(A22)=TRUE,0,if(M22=""GBX"",D22*G22/100,IF(M22=""EUR"",D22*G22/GOOGLEFINANCE(""CURRENCY:GBPEUR""),D22*G22/GOOGLEFINANCE(""CURRENCY:GBPUSD""))))"),0.0) -> 0 | J22: =H22/$B$1 -> 0 | K22: =I22/H22-1 -> #DIV/0! | L22: =IFERROR(__xludf.DUMMYFUNCTION("SPARKLINE(GoogleFinance(A22, ""price"", TODAY()-30, TODAY()),{""color"",""blue"";""linewidth"",2}) "),"#N/A") -> #N/A | M22: =IFERROR(__xludf.DUMMYFUNCTION("GOOGLEFINANCE(A22,""currency"")"),"#N/A") -> #N/A | N22: =round(D22/AE22-1,4) -> #N/A | O22: =IFERROR(__xludf.DUMMYFUNCTION("GOOGLEFINANCE(A22,""Change"")"),"#N/A") -> #N/A | P22: =IFERROR(__xludf.DUMMYFUNCTION("GOOGLEFINANCE(A22,""High"")"),"#N/A") -> #N/A | Q22: =IFERROR(__xludf.DUMMYFUNCTION("GOOGLEFINANCE(A22,""low"")"),"#N/A") -> #N/A | R22: =IFERROR(__xludf.DUMMYFUNCTION("abs(P22-Q22)/GOOGLEFINANCE(A22,""closeyest"")"),"#N/A") -> #N/A | S22: =D22/Y22-1 -> #N/A | W22: =IF(ISERROR(if(or(AND(Q22<=T22,T22<=P22),AND(Q22<=U22, U22<=P22)),"TRADE ALERT","")),"DATA UNAVAILABLE",if(or(AND(Q22<=T22,T22<=P22),T22>P22,AND(Q22<=U22, U22<=P22)),"TRADE ALERT"&" - Price level hit for "&A22&" currently at "&D22&" "&B22,"")) -> DATA UNAVAILABLE | X22: =IFERROR(__xludf.DUMMYFUNCTION("GOOGLEFINANCE($A22,X$3)"),"#N/A") -> #N/A | Y22: =IFERROR(__xludf.DUMMYFUNCTION("GOOGLEFINANCE($A22,Y$3)"),"#N/A") -> #N/A | Z22: =IFERROR(__xludf.DUMMYFUNCTION("GOOGLEFINANCE($A22,Z$3)"),"#N/A") -> #N/A | AA22: =IFERROR(__xludf.DUMMYFUNCTION("GOOGLEFINANCE($A22,AA$3)"),"#N/A") -> #N/A | AB22: =IFERROR(__xludf.DUMMYFUNCTION("GOOGLEFINANCE($A22,AB$3)"),"#N/A") -> #N/A | AC22: =IFERROR(__xludf.DUMMYFUNCTION("GOOGLEFINANCE($A22,AC$3)"),"#N/A") -> #N/A | AD22: =IFERROR(__xludf.DUMMYFUNCTION("GOOGLEFINANCE($A22,AD$3)"),"#N/A") -> #N/A | AE22: =IFERROR(__xludf.DUMMYFUNCTION("GOOGLEFINANCE($A22,AE$3)"),"#N/A") -> #N/A
B23: =IFERROR(__xludf.DUMMYFUNCTION("GOOGLEFINANCE(A23,""name"")"),"#N/A") -> #N/A | D23: =IFERROR(__xludf.DUMMYFUNCTION("GOOGLEFINANCE(A23)"),"#N/A") -> #N/A | F23: =IF(M23="USD",E23/1.21,E23) -> #N/A | H23: =IFERROR(__xludf.DUMMYFUNCTION("if(isblank(A23)=TRUE,0,if(M23=""GBX"",F23*G23/100,IF(M23=""EUR"",F23*G23/GOOGLEFINANCE(""CURRENCY:GBPEUR""),F23*G23/GOOGLEFINANCE(""CURRENCY:GBPUSD""))))"),0.0) -> 0 | I23: =IFERROR(__xludf.DUMMYFUNCTION("if(isblank(A23)=TRUE,0,if(M23=""GBX"",D23*G23/100,IF(M23=""EUR"",D23*G23/GOOGLEFINANCE(""CURRENCY:GBPEUR""),D23*G23/GOOGLEFINANCE(""CURRENCY:GBPUSD""))))"),0.0) -> 0 | J23: =H23/$B$1 -> 0 | K23: =I23/H23-1 -> #DIV/0! | L23: =IFERROR(__xludf.DUMMYFUNCTION("SPARKLINE(GoogleFinance(A23, ""price"", TODAY()-30, TODAY()),{""color"",""blue"";""linewidth"",2}) "),"#N/A") -> #N/A | M23: =IFERROR(__xludf.DUMMYFUNCTION("GOOGLEFINANCE(A23,""currency"")"),"#N/A") -> #N/A | N23: =round(D23/AE23-1,4) -> #N/A | O23: =IFERROR(__xludf.DUMMYFUNCTION("GOOGLEFINANCE(A23,""Change"")"),"#N/A") -> #N/A | P23: =IFERROR(__xludf.DUMMYFUNCTION("GOOGLEFINANCE(A23,""High"")"),"#N/A") -> #N/A | Q23: =IFERROR(__xludf.DUMMYFUNCTION("GOOGLEFINANCE(A23,""low"")"),"#N/A") -> #N/A | R23: =IFERROR(__xludf.DUMMYFUNCTION("abs(P23-Q23)/GOOGLEFINANCE(A23,""closeyest"")"),"#N/A") -> #N/A | S23: =D23/Y23-1 -> #N/A | W23: =IF(ISERROR(if(or(AND(Q23<=T23,T23<=P23),AND(Q23<=U23, U23<=P23)),"TRADE ALERT","")),"DATA UNAVAILABLE",if(or(AND(Q23<=T23,T23<=P23),T23>P23,AND(Q23<=U23, U23<=P23)),"TRADE ALERT"&" - Price level hit for "&A23&" currently at "&D23&" "&B23,"")) -> DATA UNAVAILABLE | X23: =IFERROR(__xludf.DUMMYFUNCTION("GOOGLEFINANCE($A23,X$3)"),"#N/A") -> #N/A | Y23: =IFERROR(__xludf.DUMMYFUNCTION("GOOGLEFINANCE($A23,Y$3)"),"#N/A") -> #N/A | Z23: =IFERROR(__xludf.DUMMYFUNCTION("GOOGLEFINANCE($A23,Z$3)"),"#N/A") -> #N/A | AA23: =IFERROR(__xludf.DUMMYFUNCTION("GOOGLEFINANCE($A23,AA$3)"),"#N/A") -> #N/A | AB23: =IFERROR(__xludf.DUMMYFUNCTION("GOOGLEFINANCE($A23,AB$3)"),"#N/A") -> #N/A | AC23: =IFERROR(__xludf.DUMMYFUNCTION("GOOGLEFINANCE($A23,AC$3)"),"#N/A") -> #N/A | AD23: =IFERROR(__xludf.DUMMYFUNCTION("GOOGLEFINANCE($A23,AD$3)"),"#N/A") -> #N/A | AE23: =IFERROR(__xludf.DUMMYFUNCTION("GOOGLEFINANCE($A23,AE$3)"),"#N/A") -> #N/A
B24: =IFERROR(__xludf.DUMMYFUNCTION("GOOGLEFINANCE(A24,""name"")"),"#N/A") -> #N/A | D24: =IFERROR(__xludf.DUMMYFUNCTION("GOOGLEFINANCE(A24)"),"#N/A") -> #N/A | F24: =IF(M24="USD",E24/1.21,E24) -> #N/A | H24: =IFERROR(__xludf.DUMMYFUNCTION("if(isblank(A24)=TRUE,0,if(M24=""GBX"",F24*G24/100,IF(M24=""EUR"",F24*G24/GOOGLEFINANCE(""CURRENCY:GBPEUR""),F24*G24/GOOGLEFINANCE(""CURRENCY:GBPUSD""))))"),0.0) -> 0 | I24: =IFERROR(__xludf.DUMMYFUNCTION("if(isblank(A24)=TRUE,0,if(M24=""GBX"",D24*G24/100,IF(M24=""EUR"",D24*G24/GOOGLEFINANCE(""CURRENCY:GBPEUR""),D24*G24/GOOGLEFINANCE(""CURRENCY:GBPUSD""))))"),0.0) -> 0 | J24: =H24/$B$1 -> 0 | K24: =I24/H24-1 -> #DIV/0! | L24: =IFERROR(__xludf.DUMMYFUNCTION("SPARKLINE(GoogleFinance(A24, ""price"", TODAY()-30, TODAY()),{""color"",""blue"";""linewidth"",2}) "),"#N/A") -> #N/A | M24: =IFERROR(__xludf.DUMMYFUNCTION("GOOGLEFINANCE(A24,""currency"")"),"#N/A") -> #N/A | N24: =round(D24/AE24-1,4) -> #N/A | O24: =IFERROR(__xludf.DUMMYFUNCTION("GOOGLEFINANCE(A24,""Change"")"),"#N/A") -> #N/A | P24: =IFERROR(__xludf.DUMMYFUNCTION("GOOGLEFINANCE(A24,""High"")"),"#N/A") -> #N/A | Q24: =IFERROR(__xludf.DUMMYFUNCTION("GOOGLEFINANCE(A24,""low"")"),"#N/A") -> #N/A | R24: =IFERROR(__xludf.DUMMYFUNCTION("abs(P24-Q24)/GOOGLEFINANCE(A24,""closeyest"")"),"#N/A") -> #N/A | S24: =D24/Y24-1 -> #N/A | W24: =IF(ISERROR(if(or(AND(Q24<=T24,T24<=P24),AND(Q24<=U24, U24<=P24)),"TRADE ALERT","")),"DATA UNAVAILABLE",if(or(AND(Q24<=T24,T24<=P24),T24>P24,AND(Q24<=U24, U24<=P24)),"TRADE ALERT"&" - Price level hit for "&A24&" currently at "&D24&" "&B24,"")) -> DATA UNAVAILABLE | X24: =IFERROR(__xludf.DUMMYFUNCTION("GOOGLEFINANCE($A24,X$3)"),"#N/A") -> #N/A | Y24: =IFERROR(__xludf.DUMMYFUNCTION("GOOGLEFINANCE($A24,Y$3)"),"#N/A") -> #N/A | Z24: =IFERROR(__xludf.DUMMYFUNCTION("GOOGLEFINANCE($A24,Z$3)"),"#N/A") -> #N/A | AA24: =IFERROR(__xludf.DUMMYFUNCTION("GOOGLEFINANCE($A24,AA$3)"),"#N/A") -> #N/A | AB24: =IFERROR(__xludf.DUMMYFUNCTION("GOOGLEFINANCE($A24,AB$3)"),"#N/A") -> #N/A | AC24: =IFERROR(__xludf.DUMMYFUNCTION("GOOGLEFINANCE($A24,AC$3)"),"#N/A") -> #N/A | AD24: =IFERROR(__xludf.DUMMYFUNCTION("GOOGLEFINANCE($A24,AD$3)"),"#N/A") -> #N/A | AE24: =IFERROR(__xludf.DUMMYFUNCTION("GOOGLEFINANCE($A24,AE$3)"),"#N/A") -> #N/A
B25: =IFERROR(__xludf.DUMMYFUNCTION("GOOGLEFINANCE(A25,""name"")"),"#N/A") -> #N/A | D25: =IFERROR(__xludf.DUMMYFUNCTION("GOOGLEFINANCE(A25)"),"#N/A") -> #N/A | F25: =IF(M25="USD",E25/1.21,E25) -> #N/A | H25: =IFERROR(__xludf.DUMMYFUNCTION("if(isblank(A25)=TRUE,0,if(M25=""GBX"",F25*G25/100,IF(M25=""EUR"",F25*G25/GOOGLEFINANCE(""CURRENCY:GBPEUR""),F25*G25/GOOGLEFINANCE(""CURRENCY:GBPUSD""))))"),0.0) -> 0 | I25: =IFERROR(__xludf.DUMMYFUNCTION("if(isblank(A25)=TRUE,0,if(M25=""GBX"",D25*G25/100,IF(M25=""EUR"",D25*G25/GOOGLEFINANCE(""CURRENCY:GBPEUR""),D25*G25/GOOGLEFINANCE(""CURRENCY:GBPUSD""))))"),0.0) -> 0 | J25: =H25/$B$1 -> 0 | K25: =I25/H25-1 -> #DIV/0! | L25: =IFERROR(__xludf.DUMMYFUNCTION("SPARKLINE(GoogleFinance(A25, ""price"", TODAY()-30, TODAY()),{""color"",""blue"";""linewidth"",2}) "),"#N/A") -> #N/A | M25: =IFERROR(__xludf.DUMMYFUNCTION("GOOGLEFINANCE(A25,""currency"")"),"#N/A") -> #N/A | N25: =round(D25/AE25-1,4) -> #N/A | O25: =IFERROR(__xludf.DUMMYFUNCTION("GOOGLEFINANCE(A25,""Change"")"),"#N/A") -> #N/A | P25: =IFERROR(__xludf.DUMMYFUNCTION("GOOGLEFINANCE(A25,""High"")"),"#N/A") -> #N/A | Q25: =IFERROR(__xludf.DUMMYFUNCTION("GOOGLEFINANCE(A25,""low"")"),"#N/A") -> #N/A | R25: =IFERROR(__xludf.DUMMYFUNCTION("abs(P25-Q25)/GOOGLEFINANCE(A25,""closeyest"")"),"#N/A") -> #N/A | S25: =D25/Y25-1 -> #N/A | W25: =IF(ISERROR(if(or(AND(Q25<=T25,T25<=P25),AND(Q25<=U25, U25<=P25)),"TRADE ALERT","")),"DATA UNAVAILABLE",if(or(AND(Q25<=T25,T25<=P25),T25>P25,AND(Q25<=U25, U25<=P25)),"TRADE ALERT"&" - Price level hit for "&A25&" currently at "&D25&" "&B25,"")) -> DATA UNAVAILABLE | X25: =IFERROR(__xludf.DUMMYFUNCTION("GOOGLEFINANCE($A25,X$3)"),"#N/A") -> #N/A | Y25: =IFERROR(__xludf.DUMMYFUNCTION("GOOGLEFINANCE($A25,Y$3)"),"#N/A") -> #N/A | Z25: =IFERROR(__xludf.DUMMYFUNCTION("GOOGLEFINANCE($A25,Z$3)"),"#N/A") -> #N/A | AA25: =IFERROR(__xludf.DUMMYFUNCTION("GOOGLEFINANCE($A25,AA$3)"),"#N/A") -> #N/A | AB25: =IFERROR(__xludf.DUMMYFUNCTION("GOOGLEFINANCE($A25,AB$3)"),"#N/A") -> #N/A | AC25: =IFERROR(__xludf.DUMMYFUNCTION("GOOGLEFINANCE($A25,AC$3)"),"#N/A") -> #N/A | AD25: =IFERROR(__xludf.DUMMYFUNCTION("GOOGLEFINANCE($A25,AD$3)"),"#N/A") -> #N/A | AE25: =IFERROR(__xludf.DUMMYFUNCTION("GOOGLEFINANCE($A25,AE$3)"),"#N/A") -> #N/A
B26: =IFERROR(__xludf.DUMMYFUNCTION("GOOGLEFINANCE(A26,""name"")"),"#N/A") -> #N/A | D26: =IFERROR(__xludf.DUMMYFUNCTION("GOOGLEFINANCE(A26)"),"#N/A") -> #N/A | F26: =IF(M26="USD",E26/1.21,E26) -> #N/A | H26: =IFERROR(__xludf.DUMMYFUNCTION("if(isblank(A26)=TRUE,0,if(M26=""GBX"",F26*G26/100,IF(M26=""EUR"",F26*G26/GOOGLEFINANCE(""CURRENCY:GBPEUR""),F26*G26/GOOGLEFINANCE(""CURRENCY:GBPUSD""))))"),0.0) -> 0 | I26: =IFERROR(__xludf.DUMMYFUNCTION("if(isblank(A26)=TRUE,0,if(M26=""GBX"",D26*G26/100,IF(M26=""EUR"",D26*G26/GOOGLEFINANCE(""CURRENCY:GBPEUR""),D26*G26/GOOGLEFINANCE(""CURRENCY:GBPUSD""))))"),0.0) -> 0 | J26: =H26/$B$1 -> 0 | K26: =I26/H26-1 -> #DIV/0! | L26: =IFERROR(__xludf.DUMMYFUNCTION("SPARKLINE(GoogleFinance(A26, ""price"", TODAY()-30, TODAY()),{""color"",""blue"";""linewidth"",2}) "),"#N/A") -> #N/A | M26: =IFERROR(__xludf.DUMMYFUNCTION("GOOGLEFINANCE(A26,""currency"")"),"#N/A") -> #N/A | N26: =round(D26/AE26-1,4) -> #N/A | O26: =IFERROR(__xludf.DUMMYFUNCTION("GOOGLEFINANCE(A26,""Change"")"),"#N/A") -> #N/A | P26: =IFERROR(__xludf.DUMMYFUNCTION("GOOGLEFINANCE(A26,""High"")"),"#N/A") -> #N/A | Q26: =IFERROR(__xludf.DUMMYFUNCTION("GOOGLEFINANCE(A26,""low"")"),"#N/A") -> #N/A | R26: =IFERROR(__xludf.DUMMYFUNCTION("abs(P26-Q26)/GOOGLEFINANCE(A26,""closeyest"")"),"#N/A") -> #N/A | S26: =D26/Y26-1 -> #N/A | W26: =IF(ISERROR(if(or(AND(Q26<=T26,T26<=P26),AND(Q26<=U26, U26<=P26)),"TRADE ALERT","")),"DATA UNAVAILABLE",if(or(AND(Q26<=T26,T26<=P26),T26>P26,AND(Q26<=U26, U26<=P26)),"TRADE ALERT"&" - Price level hit for "&A26&" currently at "&D26&" "&B26,"")) -> DATA UNAVAILABLE | X26: =IFERROR(__xludf.DUMMYFUNCTION("GOOGLEFINANCE($A26,X$3)"),"#N/A") -> #N/A | Y26: =IFERROR(__xludf.DUMMYFUNCTION("GOOGLEFINANCE($A26,Y$3)"),"#N/A") -> #N/A | Z26: =IFERROR(__xludf.DUMMYFUNCTION("GOOGLEFINANCE($A26,Z$3)"),"#N/A") -> #N/A | AA26: =IFERROR(__xludf.DUMMYFUNCTION("GOOGLEFINANCE($A26,AA$3)"),"#N/A") -> #N/A | AB26: =IFERROR(__xludf.DUMMYFUNCTION("GOOGLEFINANCE($A26,AB$3)"),"#N/A") -> #N/A | AC26: =IFERROR(__xludf.DUMMYFUNCTION("GOOGLEFINANCE($A26,AC$3)"),"#N/A") -> #N/A | AD26: =IFERROR(__xludf.DUMMYFUNCTION("GOOGLEFINANCE($A26,AD$3)"),"#N/A") -> #N/A | AE26: =IFERROR(__xludf.DUMMYFUNCTION("GOOGLEFINANCE($A26,AE$3)"),"#N/A") -> #N/A
B27: =IFERROR(__xludf.DUMMYFUNCTION("GOOGLEFINANCE(A27,""name"")"),"#N/A") -> #N/A | D27: =IFERROR(__xludf.DUMMYFUNCTION("GOOGLEFINANCE(A27)"),"#N/A") -> #N/A | F27: =IF(M27="USD",E27/1.21,E27) -> #N/A | H27: =IFERROR(__xludf.DUMMYFUNCTION("if(isblank(A27)=TRUE,0,if(M27=""GBX"",F27*G27/100,IF(M27=""EUR"",F27*G27/GOOGLEFINANCE(""CURRENCY:GBPEUR""),F27*G27/GOOGLEFINANCE(""CURRENCY:GBPUSD""))))"),0.0) -> 0 | I27: =IFERROR(__xludf.DUMMYFUNCTION("if(isblank(A27)=TRUE,0,if(M27=""GBX"",D27*G27/100,IF(M27=""EUR"",D27*G27/GOOGLEFINANCE(""CURRENCY:GBPEUR""),D27*G27/GOOGLEFINANCE(""CURRENCY:GBPUSD""))))"),0.0) -> 0 | J27: =H27/$B$1 -> 0 | K27: =I27/H27-1 -> #DIV/0! | L27: =IFERROR(__xludf.DUMMYFUNCTION("SPARKLINE(GoogleFinance(A27, ""price"", TODAY()-30, TODAY()),{""color"",""blue"";""linewidth"",2}) "),"#N/A") -> #N/A | M27: =IFERROR(__xludf.DUMMYFUNCTION("GOOGLEFINANCE(A27,""currency"")"),"#N/A") -> #N/A | N27: =round(D27/AE27-1,4) -> #N/A | O27: =IFERROR(__xludf.DUMMYFUNCTION("GOOGLEFINANCE(A27,""Change"")"),"#N/A") -> #N/A | P27: =IFERROR(__xludf.DUMMYFUNCTION("GOOGLEFINANCE(A27,""High"")"),"#N/A") -> #N/A | Q27: =IFERROR(__xludf.DUMMYFUNCTION("GOOGLEFINANCE(A27,""low"")"),"#N/A") -> #N/A | R27: =IFERROR(__xludf.DUMMYFUNCTION("abs(P27-Q27)/GOOGLEFINANCE(A27,""closeyest"")"),"#N/A") -> #N/A | S27: =D27/Y27-1 -> #N/A | W27: =IF(ISERROR(if(or(AND(Q27<=T27,T27<=P27),AND(Q27<=U27, U27<=P27)),"TRADE ALERT","")),"DATA UNAVAILABLE",if(or(AND(Q27<=T27,T27<=P27),T27>P27,AND(Q27<=U27, U27<=P27)),"TRADE ALERT"&" - Price level hit for "&A27&" currently at "&D27&" "&B27,"")) -> DATA UNAVAILABLE | X27: =IFERROR(__xludf.DUMMYFUNCTION("GOOGLEFINANCE($A27,X$3)"),"#N/A") -> #N/A | Y27: =IFERROR(__xludf.DUMMYFUNCTION("GOOGLEFINANCE($A27,Y$3)"),"#N/A") -> #N/A | Z27: =IFERROR(__xludf.DUMMYFUNCTION("GOOGLEFINANCE($A27,Z$3)"),"#N/A") -> #N/A | AA27: =IFERROR(__xludf.DUMMYFUNCTION("GOOGLEFINANCE($A27,AA$3)"),"#N/A") -> #N/A | AB27: =IFERROR(__xludf.DUMMYFUNCTION("GOOGLEFINANCE($A27,AB$3)"),"#N/A") -> #N/A | AC27: =IFERROR(__xludf.DUMMYFUNCTION("GOOGLEFINANCE($A27,AC$3)"),"#N/A") -> #N/A | AD27: =IFERROR(__xludf.DUMMYFUNCTION("GOOGLEFINANCE($A27,AD$3)"),"#N/A") -> #N/A | AE27: =IFERROR(__xludf.DUMMYFUNCTION("GOOGLEFINANCE($A27,AE$3)"),"#N/A") -> #N/A
B28: =IFERROR(__xludf.DUMMYFUNCTION("GOOGLEFINANCE(A28,""name"")"),"#N/A") -> #N/A | D28: =IFERROR(__xludf.DUMMYFUNCTION("GOOGLEFINANCE(A28)"),"#N/A") -> #N/A | F28: =IF(M28="USD",E28/1.21,E28) -> #N/A | H28: =IFERROR(__xludf.DUMMYFUNCTION("if(isblank(A28)=TRUE,0,if(M28=""GBX"",F28*G28/100,IF(M28=""EUR"",F28*G28/GOOGLEFINANCE(""CURRENCY:GBPEUR""),F28*G28/GOOGLEFINANCE(""CURRENCY:GBPUSD""))))"),0.0) -> 0 | I28: =IFERROR(__xludf.DUMMYFUNCTION("if(isblank(A28)=TRUE,0,if(M28=""GBX"",D28*G28/100,IF(M28=""EUR"",D28*G28/GOOGLEFINANCE(""CURRENCY:GBPEUR""),D28*G28/GOOGLEFINANCE(""CURRENCY:GBPUSD""))))"),0.0) -> 0 | J28: =H28/$B$1 -> 0 | K28: =I28/H28-1 -> #DIV/0! | L28: =IFERROR(__xludf.DUMMYFUNCTION("SPARKLINE(GoogleFinance(A28, ""price"", TODAY()-30, TODAY()),{""color"",""blue"";""linewidth"",2}) "),"#N/A") -> #N/A | M28: =IFERROR(__xludf.DUMMYFUNCTION("GOOGLEFINANCE(A28,""currency"")"),"#N/A") -> #N/A | N28: =round(D28/AE28-1,4) -> #N/A | O28: =IFERROR(__xludf.DUMMYFUNCTION("GOOGLEFINANCE(A28,""Change"")"),"#N/A") -> #N/A | P28: =IFERROR(__xludf.DUMMYFUNCTION("GOOGLEFINANCE(A28,""High"")"),"#N/A") -> #N/A | Q28: =IFERROR(__xludf.DUMMYFUNCTION("GOOGLEFINANCE(A28,""low"")"),"#N/A") -> #N/A | R28: =IFERROR(__xludf.DUMMYFUNCTION("abs(P28-Q28)/GOOGLEFINANCE(A28,""closeyest"")"),"#N/A") -> #N/A | S28: =D28/Y28-1 -> #N/A | W28: =IF(ISERROR(if(or(AND(Q28<=T28,T28<=P28),AND(Q28<=U28, U28<=P28)),"TRADE ALERT","")),"DATA UNAVAILABLE",if(or(AND(Q28<=T28,T28<=P28),T28>P28,AND(Q28<=U28, U28<=P28)),"TRADE ALERT"&" - Price level hit for "&A28&" currently at "&D28&" "&B28,"")) -> DATA UNAVAILABLE | X28: =IFERROR(__xludf.DUMMYFUNCTION("GOOGLEFINANCE($A28,X$3)"),"#N/A") -> #N/A | Y28: =IFERROR(__xludf.DUMMYFUNCTION("GOOGLEFINANCE($A28,Y$3)"),"#N/A") -> #N/A | Z28: =IFERROR(__xludf.DUMMYFUNCTION("GOOGLEFINANCE($A28,Z$3)"),"#N/A") -> #N/A | AA28: =IFERROR(__xludf.DUMMYFUNCTION("GOOGLEFINANCE($A28,AA$3)"),"#N/A") -> #N/A | AB28: =IFERROR(__xludf.DUMMYFUNCTION("GOOGLEFINANCE($A28,AB$3)"),"#N/A") -> #N/A | AC28: =IFERROR(__xludf.DUMMYFUNCTION("GOOGLEFINANCE($A28,AC$3)"),"#N/A") -> #N/A | AD28: =IFERROR(__xludf.DUMMYFUNCTION("GOOGLEFINANCE($A28,AD$3)"),"#N/A") -> #N/A | AE28: =IFERROR(__xludf.DUMMYFUNCTION("GOOGLEFINANCE($A28,AE$3)"),"#N/A") -> #N/A
A29: Watchlist Favourites | C29: Watch Reason
A30: ='Virtual Portfolio'!A33 -> SNAP | B30: =IFERROR(__xludf.DUMMYFUNCTION("GOOGLEFINANCE(A30,""name"")"),"Snap Inc") -> Snap Inc | C30: ='Virtual Portfolio'!C33 | D30: =IFERROR(__xludf.DUMMYFUNCTION("GOOGLEFINANCE(A30)"),4.75) -> 4.75 | K30: =(D30-E30)/E30 -> #DIV/0! | L30: =IFERROR(__xludf.DUMMYFUNCTION("SPARKLINE(GoogleFinance(A30, ""price"", TODAY()-30, TODAY()),{""color"",""blue"";""linewidth"",2}) "),"") | M30: =IFERROR(__xludf.DUMMYFUNCTION("GOOGLEFINANCE(A30,""currency"")"),"USD") -> USD | N30: =round(D30/AE30-1,4) -> -0.0166 | O30: =IFERROR(__xludf.DUMMYFUNCTION("GOOGLEFINANCE(A30,""Change"")"),-0.09) -> -0.09 | P30: =IFERROR(__xludf.DUMMYFUNCTION("GOOGLEFINANCE(A30,""High"")"),4.87) -> 4.87 | Q30: =IFERROR(__xludf.DUMMYFUNCTION("GOOGLEFINANCE(A30,""low"")"),4.66) -> 4.66 | R30: =IFERROR(__xludf.DUMMYFUNCTION("abs(P30-Q30)/GOOGLEFINANCE(A30,""closeyest"")"),0.04347826086956521) -> 0.043478261 | S30: =D30/Y30-1 -> 0.019313305 | T30: ='Virtual Portfolio'!T33 -> 15 | U30: ='Virtual Portfolio'!U33 -> 50 | W30: =IF(ISERROR(if(or(AND(Q30<=T30,T30<=P30),AND(Q30<=U30, U30<=P30)),"TRADE ALERT","")),"DATA UNAVAILABLE",if(or(AND(Q30<=T30,T30<=P30),T30>P30,AND(Q30<=U30, U30<=P30)),"TRADE ALERT"&" - Price level hit for "&A30&" currently at "&D30&" "&B30,"")) -> TRADE ALERT - Price level hit for SNAP currently at 4.75 Snap Inc | X30: =IFERROR(__xludf.DUMMYFUNCTION("GOOGLEFINANCE($A30,X$3)"),0.83) -> 0.83 | Y30: =IFERROR(__xludf.DUMMYFUNCTION("GOOGLEFINANCE($A30,Y$3)"),4.66) -> 4.66 | Z30: =IFERROR(__xludf.DUMMYFUNCTION("GOOGLEFINANCE($A30,Z$3)"),11.05) -> 11.05 | AA30: =IFERROR(__xludf.DUMMYFUNCTION("GOOGLEFINANCE($A30,AA$3)"),"#N/A") -> #N/A | AB30: =IFERROR(__xludf.DUMMYFUNCTION("GOOGLEFINANCE($A30,AB$3)"),"#N/A") -> #N/A | AC30: =IFERROR(__xludf.DUMMYFUNCTION("GOOGLEFINANCE($A30,AC$3)"),0.0) -> 0 | AD30: =IFERROR(__xludf.DUMMYFUNCTION("GOOGLEFINANCE($A30,AD$3)"),8.014072301E9) -> 8014072301 | AE30: =IFERROR(__xludf.DUMMYFUNCTION("GOOGLEFINANCE($A30,AE$3)"),4.83) -> 4.83
A31: ='Virtual Portfolio'!A34 -> CWBR | B31: =IFERROR(__xludf.DUMMYFUNCTION("GOOGLEFINANCE(A31,""name"")"),"#N/A") -> #N/A | C31: ='Virtual Portfolio'!C34 | D31: =IFERROR(__xludf.DUMMYFUNCTION("GOOGLEFINANCE(A31)"),"#N/A") -> #N/A | K31: =(D31-E31)/E31 -> #N/A | L31: =IFERROR(__xludf.DUMMYFUNCTION("SPARKLINE(GoogleFinance(A31, ""price"", TODAY()-30, TODAY()),{""color"",""blue"";""linewidth"",2}) "),"#N/A") -> #N/A | M31: =IFERROR(__xludf.DUMMYFUNCTION("GOOGLEFINANCE(A31,""currency"")"),"#N/A") -> #N/A | N31: =round(D31/AE31-1,4) -> #N/A | O31: =IFERROR(__xludf.DUMMYFUNCTION("GOOGLEFINANCE(A31,""Change"")"),"#N/A") -> #N/A | P31: =IFERROR(__xludf.DUMMYFUNCTION("GOOGLEFINANCE(A31,""High"")"),"#N/A") -> #N/A | Q31: =IFERROR(__xludf.DUMMYFUNCTION("GOOGLEFINANCE(A31,""low"")"),"#N/A") -> #N/A | R31: =IFERROR(__xludf.DUMMYFUNCTION("abs(P31-Q31)/GOOGLEFINANCE(A31,""closeyest"")"),"#N/A") -> #N/A | S31: =D31/Y31-1 -> #N/A | T31: ='Virtual Portfolio'!T34 -> 1.5 | U31: ='Virtual Portfolio'!U34 | W31: =IF(ISERROR(if(or(AND(Q31<=T31,T31<=P31),AND(Q31<=U31, U31<=P31)),"TRADE ALERT","")),"DATA UNAVAILABLE",if(or(AND(Q31<=T31,T31<=P31),T31>P31,AND(Q31<=U31, U31<=P31)),"TRADE ALERT"&" - Price level hit for "&A31&" currently at "&D31&" "&B31,"")) -> DATA UNAVAILABLE | X31: =IFERROR(__xludf.DUMMYFUNCTION("GOOGLEFINANCE($A31,X$3)"),"#N/A") -> #N/A | Y31: =IFERROR(__xludf.DUMMYFUNCTION("GOOGLEFINANCE($A31,Y$3)"),"#N/A") -> #N/A | Z31: =IFERROR(__xludf.DUMMYFUNCTION("GOOGLEFINANCE($A31,Z$3)"),"#N/A") -> #N/A | AA31: =IFERROR(__xludf.DUMMYFUNCTION("GOOGLEFINANCE($A31,AA$3)"),"#N/A") -> #N/A | AB31: =IFERROR(__xludf.DUMMYFUNCTION("GOOGLEFINANCE($A31,AB$3)"),"#N/A") -> #N/A | AC31: =IFERROR(__xludf.DUMMYFUNCTION("GOOGLEFINANCE($A31,AC$3)"),"#N/A") -> #N/A | AD31: =IFERROR(__xludf.DUMMYFUNCTION("GOOGLEFINANCE($A31,AD$3)"),"#N/A") -> #N/A | AE31: =IFERROR(__xludf.DUMMYFUNCTION("GOOGLEFINANCE($A31,AE$3)"),"#N/A") -> #N/A
A32: ='Virtual Portfolio'!A35 -> HZD | B32: =IFERROR(__xludf.DUMMYFUNCTION("GOOGLEFINANCE(A32,""name"")"),"#N/A") -> #N/A | C32: ='Virtual Portfolio'!C35 | D32: =IFERROR(__xludf.DUMMYFUNCTION("GOOGLEFINANCE(A32)"),"#N/A") -> #N/A | K32: =(D32-E32)/E32 -> #N/A | L32: =IFERROR(__xludf.DUMMYFUNCTION("SPARKLINE(GoogleFinance(A32, ""price"", TODAY()-30, TODAY()),{""color"",""blue"";""linewidth"",2}) "),"#N/A") -> #N/A | M32: =IFERROR(__xludf.DUMMYFUNCTION("GOOGLEFINANCE(A32,""currency"")"),"#N/A") -> #N/A | N32: =round(D32/AE32-1,4) -> #N/A | O32: =IFERROR(__xludf.DUMMYFUNCTION("GOOGLEFINANCE(A32,""Change"")"),"#N/A") -> #N/A | P32: =IFERROR(__xludf.DUMMYFUNCTION("GOOGLEFINANCE(A32,""High"")"),"#N/A") -> #N/A | Q32: =IFERROR(__xludf.DUMMYFUNCTION("GOOGLEFINANCE(A32,""low"")"),"#N/A") -> #N/A | R32: =IFERROR(__xludf.DUMMYFUNCTION("abs(P32-Q32)/GOOGLEFINANCE(A32,""closeyest"")"),"#N/A") -> #N/A | S32: =D32/Y32-1 -> #N/A | T32: ='Virtual Portfolio'!T35 -> 105 | U32: ='Virtual Portfolio'!U35 | W32: =IF(ISERROR(if(or(AND(Q32<=T32,T32<=P32),AND(Q32<=U32, U32<=P32)),"TRADE ALERT","")),"DATA UNAVAILABLE",if(or(AND(Q32<=T32,T32<=P32),T32>P32,AND(Q32<=U32, U32<=P32)),"TRADE ALERT"&" - Price level hit for "&A32&" currently at "&D32&" "&B32,"")) -> DATA UNAVAILABLE | X32: =IFERROR(__xludf.DUMMYFUNCTION("GOOGLEFINANCE($A32,X$3)"),"#N/A") -> #N/A | Y32: =IFERROR(__xludf.DUMMYFUNCTION("GOOGLEFINANCE($A32,Y$3)"),"#N/A") -> #N/A | Z32: =IFERROR(__xludf.DUMMYFUNCTION("GOOGLEFINANCE($A32,Z$3)"),"#N/A") -> #N/A | AA32: =IFERROR(__xludf.DUMMYFUNCTION("GOOGLEFINANCE($A32,AA$3)"),"#N/A") -> #N/A | AB32: =IFERROR(__xludf.DUMMYFUNCTION("GOOGLEFINANCE($A32,AB$3)"),"#N/A") -> #N/A | AC32: =IFERROR(__xludf.DUMMYFUNCTION("GOOGLEFINANCE($A32,AC$3)"),"#N/A") -> #N/A | AD32: =IFERROR(__xludf.DUMMYFUNCTION("GOOGLEFINANCE($A32,AD$3)"),"#N/A") -> #N/A | AE32: =IFERROR(__xludf.DUMMYFUNCTION("GOOGLEFINANCE($A32,AE$3)"),"#N/A") -> #N/A
A33: ='Virtual Portfolio'!A36 -> MANU | B33: =IFERROR(__xludf.DUMMYFUNCTION("GOOGLEFINANCE(A33,""name"")"),"Manchester United PLC") -> Manchester United PLC | C33: ='Virtual Portfolio'!C36 | D33: =IFERROR(__xludf.DUMMYFUNCTION("GOOGLEFINANCE(A33)"),17.75) -> 17.75 | K33: =(D33-E33)/E33 -> #DIV/0! | L33: =IFERROR(__xludf.DUMMYFUNCTION("SPARKLINE(GoogleFinance(A33, ""price"", TODAY()-30, TODAY()),{""color"",""blue"";""linewidth"",2}) "),"") | M33: =IFERROR(__xludf.DUMMYFUNCTION("GOOGLEFINANCE(A33,""currency"")"),"USD") -> USD | N33: =round(D33/AE33-1,4) -> 0.0178 | O33: =IFERROR(__xludf.DUMMYFUNCTION("GOOGLEFINANCE(A33,""Change"")"),0.31) -> 0.31 | P33: =IFERROR(__xludf.DUMMYFUNCTION("GOOGLEFINANCE(A33,""High"")"),17.75) -> 17.75 | Q33: =IFERROR(__xludf.DUMMYFUNCTION("GOOGLEFINANCE(A33,""low"")"),17.34) -> 17.34 | R33: =IFERROR(__xludf.DUMMYFUNCTION("abs(P33-Q33)/GOOGLEFINANCE(A33,""closeyest"")"),0.02350917431192661) -> 0.023509174 | S33: =D33/Y33-1 -> 0.47302905 | T33: ='Virtual Portfolio'!T36 -> 15 | U33: ='Virtual Portfolio'!U36 | W33: =IF(ISERROR(if(or(AND(Q33<=T33,T33<=P33),AND(Q33<=U33, U33<=P33)),"TRADE ALERT","")),"DATA UNAVAILABLE",if(or(AND(Q33<=T33,T33<=P33),T33>P33,AND(Q33<=U33, U33<=P33)),"TRADE ALERT"&" - Price level hit for "&A33&" currently at "&D33&" "&B33,"")) | X33: =IFERROR(__xludf.DUMMYFUNCTION("GOOGLEFINANCE($A33,X$3)"),0.54) -> 0.54 | Y33: =IFERROR(__xludf.DUMMYFUNCTION("GOOGLEFINANCE($A33,Y$3)"),12.05) -> 12.05 | Z33: =IFERROR(__xludf.DUMMYFUNCTION("GOOGLEFINANCE($A33,Z$3)"),19.65) -> 19.65 | AA33: =IFERROR(__xludf.DUMMYFUNCTION("GOOGLEFINANCE($A33,AA$3)"),"#N/A") -> #N/A | AB33: =IFERROR(__xludf.DUMMYFUNCTION("GOOGLEFINANCE($A33,AB$3)"),"#N/A") -> #N/A | AC33: =IFERROR(__xludf.DUMMYFUNCTION("GOOGLEFINANCE($A33,AC$3)"),0.0) -> 0 | AD33: =IFERROR(__xludf.DUMMYFUNCTION("GOOGLEFINANCE($A33,AD$3)"),3.055579075E9) -> 3055579075 | AE33: =IFERROR(__xludf.DUMMYFUNCTION("GOOGLEFINANCE($A33,AE$3)"),17.44) -> 17.44
A34: ='Virtual Portfolio'!A37 -> TIT | B34: =IFERROR(__xludf.DUMMYFUNCTION("GOOGLEFINANCE(A34,""name"")"),"Telecom Italia SpA") -> Telecom Italia SpA | C34: ='Virtual Portfolio'!C37 | D34: =IFERROR(__xludf.DUMMYFUNCTION("GOOGLEFINANCE(A34)"),0.66) -> 0.66 | K34: =(D34-E34)/E34 -> #DIV/0! | L34: =IFERROR(__xludf.DUMMYFUNCTION("SPARKLINE(GoogleFinance(A34, ""price"", TODAY()-30, TODAY()),{""color"",""blue"";""linewidth"",2}) "),"") | M34: =IFERROR(__xludf.DUMMYFUNCTION("GOOGLEFINANCE(A34,""currency"")"),"EUR") -> EUR | N34: =round(D34/AE34-1,4) -> 0.0313 | O34: =IFERROR(__xludf.DUMMYFUNCTION("GOOGLEFINANCE(A34,""Change"")"),0.02) -> 0.02 | P34: =IFERROR(__xludf.DUMMYFUNCTION("GOOGLEFINANCE(A34,""High"")"),0.66) -> 0.66 | Q34: =IFERROR(__xludf.DUMMYFUNCTION("GOOGLEFINANCE(A34,""low"")"),0.64) -> 0.64 | R34: =IFERROR(__xludf.DUMMYFUNCTION("abs(P34-Q34)/GOOGLEFINANCE(A34,""closeyest"")"),0.03125000000000003) -> 0.03125 | S34: =D34/Y34-1 -> 1.64 | T34: ='Virtual Portfolio'!T37 -> 0.35 | U34: ='Virtual Portfolio'!U37 | W34: =IF(ISERROR(if(or(AND(Q34<=T34,T34<=P34),AND(Q34<=U34, U34<=P34)),"TRADE ALERT","")),"DATA UNAVAILABLE",if(or(AND(Q34<=T34,T34<=P34),T34>P34,AND(Q34<=U34, U34<=P34)),"TRADE ALERT"&" - Price level hit for "&A34&" currently at "&D34&" "&B34,"")) | X34: =IFERROR(__xludf.DUMMYFUNCTION("GOOGLEFINANCE($A34,X$3)"),"#N/A") -> #N/A | Y34: =IFERROR(__xludf.DUMMYFUNCTION("GOOGLEFINANCE($A34,Y$3)"),0.25) -> 0.25 | Z34: =IFERROR(__xludf.DUMMYFUNCTION("GOOGLEFINANCE($A34,Z$3)"),0.66) -> 0.66 | AA34: =IFERROR(__xludf.DUMMYFUNCTION("GOOGLEFINANCE($A34,AA$3)"),"#N/A") -> #N/A | AB34: =IFERROR(__xludf.DUMMYFUNCTION("GOOGLEFINANCE($A34,AB$3)"),"#N/A") -> #N/A | AC34: =IFERROR(__xludf.DUMMYFUNCTION("GOOGLEFINANCE($A34,AC$3)"),0.0) -> 0 | AD34: =IFERROR(__xludf.DUMMYFUNCTION("GOOGLEFINANCE($A34,AD$3)"),1.7066289426E10) -> 17066289426 | AE34: =IFERROR(__xludf.DUMMYFUNCTION("GOOGLEFINANCE($A34,AE$3)"),0.64) -> 0.64
A35: ='Virtual Portfolio'!A38 -> OMG | B35: =IFERROR(__xludf.DUMMYFUNCTION("GOOGLEFINANCE(A35,""name"")"),"Omai Gold Mines Corp") -> Omai Gold Mines Corp | C35: ='Virtual Portfolio'!C38 | D35: =IFERROR(__xludf.DUMMYFUNCTION("GOOGLEFINANCE(A35)"),1.99) -> 1.99 | K35: =(D35-E35)/E35 -> #DIV/0! | L35: =IFERROR(__xludf.DUMMYFUNCTION("SPARKLINE(GoogleFinance(A35, ""price"", TODAY()-30, TODAY()),{""color"",""blue"";""linewidth"",2}) "),"") | M35: =IFERROR(__xludf.DUMMYFUNCTION("GOOGLEFINANCE(A35,""currency"")"),"CAD") -> CAD | N35: =round(D35/AE35-1,4) -> -0.0293 | O35: =IFERROR(__xludf.DUMMYFUNCTION("GOOGLEFINANCE(A35,""Change"")"),-0.06) -> -0.06 | P35: =IFERROR(__xludf.DUMMYFUNCTION("GOOGLEFINANCE(A35,""High"")"),2.06) -> 2.06 | Q35: =IFERROR(__xludf.DUMMYFUNCTION("GOOGLEFINANCE(A35,""low"")"),1.91) -> 1.91 | R35: =IFERROR(__xludf.DUMMYFUNCTION("abs(P35-Q35)/GOOGLEFINANCE(A35,""closeyest"")"),0.07317073170731714) -> 0.073170732 | S35: =D35/Y35-1 -> 5.4193548 | T35: ='Virtual Portfolio'!T38 -> 80 | U35: ='Virtual Portfolio'!U38 | W35: =IF(ISERROR(if(or(AND(Q35<=T35,T35<=P35),AND(Q35<=U35, U35<=P35)),"TRADE ALERT","")),"DATA UNAVAILABLE",if(or(AND(Q35<=T35,T35<=P35),T35>P35,AND(Q35<=U35, U35<=P35)),"TRADE ALERT"&" - Price level hit for "&A35&" currently at "&D35&" "&B35,"")) -> TRADE ALERT - Price level hit for OMG currently at 1.99 Omai Gold Mines Corp | X35: =IFERROR(__xludf.DUMMYFUNCTION("GOOGLEFINANCE($A35,X$3)"),1.71) -> 1.71 | Y35: =IFERROR(__xludf.DUMMYFUNCTION("GOOGLEFINANCE($A35,Y$3)"),0.31) -> 0.31 | Z35: =IFERROR(__xludf.DUMMYFUNCTION("GOOGLEFINANCE($A35,Z$3)"),2.18) -> 2.18 | AA35: =IFERROR(__xludf.DUMMYFUNCTION("GOOGLEFINANCE($A35,AA$3)"),"#N/A") -> #N/A | AB35: =IFERROR(__xludf.DUMMYFUNCTION("GOOGLEFINANCE($A35,AB$3)"),"#N/A") -> #N/A | AC35: =IFERROR(__xludf.DUMMYFUNCTION("GOOGLEFINANCE($A35,AC$3)"),15.0) -> 15 | AD35: =IFERROR(__xludf.DUMMYFUNCTION("GOOGLEFINANCE($A35,AD$3)"),1.340140631E9) -> 1340140631 | AE35: =IFERROR(__xludf.DUMMYFUNCTION("GOOGLEFINANCE($A35,AE$3)"),2.05) -> 2.05
A36: ='Virtual Portfolio'!A39 -> GNUS | B36: =IFERROR(__xludf.DUMMYFUNCTION("GOOGLEFINANCE(A36,""name"")"),"#N/A") -> #N/A | C36: ='Virtual Portfolio'!C39 | D36: =IFERROR(__xludf.DUMMYFUNCTION("GOOGLEFINANCE(A36)"),"#N/A") -> #N/A | K36: =(D36-E36)/E36 -> #N/A | L36: =IFERROR(__xludf.DUMMYFUNCTION("SPARKLINE(GoogleFinance(A36, ""price"", TODAY()-30, TODAY()),{""color"",""blue"";""linewidth"",2}) "),"#N/A") -> #N/A | M36: =IFERROR(__xludf.DUMMYFUNCTION("GOOGLEFINANCE(A36,""currency"")"),"#N/A") -> #N/A | N36: =round(D36/AE36-1,4) -> #N/A | O36: =IFERROR(__xludf.DUMMYFUNCTION("GOOGLEFINANCE(A36,""Change"")"),"#N/A") -> #N/A | P36: =IFERROR(__xludf.DUMMYFUNCTION("GOOGLEFINANCE(A36,""High"")"),"#N/A") -> #N/A | Q36: =IFERROR(__xludf.DUMMYFUNCTION("GOOGLEFINANCE(A36,""low"")"),"#N/A") -> #N/A | R36: =IFERROR(__xludf.DUMMYFUNCTION("abs(P36-Q36)/GOOGLEFINANCE(A36,""closeyest"")"),"#N/A") -> #N/A | S36: =D36/Y36-1 -> #N/A | T36: ='Virtual Portfolio'!T39 -> 2.5 | U36: ='Virtual Portfolio'!U39 | W36: =IF(ISERROR(if(or(AND(Q36<=T36,T36<=P36),AND(Q36<=U36, U36<=P36)),"TRADE ALERT","")),"DATA UNAVAILABLE",if(or(AND(Q36<=T36,T36<=P36),T36>P36,AND(Q36<=U36, U36<=P36)),"TRADE ALERT"&" - Price level hit for "&A36&" currently at "&D36&" "&B36,"")) -> DATA UNAVAILABLE | X36: =IFERROR(__xludf.DUMMYFUNCTION("GOOGLEFINANCE($A36,X$3)"),"#N/A") -> #N/A | Y36: =IFERROR(__xludf.DUMMYFUNCTION("GOOGLEFINANCE($A36,Y$3)"),"#N/A") -> #N/A | Z36: =IFERROR(__xludf.DUMMYFUNCTION("GOOGLEFINANCE($A36,Z$3)"),"#N/A") -> #N/A | AA36: =IFERROR(__xludf.DUMMYFUNCTION("GOOGLEFINANCE($A36,AA$3)"),"#N/A") -> #N/A | AB36: =IFERROR(__xludf.DUMMYFUNCTION("GOOGLEFINANCE($A36,AB$3)"),"#N/A") -> #N/A | AC36: =IFERROR(__xludf.DUMMYFUNCTION("GOOGLEFINANCE($A36,AC$3)"),"#N/A") -> #N/A | AD36: =IFERROR(__xludf.DUMMYFUNCTION("GOOGLEFINANCE($A36,AD$3)"),"#N/A") -> #N/A | AE36: =IFERROR(__xludf.DUMMYFUNCTION("GOOGLEFINANCE($A36,AE$3)"),"#N/A") -> #N/A
A37: ='Virtual Portfolio'!A40 -> CPE | B37: =IFERROR(__xludf.DUMMYFUNCTION("GOOGLEFINANCE(A37,""name"")"),"Callon Petroleum Ord Shs") -> Callon Petroleum Ord Shs | C37: ='Virtual Portfolio'!C40 | D37: =IFERROR(__xludf.DUMMYFUNCTION("GOOGLEFINANCE(A37)"),0.0) -> 0 | K37: =(D37-E37)/E37 -> #DIV/0! | L37: =IFERROR(__xludf.DUMMYFUNCTION("SPARKLINE(GoogleFinance(A37, ""price"", TODAY()-30, TODAY()),{""color"",""blue"";""linewidth"",2}) "),"#N/A") -> #N/A | M37: =IFERROR(__xludf.DUMMYFUNCTION("GOOGLEFINANCE(A37,""currency"")"),"MXN") -> MXN | N37: =round(D37/AE37-1,4) -> -1 | O37: =IFERROR(__xludf.DUMMYFUNCTION("GOOGLEFINANCE(A37,""Change"")"),-557.0) -> -557 | P37: =IFERROR(__xludf.DUMMYFUNCTION("GOOGLEFINANCE(A37,""High"")"),"#N/A") -> #N/A | Q37: =IFERROR(__xludf.DUMMYFUNCTION("GOOGLEFINANCE(A37,""low"")"),"#N/A") -> #N/A | R37: =IFERROR(__xludf.DUMMYFUNCTION("abs(P37-Q37)/GOOGLEFINANCE(A37,""closeyest"")"),"#N/A") -> #N/A | S37: =D37/Y37-1 -> -1 | T37: ='Virtual Portfolio'!T40 -> 1 | U37: ='Virtual Portfolio'!U40 | W37: =IF(ISERROR(if(or(AND(Q37<=T37,T37<=P37),AND(Q37<=U37, U37<=P37)),"TRADE ALERT","")),"DATA UNAVAILABLE",if(or(AND(Q37<=T37,T37<=P37),T37>P37,AND(Q37<=U37, U37<=P37)),"TRADE ALERT"&" - Price level hit for "&A37&" currently at "&D37&" "&B37,"")) -> DATA UNAVAILABLE | X37: =IFERROR(__xludf.DUMMYFUNCTION("GOOGLEFINANCE($A37,X$3)"),"#N/A") -> #N/A | Y37: =IFERROR(__xludf.DUMMYFUNCTION("GOOGLEFINANCE($A37,Y$3)"),557.0) -> 557 | Z37: =IFERROR(__xludf.DUMMYFUNCTION("GOOGLEFINANCE($A37,Z$3)"),557.0) -> 557 | AA37: =IFERROR(__xludf.DUMMYFUNCTION("GOOGLEFINANCE($A37,AA$3)"),"#N/A") -> #N/A | AB37: =IFERROR(__xludf.DUMMYFUNCTION("GOOGLEFINANCE($A37,AB$3)"),"#N/A") -> #N/A | AC37: =IFERROR(__xludf.DUMMYFUNCTION("GOOGLEFINANCE($A37,AC$3)"),20.0) -> 20 | AD37: =IFERROR(__xludf.DUMMYFUNCTION("GOOGLEFINANCE($A37,AD$3)"),"#N/A") -> #N/A | AE37: =IFERROR(__xludf.DUMMYFUNCTION("GOOGLEFINANCE($A37,AE$3)"),557.0) -> 557
A38: ='Virtual Portfolio'!A41 -> LLOY | B38: =IFERROR(__xludf.DUMMYFUNCTION("GOOGLEFINANCE(A38,""name"")"),"Lloyds Banking Group PLC") -> Lloyds Banking Group PLC | C38: ='Virtual Portfolio'!C41 | D38: =IFERROR(__xludf.DUMMYFUNCTION("GOOGLEFINANCE(A38)"),101.85) -> 101.85 | K38: =(D38-E38)/E38 -> #DIV/0! | L38: =IFERROR(__xludf.DUMMYFUNCTION("SPARKLINE(GoogleFinance(A38, ""price"", TODAY()-30, TODAY()),{""color"",""blue"";""linewidth"",2}) "),"") | M38: =IFERROR(__xludf.DUMMYFUNCTION("GOOGLEFINANCE(A38,""currency"")"),"GBX") -> GBX | N38: =round(D38/AE38-1,4) -> 0.0044 | O38: =IFERROR(__xludf.DUMMYFUNCTION("GOOGLEFINANCE(A38,""Change"")"),0.45) -> 0.45 | P38: =IFERROR(__xludf.DUMMYFUNCTION("GOOGLEFINANCE(A38,""High"")"),102.75) -> 102.75 | Q38: =IFERROR(__xludf.DUMMYFUNCTION("GOOGLEFINANCE(A38,""low"")"),100.6) -> 100.6 | R38: =IFERROR(__xludf.DUMMYFUNCTION("abs(P38-Q38)/GOOGLEFINANCE(A38,""closeyest"")"),0.02120315581854049) -> 0.021203156 | S38: =D38/Y38-1 -> 0.6757157 | T38: ='Virtual Portfolio'!T41 -> 30 | U38: ='Virtual Portfolio'!U41 | W38: =IF(ISERROR(if(or(AND(Q38<=T38,T38<=P38),AND(Q38<=U38, U38<=P38)),"TRADE ALERT","")),"DATA UNAVAILABLE",if(or(AND(Q38<=T38,T38<=P38),T38>P38,AND(Q38<=U38, U38<=P38)),"TRADE ALERT"&" - Price level hit for "&A38&" currently at "&D38&" "&B38,"")) | X38: =IFERROR(__xludf.DUMMYFUNCTION("GOOGLEFINANCE($A38,X$3)"),"#N/A") -> #N/A | Y38: =IFERROR(__xludf.DUMMYFUNCTION("GOOGLEFINANCE($A38,Y$3)"),60.78) -> 60.78 | Z38: =IFERROR(__xludf.DUMMYFUNCTION("GOOGLEFINANCE($A38,Z$3)"),114.6) -> 114.6 | AA38: =IFERROR(__xludf.DUMMYFUNCTION("GOOGLEFINANCE($A38,AA$3)"),"#N/A") -> #N/A | AB38: =IFERROR(__xludf.DUMMYFUNCTION("GOOGLEFINANCE($A38,AB$3)"),"#N/A") -> #N/A | AC38: =IFERROR(__xludf.DUMMYFUNCTION("GOOGLEFINANCE($A38,AC$3)"),0.0) -> 0 | AD38: =IFERROR(__xludf.DUMMYFUNCTION("GOOGLEFINANCE($A38,AD$3)"),8.2759581393E10) -> 82759581393 | AE38: =IFERROR(__xludf.DUMMYFUNCTION("GOOGLEFINANCE($A38,AE$3)"),101.4) -> 101.4
A39: ='Virtual Portfolio'!A42 -> TED | B39: =IFERROR(__xludf.DUMMYFUNCTION("GOOGLEFINANCE(A39,""name"")"),"Terrascend Corp") -> Terrascend Corp | C39: ='Virtual Portfolio'!C42 | D39: =IFERROR(__xludf.DUMMYFUNCTION("GOOGLEFINANCE(A39)"),0.47) -> 0.47 | K39: =(D39-E39)/E39 -> #DIV/0! | L39: =IFERROR(__xludf.DUMMYFUNCTION("SPARKLINE(GoogleFinance(A39, ""price"", TODAY()-30, TODAY()),{""color"",""blue"";""linewidth"",2}) "),"") | M39: =IFERROR(__xludf.DUMMYFUNCTION("GOOGLEFINANCE(A39,""currency"")"),"EUR") -> EUR | N39: =round(D39/AE39-1,4) -> 0 | O39: =IFERROR(__xludf.DUMMYFUNCTION("GOOGLEFINANCE(A39,""Change"")"),0.0) -> 0 | P39: =IFERROR(__xludf.DUMMYFUNCTION("GOOGLEFINANCE(A39,""High"")"),0.49) -> 0.49 | Q39: =IFERROR(__xludf.DUMMYFUNCTION("GOOGLEFINANCE(A39,""low"")"),0.47) -> 0.47 | R39: =IFERROR(__xludf.DUMMYFUNCTION("abs(P39-Q39)/GOOGLEFINANCE(A39,""closeyest"")"),0.04255319148936174) -> 0.042553191 | S39: =D39/Y39-1 -> 1.7647059 | T39: ='Virtual Portfolio'!T42 -> 75 | U39: ='Virtual Portfolio'!U42 | W39: =IF(ISERROR(if(or(AND(Q39<=T39,T39<=P39),AND(Q39<=U39, U39<=P39)),"TRADE ALERT","")),"DATA UNAVAILABLE",if(or(AND(Q39<=T39,T39<=P39),T39>P39,AND(Q39<=U39, U39<=P39)),"TRADE ALERT"&" - Price level hit for "&A39&" currently at "&D39&" "&B39,"")) -> TRADE ALERT - Price level hit for TED currently at 0.47 Terrascend Corp | X39: =IFERROR(__xludf.DUMMYFUNCTION("GOOGLEFINANCE($A39,X$3)"),"#N/A") -> #N/A | Y39: =IFERROR(__xludf.DUMMYFUNCTION("GOOGLEFINANCE($A39,Y$3)"),0.17) -> 0.17 | Z39: =IFERROR(__xludf.DUMMYFUNCTION("GOOGLEFINANCE($A39,Z$3)"),1.09) -> 1.09 | AA39: =IFERROR(__xludf.DUMMYFUNCTION("GOOGLEFINANCE($A39,AA$3)"),"#N/A") -> #N/A | AB39: =IFERROR(__xludf.DUMMYFUNCTION("GOOGLEFINANCE($A39,AB$3)"),"#N/A") -> #N/A | AC39: =IFERROR(__xludf.DUMMYFUNCTION("GOOGLEFINANCE($A39,AC$3)"),15.0) -> 15 | AD39: =IFERROR(__xludf.DUMMYFUNCTION("GOOGLEFINANCE($A39,AD$3)"),3.01350132E8) -> 301350132 | AE39: =IFERROR(__xludf.DUMMYFUNCTION("GOOGLEFINANCE($A39,AE$3)"),0.47) -> 0.47
A40: ='Virtual Portfolio'!A43 -> KO | B40: =IFERROR(__xludf.DUMMYFUNCTION("GOOGLEFINANCE(A40,""name"")"),"Coca-Cola Co") -> Coca-Cola Co | C40: ='Virtual Portfolio'!C43 | D40: =IFERROR(__xludf.DUMMYFUNCTION("GOOGLEFINANCE(A40)"),79.37) -> 79.37 | K40: =(D40-E40)/E40 -> #DIV/0! | L40: =IFERROR(__xludf.DUMMYFUNCTION("SPARKLINE(GoogleFinance(A40, ""price"", TODAY()-30, TODAY()),{""color"",""blue"";""linewidth"",2}) "),"") | M40: =IFERROR(__xludf.DUMMYFUNCTION("GOOGLEFINANCE(A40,""currency"")"),"USD") -> USD | N40: =round(D40/AE40-1,4) -> 0.0088 | O40: =IFERROR(__xludf.DUMMYFUNCTION("GOOGLEFINANCE(A40,""Change"")"),0.69) -> 0.69 | P40: =IFERROR(__xludf.DUMMYFUNCTION("GOOGLEFINANCE(A40,""High"")"),79.54) -> 79.54 | Q40: =IFERROR(__xludf.DUMMYFUNCTION("GOOGLEFINANCE(A40,""low"")"),78.74) -> 78.74 | R40: =IFERROR(__xludf.DUMMYFUNCTION("abs(P40-Q40)/GOOGLEFINANCE(A40,""closeyest"")"),0.010167768174885756) -> 0.010167768 | S40: =D40/Y40-1 -> 0.21453711 | T40: ='Virtual Portfolio'!T43 -> 40 | U40: ='Virtual Portfolio'!U43 | W40: =IF(ISERROR(if(or(AND(Q40<=T40,T40<=P40),AND(Q40<=U40, U40<=P40)),"TRADE ALERT","")),"DATA UNAVAILABLE",if(or(AND(Q40<=T40,T40<=P40),T40>P40,AND(Q40<=U40, U40<=P40)),"TRADE ALERT"&" - Price level hit for "&A40&" currently at "&D40&" "&B40,"")) | X40: =IFERROR(__xludf.DUMMYFUNCTION("GOOGLEFINANCE($A40,X$3)"),0.36) -> 0.36 | Y40: =IFERROR(__xludf.DUMMYFUNCTION("GOOGLEFINANCE($A40,Y$3)"),65.35) -> 65.35 | Z40: =IFERROR(__xludf.DUMMYFUNCTION("GOOGLEFINANCE($A40,Z$3)"),80.41) -> 80.41 | AA40: =IFERROR(__xludf.DUMMYFUNCTION("GOOGLEFINANCE($A40,AA$3)"),"#N/A") -> #N/A | AB40: =IFERROR(__xludf.DUMMYFUNCTION("GOOGLEFINANCE($A40,AB$3)"),26.12) -> 26.12 | AC40: =IFERROR(__xludf.DUMMYFUNCTION("GOOGLEFINANCE($A40,AC$3)"),0.0) -> 0 | AD40: =IFERROR(__xludf.DUMMYFUNCTION("GOOGLEFINANCE($A40,AD$3)"),3.41440214375E11) -> 341440214375 | AE40: =IFERROR(__xludf.DUMMYFUNCTION("GOOGLEFINANCE($A40,AE$3)"),78.68) -> 78.68
A41: ='Virtual Portfolio'!A44 -> DIS | B41: =IFERROR(__xludf.DUMMYFUNCTION("GOOGLEFINANCE(A41,""name"")"),"Walt Disney Co") -> Walt Disney Co | C41: ='Virtual Portfolio'!C44 | D41: =IFERROR(__xludf.DUMMYFUNCTION("GOOGLEFINANCE(A41)"),105.69) -> 105.69 | K41: =(D41-E41)/E41 -> #DIV/0! | L41: =IFERROR(__xludf.DUMMYFUNCTION("SPARKLINE(GoogleFinance(A41, ""price"", TODAY()-30, TODAY()),{""color"",""blue"";""linewidth"",2}) "),"") | M41: =IFERROR(__xludf.DUMMYFUNCTION("GOOGLEFINANCE(A41,""currency"")"),"USD") -> USD | N41: =round(D41/AE41-1,4) -> 0.0023 | O41: =IFERROR(__xludf.DUMMYFUNCTION("GOOGLEFINANCE(A41,""Change"")"),0.24) -> 0.24 | P41: =IFERROR(__xludf.DUMMYFUNCTION("GOOGLEFINANCE(A41,""High"")"),107.28) -> 107.28 | Q41: =IFERROR(__xludf.DUMMYFUNCTION("GOOGLEFINANCE(A41,""low"")"),104.37) -> 104.37 | R41: =IFERROR(__xludf.DUMMYFUNCTION("abs(P41-Q41)/GOOGLEFINANCE(A41,""closeyest"")"),0.02759601706970125) -> 0.027596017 | S41: =D41/Y41-1 -> 0.31947566 | T41: ='Virtual Portfolio'!T44 -> 100 | U41: ='Virtual Portfolio'!U44 | W41: =IF(ISERROR(if(or(AND(Q41<=T41,T41<=P41),AND(Q41<=U41, U41<=P41)),"TRADE ALERT","")),"DATA UNAVAILABLE",if(or(AND(Q41<=T41,T41<=P41),T41>P41,AND(Q41<=U41, U41<=P41)),"TRADE ALERT"&" - Price level hit for "&A41&" currently at "&D41&" "&B41,"")) | X41: =IFERROR(__xludf.DUMMYFUNCTION("GOOGLEFINANCE($A41,X$3)"),1.43) -> 1.43 | Y41: =IFERROR(__xludf.DUMMYFUNCTION("GOOGLEFINANCE($A41,Y$3)"),80.1) -> 80.1 | Z41: =IFERROR(__xludf.DUMMYFUNCTION("GOOGLEFINANCE($A41,Z$3)"),124.69) -> 124.69 | AA41: =IFERROR(__xludf.DUMMYFUNCTION("GOOGLEFINANCE($A41,AA$3)"),"#N/A") -> #N/A | AB41: =IFERROR(__xludf.DUMMYFUNCTION("GOOGLEFINANCE($A41,AB$3)"),15.57) -> 15.57 | AC41: =IFERROR(__xludf.DUMMYFUNCTION("GOOGLEFINANCE($A41,AC$3)"),0.0) -> 0 | AD41: =IFERROR(__xludf.DUMMYFUNCTION("GOOGLEFINANCE($A41,AD$3)"),1.87231953125E11) -> 187231953125 | AE41: =IFERROR(__xludf.DUMMYFUNCTION("GOOGLEFINANCE($A41,AE$3)"),105.45) -> 105.45
A42: ='Virtual Portfolio'!A45 -> NKE | B42: =IFERROR(__xludf.DUMMYFUNCTION("GOOGLEFINANCE(A42,""name"")"),"Nike Inc") -> Nike Inc | C42: ='Virtual Portfolio'!C45 | D42: =IFERROR(__xludf.DUMMYFUNCTION("GOOGLEFINANCE(A42)"),64.37) -> 64.37 | K42: =(D42-E42)/E42 -> #DIV/0! | L42: =IFERROR(__xludf.DUMMYFUNCTION("SPARKLINE(GoogleFinance(A42, ""price"", TODAY()-30, TODAY()),{""color"",""blue"";""linewidth"",2}) "),"") | M42: =IFERROR(__xludf.DUMMYFUNCTION("GOOGLEFINANCE(A42,""currency"")"),"USD") -> USD | N42: =round(D42/AE42-1,4) -> 0.0196 | O42: =IFERROR(__xludf.DUMMYFUNCTION("GOOGLEFINANCE(A42,""Change"")"),1.24) -> 1.24 | P42: =IFERROR(__xludf.DUMMYFUNCTION("GOOGLEFINANCE(A42,""High"")"),64.38) -> 64.38 | Q42: =IFERROR(__xludf.DUMMYFUNCTION("GOOGLEFINANCE(A42,""low"")"),62.94) -> 62.94 | R42: =IFERROR(__xludf.DUMMYFUNCTION("abs(P42-Q42)/GOOGLEFINANCE(A42,""closeyest"")"),0.022810074449548513) -> 0.022810074 | S42: =D42/Y42-1 -> 0.23125478 | T42: ='Virtual Portfolio'!T45 -> 70 | U42: ='Virtual Portfolio'!U45 | W42: =IF(ISERROR(if(or(AND(Q42<=T42,T42<=P42),AND(Q42<=U42, U42<=P42)),"TRADE ALERT","")),"DATA UNAVAILABLE",if(or(AND(Q42<=T42,T42<=P42),T42>P42,AND(Q42<=U42, U42<=P42)),"TRADE ALERT"&" - Price level hit for "&A42&" currently at "&D42&" "&B42,"")) -> TRADE ALERT - Price level hit for NKE currently at 64.37 Nike Inc | X42: =IFERROR(__xludf.DUMMYFUNCTION("GOOGLEFINANCE($A42,X$3)"),1.27) -> 1.27 | Y42: =IFERROR(__xludf.DUMMYFUNCTION("GOOGLEFINANCE($A42,Y$3)"),52.28) -> 52.28 | Z42: =IFERROR(__xludf.DUMMYFUNCTION("GOOGLEFINANCE($A42,Z$3)"),82.44) -> 82.44 | AA42: =IFERROR(__xludf.DUMMYFUNCTION("GOOGLEFINANCE($A42,AA$3)"),"#N/A") -> #N/A | AB42: =IFERROR(__xludf.DUMMYFUNCTION("GOOGLEFINANCE($A42,AB$3)"),37.77) -> 37.77 | AC42: =IFERROR(__xludf.DUMMYFUNCTION("GOOGLEFINANCE($A42,AC$3)"),0.0) -> 0 | AD42: =IFERROR(__xludf.DUMMYFUNCTION("GOOGLEFINANCE($A42,AD$3)"),9.5292257775E10) -> 95292257775 | AE42: =IFERROR(__xludf.DUMMYFUNCTION("GOOGLEFINANCE($A42,AE$3)"),63.13) -> 63.13
A43: ='Virtual Portfolio'!A46 -> PEP | B43: =IFERROR(__xludf.DUMMYFUNCTION("GOOGLEFINANCE(A43,""name"")"),"PepsiCo Inc") -> PepsiCo Inc | C43: ='Virtual Portfolio'!C46 | D43: =IFERROR(__xludf.DUMMYFUNCTION("GOOGLEFINANCE(A43)"),161.45) -> 161.45 | K43: =(D43-E43)/E43 -> #DIV/0! | L43: =IFERROR(__xludf.DUMMYFUNCTION("SPARKLINE(GoogleFinance(A43, ""price"", TODAY()-30, TODAY()),{""color"",""blue"";""linewidth"",2}) "),"") | M43: =IFERROR(__xludf.DUMMYFUNCTION("GOOGLEFINANCE(A43,""currency"")"),"USD") -> USD | N43: =round(D43/AE43-1,4) -> -0.0271 | O43: =IFERROR(__xludf.DUMMYFUNCTION("GOOGLEFINANCE(A43,""Change"")"),-4.49) -> -4.49 | P43: =IFERROR(__xludf.DUMMYFUNCTION("GOOGLEFINANCE(A43,""High"")"),167.54) -> 167.54 | Q43: =IFERROR(__xludf.DUMMYFUNCTION("GOOGLEFINANCE(A43,""low"")"),160.81) -> 160.81 | R43: =IFERROR(__xludf.DUMMYFUNCTION("abs(P43-Q43)/GOOGLEFINANCE(A43,""closeyest"")"),0.0405568277690731) -> 0.040556828 | S43: =D43/Y43-1 -> 0.26528213 | T43: 110 | W43: =IF(ISERROR(if(or(AND(Q43<=T43,T43<=P43),AND(Q43<=U43, U43<=P43)),"TRADE ALERT","")),"DATA UNAVAILABLE",if(or(AND(Q43<=T43,T43<=P43),T43>P43,AND(Q43<=U43, U43<=P43)),"TRADE ALERT"&" - Price level hit for "&A43&" currently at "&D43&" "&B43,"")) | X43: =IFERROR(__xludf.DUMMYFUNCTION("GOOGLEFINANCE($A43,X$3)"),0.4) -> 0.4 | Y43: =IFERROR(__xludf.DUMMYFUNCTION("GOOGLEFINANCE($A43,Y$3)"),127.6) -> 127.6 | Z43: =IFERROR(__xludf.DUMMYFUNCTION("GOOGLEFINANCE($A43,Z$3)"),171.48) -> 171.48 | AA43: =IFERROR(__xludf.DUMMYFUNCTION("GOOGLEFINANCE($A43,AA$3)"),"#N/A") -> #N/A | AB43: =IFERROR(__xludf.DUMMYFUNCTION("GOOGLEFINANCE($A43,AB$3)"),26.9) -> 26.9 | AC43: =IFERROR(__xludf.DUMMYFUNCTION("GOOGLEFINANCE($A43,AC$3)"),0.0) -> 0 | AD43: =IFERROR(__xludf.DUMMYFUNCTION("GOOGLEFINANCE($A43,AD$3)"),2.20590820094E11) -> 220590820094 | AE43: =IFERROR(__xludf.DUMMYFUNCTION("GOOGLEFINANCE($A43,AE$3)"),165.94) -> 165.94
A44: ='Virtual Portfolio'!A47 | B44: =IFERROR(__xludf.DUMMYFUNCTION("GOOGLEFINANCE(A44,""name"")"),"#N/A") -> #N/A | C44: ='Virtual Portfolio'!C47 | D44: =IFERROR(__xludf.DUMMYFUNCTION("GOOGLEFINANCE(A44)"),"#N/A") -> #N/A | K44: =(D44-E44)/E44 -> #N/A | L44: =IFERROR(__xludf.DUMMYFUNCTION("SPARKLINE(GoogleFinance(A44, ""price"", TODAY()-30, TODAY()),{""color"",""blue"";""linewidth"",2}) "),"#N/A") -> #N/A | M44: =IFERROR(__xludf.DUMMYFUNCTION("GOOGLEFINANCE(A44,""currency"")"),"#N/A") -> #N/A | N44: =round(D44/AE44-1,4) -> #N/A | O44: =IFERROR(__xludf.DUMMYFUNCTION("GOOGLEFINANCE(A44,""Change"")"),"#N/A") -> #N/A | P44: =IFERROR(__xludf.DUMMYFUNCTION("GOOGLEFINANCE(A44,""High"")"),"#N/A") -> #N/A | Q44: =IFERROR(__xludf.DUMMYFUNCTION("GOOGLEFINANCE(A44,""low"")"),"#N/A") -> #N/A | R44: =IFERROR(__xludf.DUMMYFUNCTION("abs(P44-Q44)/GOOGLEFINANCE(A44,""closeyest"")"),"#N/A") -> #N/A | S44: =D44/Y44-1 -> #N/A | T44: ='Virtual Portfolio'!T47 | U44: ='Virtual Portfolio'!U47 | W44: =IF(ISERROR(if(or(AND(Q44<=T44,T44<=P44),AND(Q44<=U44, U44<=P44)),"TRADE ALERT","")),"DATA UNAVAILABLE",if(or(AND(Q44<=T44,T44<=P44),T44>P44,AND(Q44<=U44, U44<=P44)),"TRADE ALERT"&" - Price level hit for "&A44&" currently at "&D44&" "&B44,"")) -> DATA UNAVAILABLE | X44: =IFERROR(__xludf.DUMMYFUNCTION("GOOGLEFINANCE($A44,X$3)"),"#N/A") -> #N/A | Y44: =IFERROR(__xludf.DUMMYFUNCTION("GOOGLEFINANCE($A44,Y$3)"),"#N/A") -> #N/A | Z44: =IFERROR(__xludf.DUMMYFUNCTION("GOOGLEFINANCE($A44,Z$3)"),"#N/A") -> #N/A | AA44: =IFERROR(__xludf.DUMMYFUNCTION("GOOGLEFINANCE($A44,AA$3)"),"#N/A") -> #N/A | AB44: =IFERROR(__xludf.DUMMYFUNCTION("GOOGLEFINANCE($A44,AB$3)"),"#N/A") -> #N/A | AC44: =IFERROR(__xludf.DUMMYFUNCTION("GOOGLEFINANCE($A44,AC$3)"),"#N/A") -> #N/A | AD44: =IFERROR(__xludf.DUMMYFUNCTION("GOOGLEFINANCE($A44,AD$3)"),"#N/A") -> #N/A | AE44: =IFERROR(__xludf.DUMMYFUNCTION("GOOGLEFINANCE($A44,AE$3)"),"#N/A") -> #N/A
A45: ='Virtual Portfolio'!A48 | B45: =IFERROR(__xludf.DUMMYFUNCTION("GOOGLEFINANCE(A45,""name"")"),"#N/A") -> #N/A | C45: ='Virtual Portfolio'!C48 | D45: =IFERROR(__xludf.DUMMYFUNCTION("GOOGLEFINANCE(A45)"),"#N/A") -> #N/A | K45: =(D45-E45)/E45 -> #N/A | L45: =IFERROR(__xludf.DUMMYFUNCTION("SPARKLINE(GoogleFinance(A45, ""price"", TODAY()-30, TODAY()),{""color"",""blue"";""linewidth"",2}) "),"#N/A") -> #N/A | M45: =IFERROR(__xludf.DUMMYFUNCTION("GOOGLEFINANCE(A45,""currency"")"),"#N/A") -> #N/A | N45: =round(D45/AE45-1,4) -> #N/A | O45: =IFERROR(__xludf.DUMMYFUNCTION("GOOGLEFINANCE(A45,""Change"")"),"#N/A") -> #N/A | P45: =IFERROR(__xludf.DUMMYFUNCTION("GOOGLEFINANCE(A45,""High"")"),"#N/A") -> #N/A | Q45: =IFERROR(__xludf.DUMMYFUNCTION("GOOGLEFINANCE(A45,""low"")"),"#N/A") -> #N/A | R45: =IFERROR(__xludf.DUMMYFUNCTION("abs(P45-Q45)/GOOGLEFINANCE(A45,""closeyest"")"),"#N/A") -> #N/A | S45: =D45/Y45-1 -> #N/A | T45: ='Virtual Portfolio'!T48 | U45: ='Virtual Portfolio'!U48 | W45: =IF(ISERROR(if(or(AND(Q45<=T45,T45<=P45),AND(Q45<=U45, U45<=P45)),"TRADE ALERT","")),"DATA UNAVAILABLE",if(or(AND(Q45<=T45,T45<=P45),T45>P45,AND(Q45<=U45, U45<=P45)),"TRADE ALERT"&" - Price level hit for "&A45&" currently at "&D45&" "&B45,"")) -> DATA UNAVAILABLE | X45: =IFERROR(__xludf.DUMMYFUNCTION("GOOGLEFINANCE($A45,X$3)"),"#N/A") -> #N/A | Y45: =IFERROR(__xludf.DUMMYFUNCTION("GOOGLEFINANCE($A45,Y$3)"),"#N/A") -> #N/A | Z45: =IFERROR(__xludf.DUMMYFUNCTION("GOOGLEFINANCE($A45,Z$3)"),"#N/A") -> #N/A | AA45: =IFERROR(__xludf.DUMMYFUNCTION("GOOGLEFINANCE($A45,AA$3)"),"#N/A") -> #N/A | AB45: =IFERROR(__xludf.DUMMYFUNCTION("GOOGLEFINANCE($A45,AB$3)"),"#N/A") -> #N/A | AC45: =IFERROR(__xludf.DUMMYFUNCTION("GOOGLEFINANCE($A45,AC$3)"),"#N/A") -> #N/A | AD45: =IFERROR(__xludf.DUMMYFUNCTION("GOOGLEFINANCE($A45,AD$3)"),"#N/A") -> #N/A | AE45: =IFERROR(__xludf.DUMMYFUNCTION("GOOGLEFINANCE($A45,AE$3)"),"#N/A") -> #N/A
A46: ='Virtual Portfolio'!A49 | B46: =IFERROR(__xludf.DUMMYFUNCTION("GOOGLEFINANCE(A46,""name"")"),"#N/A") -> #N/A | C46: ='Virtual Portfolio'!C49 | D46: =IFERROR(__xludf.DUMMYFUNCTION("GOOGLEFINANCE(A46)"),"#N/A") -> #N/A | K46: =(D46-E46)/E46 -> #N/A | L46: =IFERROR(__xludf.DUMMYFUNCTION("SPARKLINE(GoogleFinance(A46, ""price"", TODAY()-30, TODAY()),{""color"",""blue"";""linewidth"",2}) "),"#N/A") -> #N/A | M46: =IFERROR(__xludf.DUMMYFUNCTION("GOOGLEFINANCE(A46,""currency"")"),"#N/A") -> #N/A | N46: =round(D46/AE46-1,4) -> #N/A | O46: =IFERROR(__xludf.DUMMYFUNCTION("GOOGLEFINANCE(A46,""Change"")"),"#N/A") -> #N/A | P46: =IFERROR(__xludf.DUMMYFUNCTION("GOOGLEFINANCE(A46,""High"")"),"#N/A") -> #N/A | Q46: =IFERROR(__xludf.DUMMYFUNCTION("GOOGLEFINANCE(A46,""low"")"),"#N/A") -> #N/A | R46: =IFERROR(__xludf.DUMMYFUNCTION("abs(P46-Q46)/GOOGLEFINANCE(A46,""closeyest"")"),"#N/A") -> #N/A | S46: =D46/Y46-1 -> #N/A | T46: ='Virtual Portfolio'!T49 | U46: ='Virtual Portfolio'!U49 | W46: =IF(ISERROR(if(or(AND(Q46<=T46,T46<=P46),AND(Q46<=U46, U46<=P46)),"TRADE ALERT","")),"DATA UNAVAILABLE",if(or(AND(Q46<=T46,T46<=P46),T46>P46,AND(Q46<=U46, U46<=P46)),"TRADE ALERT"&" - Price level hit for "&A46&" currently at "&D46&" "&B46,"")) -> DATA UNAVAILABLE | X46: =IFERROR(__xludf.DUMMYFUNCTION("GOOGLEFINANCE($A46,X$3)"),"#N/A") -> #N/A | Y46: =IFERROR(__xludf.DUMMYFUNCTION("GOOGLEFINANCE($A46,Y$3)"),"#N/A") -> #N/A | Z46: =IFERROR(__xludf.DUMMYFUNCTION("GOOGLEFINANCE($A46,Z$3)"),"#N/A") -> #N/A | AA46: =IFERROR(__xludf.DUMMYFUNCTION("GOOGLEFINANCE($A46,AA$3)"),"#N/A") -> #N/A | AB46: =IFERROR(__xludf.DUMMYFUNCTION("GOOGLEFINANCE($A46,AB$3)"),"#N/A") -> #N/A | AC46: =IFERROR(__xludf.DUMMYFUNCTION("GOOGLEFINANCE($A46,AC$3)"),"#N/A") -> #N/A | AD46: =IFERROR(__xludf.DUMMYFUNCTION("GOOGLEFINANCE($A46,AD$3)"),"#N/A") -> #N/A | AE46: =IFERROR(__xludf.DUMMYFUNCTION("GOOGLEFINANCE($A46,AE$3)"),"#N/A") -> #N/A
A47: ='Virtual Portfolio'!A50 | B47: =IFERROR(__xludf.DUMMYFUNCTION("GOOGLEFINANCE(A47,""name"")"),"#N/A") -> #N/A | C47: ='Virtual Portfolio'!C50 | D47: =IFERROR(__xludf.DUMMYFUNCTION("GOOGLEFINANCE(A47)"),"#N/A") -> #N/A | K47: =(D47-E47)/E47 -> #N/A | L47: =IFERROR(__xludf.DUMMYFUNCTION("SPARKLINE(GoogleFinance(A47, ""price"", TODAY()-30, TODAY()),{""color"",""blue"";""linewidth"",2}) "),"#N/A") -> #N/A | M47: =IFERROR(__xludf.DUMMYFUNCTION("GOOGLEFINANCE(A47,""currency"")"),"#N/A") -> #N/A | N47: =round(D47/AE47-1,4) -> #N/A | O47: =IFERROR(__xludf.DUMMYFUNCTION("GOOGLEFINANCE(A47,""Change"")"),"#N/A") -> #N/A | P47: =IFERROR(__xludf.DUMMYFUNCTION("GOOGLEFINANCE(A47,""High"")"),"#N/A") -> #N/A | Q47: =IFERROR(__xludf.DUMMYFUNCTION("GOOGLEFINANCE(A47,""low"")"),"#N/A") -> #N/A | R47: =IFERROR(__xludf.DUMMYFUNCTION("abs(P47-Q47)/GOOGLEFINANCE(A47,""closeyest"")"),"#N/A") -> #N/A | S47: =D47/Y47-1 -> #N/A | T47: ='Virtual Portfolio'!T50 | U47: ='Virtual Portfolio'!U50 | W47: =IF(ISERROR(if(or(AND(Q47<=T47,T47<=P47),AND(Q47<=U47, U47<=P47)),"TRADE ALERT","")),"DATA UNAVAILABLE",if(or(AND(Q47<=T47,T47<=P47),T47>P47,AND(Q47<=U47, U47<=P47)),"TRADE ALERT"&" - Price level hit for "&A47&" currently at "&D47&" "&B47,"")) -> DATA UNAVAILABLE | X47: =IFERROR(__xludf.DUMMYFUNCTION("GOOGLEFINANCE($A47,X$3)"),"#N/A") -> #N/A | Y47: =IFERROR(__xludf.DUMMYFUNCTION("GOOGLEFINANCE($A47,Y$3)"),"#N/A") -> #N/A | Z47: =IFERROR(__xludf.DUMMYFUNCTION("GOOGLEFINANCE($A47,Z$3)"),"#N/A") -> #N/A | AA47: =IFERROR(__xludf.DUMMYFUNCTION("GOOGLEFINANCE($A47,AA$3)"),"#N/A") -> #N/A | AB47: =IFERROR(__xludf.DUMMYFUNCTION("GOOGLEFINANCE($A47,AB$3)"),"#N/A") -> #N/A | AC47: =IFERROR(__xludf.DUMMYFUNCTION("GOOGLEFINANCE($A47,AC$3)"),"#N/A") -> #N/A | AD47: =IFERROR(__xludf.DUMMYFUNCTION("GOOGLEFINANCE($A47,AD$3)"),"#N/A") -> #N/A | AE47: =IFERROR(__xludf.DUMMYFUNCTION("GOOGLEFINANCE($A47,AE$3)"),"#N/A") -> #N/A
A48: ='Virtual Portfolio'!A51 | B48: =IFERROR(__xludf.DUMMYFUNCTION("GOOGLEFINANCE(A48,""name"")"),"#N/A") -> #N/A | C48: ='Virtual Portfolio'!C51 | D48: =IFERROR(__xludf.DUMMYFUNCTION("GOOGLEFINANCE(A48)"),"#N/A") -> #N/A | K48: =(D48-E48)/E48 -> #N/A | L48: =IFERROR(__xludf.DUMMYFUNCTION("SPARKLINE(GoogleFinance(A48, ""price"", TODAY()-30, TODAY()),{""color"",""blue"";""linewidth"",2}) "),"#N/A") -> #N/A | M48: =IFERROR(__xludf.DUMMYFUNCTION("GOOGLEFINANCE(A48,""currency"")"),"#N/A") -> #N/A | N48: =round(D48/AE48-1,4) -> #N/A | O48: =IFERROR(__xludf.DUMMYFUNCTION("GOOGLEFINANCE(A48,""Change"")"),"#N/A") -> #N/A | P48: =IFERROR(__xludf.DUMMYFUNCTION("GOOGLEFINANCE(A48,""High"")"),"#N/A") -> #N/A | Q48: =IFERROR(__xludf.DUMMYFUNCTION("GOOGLEFINANCE(A48,""low"")"),"#N/A") -> #N/A | R48: =IFERROR(__xludf.DUMMYFUNCTION("abs(P48-Q48)/GOOGLEFINANCE(A48,""closeyest"")"),"#N/A") -> #N/A | S48: =D48/Y48-1 -> #N/A | T48: ='Virtual Portfolio'!T51 | U48: ='Virtual Portfolio'!U51 | W48: =IF(ISERROR(if(or(AND(Q48<=T48,T48<=P48),AND(Q48<=U48, U48<=P48)),"TRADE ALERT","")),"DATA UNAVAILABLE",if(or(AND(Q48<=T48,T48<=P48),T48>P48,AND(Q48<=U48, U48<=P48)),"TRADE ALERT"&" - Price level hit for "&A48&" currently at "&D48&" "&B48,"")) -> DATA UNAVAILABLE | X48: =IFERROR(__xludf.DUMMYFUNCTION("GOOGLEFINANCE($A48,X$3)"),"#N/A") -> #N/A | Y48: =IFERROR(__xludf.DUMMYFUNCTION("GOOGLEFINANCE($A48,Y$3)"),"#N/A") -> #N/A | Z48: =IFERROR(__xludf.DUMMYFUNCTION("GOOGLEFINANCE($A48,Z$3)"),"#N/A") -> #N/A | AA48: =IFERROR(__xludf.DUMMYFUNCTION("GOOGLEFINANCE($A48,AA$3)"),"#N/A") -> #N/A | AB48: =IFERROR(__xludf.DUMMYFUNCTION("GOOGLEFINANCE($A48,AB$3)"),"#N/A") -> #N/A | AC48: =IFERROR(__xludf.DUMMYFUNCTION("GOOGLEFINANCE($A48,AC$3)"),"#N/A") -> #N/A | AD48: =IFERROR(__xludf.DUMMYFUNCTION("GOOGLEFINANCE($A48,AD$3)"),"#N/A") -> #N/A | AE48: =IFERROR(__xludf.DUMMYFUNCTION("GOOGLEFINANCE($A48,AE$3)"),"#N/A") -> #N/A
A49: ='Virtual Portfolio'!A52 | B49: =IFERROR(__xludf.DUMMYFUNCTION("GOOGLEFINANCE(A49,""name"")"),"#N/A") -> #N/A | C49: ='Virtual Portfolio'!C52 | D49: =IFERROR(__xludf.DUMMYFUNCTION("GOOGLEFINANCE(A49)"),"#N/A") -> #N/A | K49: =(D49-E49)/E49 -> #N/A | L49: =IFERROR(__xludf.DUMMYFUNCTION("SPARKLINE(GoogleFinance(A49, ""price"", TODAY()-30, TODAY()),{""color"",""blue"";""linewidth"",2}) "),"#N/A") -> #N/A | M49: =IFERROR(__xludf.DUMMYFUNCTION("GOOGLEFINANCE(A49,""currency"")"),"#N/A") -> #N/A | N49: =round(D49/AE49-1,4) -> #N/A | O49: =IFERROR(__xludf.DUMMYFUNCTION("GOOGLEFINANCE(A49,""Change"")"),"#N/A") -> #N/A | P49: =IFERROR(__xludf.DUMMYFUNCTION("GOOGLEFINANCE(A49,""High"")"),"#N/A") -> #N/A | Q49: =IFERROR(__xludf.DUMMYFUNCTION("GOOGLEFINANCE(A49,""low"")"),"#N/A") -> #N/A | R49: =IFERROR(__xludf.DUMMYFUNCTION("abs(P49-Q49)/GOOGLEFINANCE(A49,""closeyest"")"),"#N/A") -> #N/A | S49: =D49/Y49-1 -> #N/A | T49: ='Virtual Portfolio'!T52 | U49: ='Virtual Portfolio'!U52 | W49: =IF(ISERROR(if(or(AND(Q49<=T49,T49<=P49),AND(Q49<=U49, U49<=P49)),"TRADE ALERT","")),"DATA UNAVAILABLE",if(or(AND(Q49<=T49,T49<=P49),T49>P49,AND(Q49<=U49, U49<=P49)),"TRADE ALERT"&" - Price level hit for "&A49&" currently at "&D49&" "&B49,"")) -> DATA UNAVAILABLE | X49: =IFERROR(__xludf.DUMMYFUNCTION("GOOGLEFINANCE($A49,X$3)"),"#N/A") -> #N/A | Y49: =IFERROR(__xludf.DUMMYFUNCTION("GOOGLEFINANCE($A49,Y$3)"),"#N/A") -> #N/A | Z49: =IFERROR(__xludf.DUMMYFUNCTION("GOOGLEFINANCE($A49,Z$3)"),"#N/A") -> #N/A | AA49: =IFERROR(__xludf.DUMMYFUNCTION("GOOGLEFINANCE($A49,AA$3)"),"#N/A") -> #N/A | AB49: =IFERROR(__xludf.DUMMYFUNCTION("GOOGLEFINANCE($A49,AB$3)"),"#N/A") -> #N/A | AC49: =IFERROR(__xludf.DUMMYFUNCTION("GOOGLEFINANCE($A49,AC$3)"),"#N/A") -> #N/A | AD49: =IFERROR(__xludf.DUMMYFUNCTION("GOOGLEFINANCE($A49,AD$3)"),"#N/A") -> #N/A | AE49: =IFERROR(__xludf.DUMMYFUNCTION("GOOGLEFINANCE($A49,AE$3)"),"#N/A") -> #N/A
A50: ='Virtual Portfolio'!A53 | B50: =IFERROR(__xludf.DUMMYFUNCTION("GOOGLEFINANCE(A50,""name"")"),"#N/A") -> #N/A | C50: ='Virtual Portfolio'!C53 | D50: =IFERROR(__xludf.DUMMYFUNCTION("GOOGLEFINANCE(A50)"),"#N/A") -> #N/A | K50: =(D50-E50)/E50 -> #N/A | L50: =IFERROR(__xludf.DUMMYFUNCTION("SPARKLINE(GoogleFinance(A50, ""price"", TODAY()-30, TODAY()),{""color"",""blue"";""linewidth"",2}) "),"#N/A") -> #N/A | M50: =IFERROR(__xludf.DUMMYFUNCTION("GOOGLEFINANCE(A50,""currency"")"),"#N/A") -> #N/A | N50: =round(D50/AE50-1,4) -> #N/A | O50: =IFERROR(__xludf.DUMMYFUNCTION("GOOGLEFINANCE(A50,""Change"")"),"#N/A") -> #N/A | P50: =IFERROR(__xludf.DUMMYFUNCTION("GOOGLEFINANCE(A50,""High"")"),"#N/A") -> #N/A | Q50: =IFERROR(__xludf.DUMMYFUNCTION("GOOGLEFINANCE(A50,""low"")"),"#N/A") -> #N/A | R50: =IFERROR(__xludf.DUMMYFUNCTION("abs(P50-Q50)/GOOGLEFINANCE(A50,""closeyest"")"),"#N/A") -> #N/A | S50: =D50/Y50-1 -> #N/A | T50: ='Virtual Portfolio'!T53 | U50: ='Virtual Portfolio'!U53 | W50: =IF(ISERROR(if(or(AND(Q50<=T50,T50<=P50),AND(Q50<=U50, U50<=P50)),"TRADE ALERT","")),"DATA UNAVAILABLE",if(or(AND(Q50<=T50,T50<=P50),T50>P50,AND(Q50<=U50, U50<=P50)),"TRADE ALERT"&" - Price level hit for "&A50&" currently at "&D50&" "&B50,"")) -> DATA UNAVAILABLE | X50: =IFERROR(__xludf.DUMMYFUNCTION("GOOGLEFINANCE($A50,X$3)"),"#N/A") -> #N/A | Y50: =IFERROR(__xludf.DUMMYFUNCTION("GOOGLEFINANCE($A50,Y$3)"),"#N/A") -> #N/A | Z50: =IFERROR(__xludf.DUMMYFUNCTION("GOOGLEFINANCE($A50,Z$3)"),"#N/A") -> #N/A | AA50: =IFERROR(__xludf.DUMMYFUNCTION("GOOGLEFINANCE($A50,AA$3)"),"#N/A") -> #N/A | AB50: =IFERROR(__xludf.DUMMYFUNCTION("GOOGLEFINANCE($A50,AB$3)"),"#N/A") -> #N/A | AC50: =IFERROR(__xludf.DUMMYFUNCTION("GOOGLEFINANCE($A50,AC$3)"),"#N/A") -> #N/A | AD50: =IFERROR(__xludf.DUMMYFUNCTION("GOOGLEFINANCE($A50,AD$3)"),"#N/A") -> #N/A | AE50: =IFERROR(__xludf.DUMMYFUNCTION("GOOGLEFINANCE($A50,AE$3)"),"#N/A") -> #N/A
A51: ='Virtual Portfolio'!A54 | B51: =IFERROR(__xludf.DUMMYFUNCTION("GOOGLEFINANCE(A51,""name"")"),"#N/A") -> #N/A | C51: ='Virtual Portfolio'!C54 | D51: =IFERROR(__xludf.DUMMYFUNCTION("GOOGLEFINANCE(A51)"),"#N/A") -> #N/A | K51: =(D51-E51)/E51 -> #N/A | L51: =IFERROR(__xludf.DUMMYFUNCTION("SPARKLINE(GoogleFinance(A51, ""price"", TODAY()-30, TODAY()),{""color"",""blue"";""linewidth"",2}) "),"#N/A") -> #N/A | M51: =IFERROR(__xludf.DUMMYFUNCTION("GOOGLEFINANCE(A51,""currency"")"),"#N/A") -> #N/A | N51: =round(D51/AE51-1,4) -> #N/A | O51: =IFERROR(__xludf.DUMMYFUNCTION("GOOGLEFINANCE(A51,""Change"")"),"#N/A") -> #N/A | P51: =IFERROR(__xludf.DUMMYFUNCTION("GOOGLEFINANCE(A51,""High"")"),"#N/A") -> #N/A | Q51: =IFERROR(__xludf.DUMMYFUNCTION("GOOGLEFINANCE(A51,""low"")"),"#N/A") -> #N/A | R51: =IFERROR(__xludf.DUMMYFUNCTION("abs(P51-Q51)/GOOGLEFINANCE(A51,""closeyest"")"),"#N/A") -> #N/A | S51: =D51/Y51-1 -> #N/A | T51: ='Virtual Portfolio'!T54 | U51: ='Virtual Portfolio'!U54 | W51: =IF(ISERROR(if(or(AND(Q51<=T51,T51<=P51),AND(Q51<=U51, U51<=P51)),"TRADE ALERT","")),"DATA UNAVAILABLE",if(or(AND(Q51<=T51,T51<=P51),T51>P51,AND(Q51<=U51, U51<=P51)),"TRADE ALERT"&" - Price level hit for "&A51&" currently at "&D51&" "&B51,"")) -> DATA UNAVAILABLE | X51: =IFERROR(__xludf.DUMMYFUNCTION("GOOGLEFINANCE($A51,X$3)"),"#N/A") -> #N/A | Y51: =IFERROR(__xludf.DUMMYFUNCTION("GOOGLEFINANCE($A51,Y$3)"),"#N/A") -> #N/A | Z51: =IFERROR(__xludf.DUMMYFUNCTION("GOOGLEFINANCE($A51,Z$3)"),"#N/A") -> #N/A | AA51: =IFERROR(__xludf.DUMMYFUNCTION("GOOGLEFINANCE($A51,AA$3)"),"#N/A") -> #N/A | AB51: =IFERROR(__xludf.DUMMYFUNCTION("GOOGLEFINANCE($A51,AB$3)"),"#N/A") -> #N/A | AC51: =IFERROR(__xludf.DUMMYFUNCTION("GOOGLEFINANCE($A51,AC$3)"),"#N/A") -> #N/A | AD51: =IFERROR(__xludf.DUMMYFUNCTION("GOOGLEFINANCE($A51,AD$3)"),"#N/A") -> #N/A | AE51: =IFERROR(__xludf.DUMMYFUNCTION("GOOGLEFINANCE($A51,AE$3)"),"#N/A") -> #N/A
A52: ='Virtual Portfolio'!A55 | B52: =IFERROR(__xludf.DUMMYFUNCTION("GOOGLEFINANCE(A52,""name"")"),"#N/A") -> #N/A | C52: ='Virtual Portfolio'!C55 | D52: =IFERROR(__xludf.DUMMYFUNCTION("GOOGLEFINANCE(A52)"),"#N/A") -> #N/A | K52: =(D52-E52)/E52 -> #N/A | L52: =IFERROR(__xludf.DUMMYFUNCTION("SPARKLINE(GoogleFinance(A52, ""price"", TODAY()-30, TODAY()),{""color"",""blue"";""linewidth"",2}) "),"#N/A") -> #N/A | M52: =IFERROR(__xludf.DUMMYFUNCTION("GOOGLEFINANCE(A52,""currency"")"),"#N/A") -> #N/A | N52: =round(D52/AE52-1,4) -> #N/A | O52: =IFERROR(__xludf.DUMMYFUNCTION("GOOGLEFINANCE(A52,""Change"")"),"#N/A") -> #N/A | P52: =IFERROR(__xludf.DUMMYFUNCTION("GOOGLEFINANCE(A52,""High"")"),"#N/A") -> #N/A | Q52: =IFERROR(__xludf.DUMMYFUNCTION("GOOGLEFINANCE(A52,""low"")"),"#N/A") -> #N/A | R52: =IFERROR(__xludf.DUMMYFUNCTION("abs(P52-Q52)/GOOGLEFINANCE(A52,""closeyest"")"),"#N/A") -> #N/A | S52: =D52/Y52-1 -> #N/A | T52: ='Virtual Portfolio'!T55 | U52: ='Virtual Portfolio'!U55 | W52: =IF(ISERROR(if(or(AND(Q52<=T52,T52<=P52),AND(Q52<=U52, U52<=P52)),"TRADE ALERT","")),"DATA UNAVAILABLE",if(or(AND(Q52<=T52,T52<=P52),T52>P52,AND(Q52<=U52, U52<=P52)),"TRADE ALERT"&" - Price level hit for "&A52&" currently at "&D52&" "&B52,"")) -> DATA UNAVAILABLE | X52: =IFERROR(__xludf.DUMMYFUNCTION("GOOGLEFINANCE($A52,X$3)"),"#N/A") -> #N/A | Y52: =IFERROR(__xludf.DUMMYFUNCTION("GOOGLEFINANCE($A52,Y$3)"),"#N/A") -> #N/A | Z52: =IFERROR(__xludf.DUMMYFUNCTION("GOOGLEFINANCE($A52,Z$3)"),"#N/A") -> #N/A | AA52: =IFERROR(__xludf.DUMMYFUNCTION("GOOGLEFINANCE($A52,AA$3)"),"#N/A") -> #N/A | AB52: =IFERROR(__xludf.DUMMYFUNCTION("GOOGLEFINANCE($A52,AB$3)"),"#N/A") -> #N/A | AC52: =IFERROR(__xludf.DUMMYFUNCTION("GOOGLEFINANCE($A52,AC$3)"),"#N/A") -> #N/A | AD52: =IFERROR(__xludf.DUMMYFUNCTION("GOOGLEFINANCE($A52,AD$3)"),"#N/A") -> #N/A | AE52: =IFERROR(__xludf.DUMMYFUNCTION("GOOGLEFINANCE($A52,AE$3)"),"#N/A") -> #N/A

Sheet Average Price Calculator
A2: Use this sheet to track but also to see what your new average price will be if you were to add a new investment e.g. if you only have 2 Trades, fill in a line for trade 3 and you will see new average price
B4: EXAMPLE | C4: DO NOT USE | F4: GBPUSD | I4: EXAMPLE | J4: DO NOT USE
B5: SNAP | C5: =IFERROR(__xludf.DUMMYFUNCTION("GOOGLEFINANCE(B5)"),4.75) -> 4.75 | D5: Position Size Limit | E5: 1000 | F5: =IFERROR(__xludf.DUMMYFUNCTION("GOOGLEFINANCE(""CURRENCY:GBPUSD"")"),1.35588) -> 1.35588 | I5: AML | J5: =IFERROR(__xludf.DUMMYFUNCTION("GOOGLEFINANCE(I5)"),0.13) -> 0.13 | K5: Position Size Limit | L5: 4000
C6: Number of Shares | D6: Price | E6: Value | F6: SIZE | G6: SIZE ($) | I6: =IFERROR(__xludf.DUMMYFUNCTION("GOOGLEFINANCE(I5,""name"")"),"Akwaaba Mining Ltd") -> Akwaaba Mining Ltd | J6: Number of Shares | K6: Price | L6: Value | M6: Size (GBP)
B7: Trade 1 | C7: =round(F7*100/D7,0) -> 6316 | D7: =C5 -> 4.75 | E7: =C7*D7/100 -> 300.01 | F7: 300 | G7: =F7*F5 -> 406.764 | I7: Trade 1 | J7: =round(M7/K7*100,0) -> 882 | K7: 170 | L7: =J7*K7/100 -> 1499.4 | M7: 1500
B8: Trade 2 | C8: =round(F8*100/D8,0) -> 15789 | D8: =D7*0.4 -> 1.9 | E8: =C8*D8/100 -> 299.991 | F8: 300 | G8: =F8*F5 -> 406.764 | I8: Trade 2 | J8: =round(M8/K8*100,0) -> 2941 | K8: =K7*0.3 -> 51 | L8: =J8*K8/100 -> 1499.91 | M8: 1500
B9: Trade 3 | C9: =round(F9*100/D9,0) -> 52632 | D9: =D8*0.4 -> 0.76 | E9: =C9*D9/100 -> 400.0032 | F9: 400 | G9: =F9*F5 -> 542.352 | I9: Trade 3 | J9: =round(M9/K9*100,0) -> 3333 | K9: 30 | L9: =J9*K9/100 -> 999.9 | M9: 1000
B10: Trade 4 | E10: =C10*D10 -> 0 | I10: Trade 4 | L10: =J10*K10 -> 0
C11: =sum(C7:C10) -> 74737 | E11: =sum(E7:E10) -> 1000.0042 | J11: =sum(J7:J10) -> 7156 | L11: =sum(L7:L10) -> 3999.21
D12: Average Price | E12: =E11/C11 -> 0.01338031
K13: Average Price | L13: =L11/J11 -> 0.5588611
B14: =IFERROR(__xludf.DUMMYFUNCTION("GOOGLEFINANCE(B15,""NAME"")"),"#N/A") -> #N/A | E14: =E15*F15 -> 1355.88 | F14: GBPUSD
B15: toop | C15: =IFERROR(__xludf.DUMMYFUNCTION("GOOGLEFINANCE(B15)"),"#N/A") -> #N/A | D15: Budget | E15: 1000 | F15: =IFERROR(__xludf.DUMMYFUNCTION("GOOGLEFINANCE(""CURRENCY:GBPUSD"")"),1.35588) -> 1.35588 | G15: =E15*F15 -> 1355.88 | I15: TED | J15: =IFERROR(__xludf.DUMMYFUNCTION("GOOGLEFINANCE(I15)"),0.47) -> 0.47 | K15: Position Size Limit | L15: 1000
C16: Number of Shares | D16: Price | E16: Value (USD) | F16: Size (GBP) | G16: SIZE ($) | I16: =IFERROR(__xludf.DUMMYFUNCTION("GOOGLEFINANCE(I15,""name"")"),"Terrascend Corp") -> Terrascend Corp | J16: Number of Shares | K16: Price | L16: Value | M16: Size (GBP)
B17: Trade 1 | C17: 1500 | D17: =C15 -> #N/A | E17: =D17*C17 -> #N/A | F17: 300 | G17: =F17*F15 -> 406.764 | I17: Trade 1 | J17: =ROUND(M17/K17*100,0) -> 725 | K17: 69 | L17: =J17*K17/100 -> 500.25 | M17: 500
B18: Trade 2 | C18: 2000 | D18: =D17*0.5 -> #N/A | E18: =D18*C18 -> #N/A | F18: 300 | G18: =F18*F15 -> 406.764 | I18: Trade 2 | J18: =ROUND(M18/K18*100,0) -> 1449 | K18: =K17*0.5 -> 34.5 | L18: =J18*K18/100 -> 499.905 | M18: 500
B19: Trade 3 | C19: 3000 | D19: =D18*0.5 -> #N/A | E19: =D19*C19 -> #N/A | F19: 400 | G19: =F19*F15 -> 542.352 | I19: Trade 3 | L19: =J19*K19/100 -> 0
B20: Trade 4 | E20: =C20*D20 -> 0 | I20: Trade 4 | L20: =J20*K20 -> 0
C21: =sum(C17:C20) -> 6500 | E21: =sum(E17:E20) -> #N/A | J21: =sum(J17:J20) -> 2174 | L21: =sum(L17:L20) -> 1000.155
D23: Average Price | E23: =E21/C21 -> #N/A | K23: Average Price | L23: =L21/J21 -> 0.4600529
B25: =IFERROR(__xludf.DUMMYFUNCTION("GOOGLEFINANCE(B26,""NAME"")"),"Jumia Technologies AG - ADR") -> Jumia Technologies AG - ADR | F25: GBPUSD | I25: MERI | J25: =IFERROR(__xludf.DUMMYFUNCTION("GOOGLEFINANCE(I25)"),138.0) -> 138 | K25: Position Size Limit | L25: 1000
B26: JMIA | C26: =IFERROR(__xludf.DUMMYFUNCTION("GOOGLEFINANCE(B26)"),9.34) -> 9.34 | D26: Position Size Limit | E26: 1000 | F26: =IFERROR(__xludf.DUMMYFUNCTION("GOOGLEFINANCE(""CURRENCY:GBPUSD"")"),1.35588) -> 1.35588 | J26: Number of Shares | K26: Price | L26: Value | M26: Size (GBP)
C27: Number of Shares | D27: Price | E27: Value (USD) | F27: Size (GBP) | G27: SIZE ($) | I27: Trade 1 | J27: =round(M27/K27*100,0) -> 229 | K27: 131 | L27: =J27*K27/100 -> 299.99 | M27: 300
B28: Trade 1 | C28: 150 | D28: =C26 -> 9.34 | E28: =D28*C28 -> 1401 | F28: 300 | G28: =F28*F26 -> 406.764 | I28: Trade 2 | J28: =round(M28/K28*100,0) -> 286 | K28: =K27*0.8 -> 104.8 | L28: =J28*K28/100 -> 299.728 | M28: 300
B29: Trade 2 | C29: 200 | D29: =D28*0.5 -> 4.67 | E29: =D29*C29 -> 934 | F29: 300 | G29: =F29*F26 -> 406.764 | I29: Trade 3 | J29: =round(M29/K29*100,0) -> 477 | K29: =K28*0.8 -> 83.84 | L29: =J29*K29/100 -> 399.9168 | M29: 400
B30: Trade 3 | C30: 400 | D30: =D29*0.5 -> 2.335 | E30: =D30*C30 -> 934 | F30: 400 | G30: =F30*F26 -> 542.352 | I30: Trade 4 | L30: =J30*K30 -> 0
B31: Trade 4 | E31: =C31*D31 -> 0 | J31: =sum(J27:J30) -> 992 | L31: =sum(L27:L30) -> 999.6348
C32: =sum(C28:C31) -> 750 | E32: =sum(E28:E31) -> 3269
K33: Average Price | L33: =L31/J31 -> 1.0076964
D34: Average Price | E34: =E32/C32 -> 4.3586667
I35: MKS | J35: =IFERROR(__xludf.DUMMYFUNCTION("GOOGLEFINANCE(I35)"),406.1) -> 406.1 | K35: Position Size Limit | L35: 1000
B36: =IFERROR(__xludf.DUMMYFUNCTION("GOOGLEFINANCE(B37,""NAME"")"),"Virgin Galactic Holdings Inc") -> Virgin Galactic Holdings Inc | E36: =E37*F37 -> 572.1275 | F36: GBPEUR | J36: Number of Shares | K36: Price | L36: Value | M36: Size (GBP)
B37: spce | C37: =IFERROR(__xludf.DUMMYFUNCTION("GOOGLEFINANCE(B37)"),2.52) -> 2.52 | D37: Position Size Limit | E37: 500 | F37: =IFERROR(__xludf.DUMMYFUNCTION("GOOGLEFINANCE(""CURRENCY:GBPEUR"")"),1.144255) -> 1.144255 | I37: Trade 1 | J37: =round(M37/K37*100,0) -> 74 | K37: =J35 -> 406.1 | L37: =J37*K37/100 -> 300.514 | M37: 300
C38: Number of Shares | D38: Price | E38: Value (EUR) | F38: Size (GBP) | G38: SIZE (EUR) | I38: Trade 2 | J38: =round(M38/K38*100,0) -> 148 | K38: =K37*0.5 -> 203.05 | L38: =J38*K38/100 -> 300.514 | M38: 300
B39: Trade 1 | C39: =round(G39/D39,0) -> 381 | D39: =C37 -> 2.52 | E39: =D39*C39 -> 960.12 | F39: 838 | G39: =F39*F37 -> 958.88569 | I39: Trade 3 | J39: =round(M39/K39*100,0) -> 394 | K39: =K38*0.5 -> 101.525 | L39: =J39*K39/100 -> 400.0085 | M39: 400
B40: Trade 2 | C40: =round(G40/D40,0) -> 908 | D40: =D39*0.4 -> 1.008 | E40: =D40*C40 -> 915.264 | F40: 800 | G40: =F40*F37 -> 915.404 | I40: Trade 4 | L40: =J40*K40 -> 0
B41: Trade 3 | C41: =round(G41/D41,0) -> 0 | D41: =D40*0.9 -> 0.9072 | E41: =D41*C41 -> 0 | F41: 0 | G41: =F41*F37 -> 0 | J41: =sum(J37:J40) -> 616 | L41: =sum(L37:L40) -> 1001.0365
B42: Trade 4 | E42: =C42*D42 -> 0
C43: =sum(C39:C42) -> 1289 | E43: =sum(E39:E42) -> 1875.384 | K43: Average Price | L43: =L41/J41 -> 1.6250593
D45: Average Price | E45: =E43/C43 -> 1.4549139 | I45: MKS | J45: =IFERROR(__xludf.DUMMYFUNCTION("GOOGLEFINANCE(I45)"),406.1) -> 406.1 | K45: Position Size Limit | L45: 1000
J46: Number of Shares | K46: Price | L46: Value | M46: Size (GBP)
B47: =IFERROR(__xludf.DUMMYFUNCTION("GOOGLEFINANCE(B48,""NAME"")"),"Sonos Inc") -> Sonos Inc | F47: GBPUSD | I47: Trade 1 | J47: =round(M47/K47*100,0) -> 74 | K47: =J45 -> 406.1 | L47: =J47*K47/100 -> 300.514 | M47: 300
B48: SONO | C48: =IFERROR(__xludf.DUMMYFUNCTION("GOOGLEFINANCE(B48)"),15.52) -> 15.52 | D48: Position Size Limit | E48: 500 | F48: =IFERROR(__xludf.DUMMYFUNCTION("GOOGLEFINANCE(""CURRENCY:GBPUSD"")"),1.35588) -> 1.35588 | I48: Trade 2 | J48: =round(M48/K48*100,0) -> 148 | K48: =K47*0.5 -> 203.05 | L48: =J48*K48/100 -> 300.514 | M48: 300
C49: Number of Shares | D49: Price | E49: Value (USD) | F49: Size (GBP) | G49: SIZE ($) | I49: Trade 3 | J49: =round(M49/K49*100,0) -> 394 | K49: =K48*0.5 -> 101.525 | L49: =J49*K49/100 -> 400.0085 | M49: 400
B50: Trade 1 | C50: =round(G50/D50,0) -> 123 | D50: 1.1 | E50: =D50*C50 -> 135.3 | F50: 100 | G50: =F50*F48 -> 135.588 | I50: Trade 4 | L50: =J50*K50 -> 0
B51: Trade 2 | C51: =round(G51/D51,0) -> 370 | D51: =D50*0.5 -> 0.55 | E51: =D51*C51 -> 203.5 | F51: 150 | G51: =F51*F48 -> 203.382 | J51: =sum(J47:J50) -> 616 | L51: =sum(L47:L50) -> 1001.0365
B52: Trade 3 | C52: =round(G52/D52,0) -> 1233 | D52: =D51*0.5 -> 0.275 | E52: =D52*C52 -> 339.075 | F52: 250 | G52: =F52*F48 -> 338.97
B53: Trade 4 | E53: =C53*D53 -> 0 | K53: Average Price | L53: =L51/J51 -> 1.6250593
C54: =sum(C50:C53) -> 1726 | E54: =sum(E50:E53) -> 677.875
I55: MKS | J55: =IFERROR(__xludf.DUMMYFUNCTION("GOOGLEFINANCE(I55)"),406.1) -> 406.1 | K55: Position Size Limit | L55: 1000
D56: Average Price | E56: =E54/C54 -> 0.39274334 | J56: Number of Shares | K56: Price | L56: Value | M56: Size (GBP)
I57: Trade 1 | J57: =round(M57/K57*100,0) -> 74 | K57: =J55 -> 406.1 | L57: =J57*K57/100 -> 300.514 | M57: 300
B58: =IFERROR(__xludf.DUMMYFUNCTION("GOOGLEFINANCE(B59,""NAME"")"),"Berkshire Hathaway Inc Cedear") -> Berkshire Hathaway Inc Cedear | F58: GBPUSD | I58: Trade 2 | J58: =round(M58/K58*100,0) -> 148 | K58: =K57*0.5 -> 203.05 | L58: =J58*K58/100 -> 300.514 | M58: 300
B59: BRKB | C59: =IFERROR(__xludf.DUMMYFUNCTION("GOOGLEFINANCE(B59)"),33360.0) -> 33360 | D59: Position Size Limit | E59: 500 | F59: =IFERROR(__xludf.DUMMYFUNCTION("GOOGLEFINANCE(""CURRENCY:GBPUSD"")"),1.35588) -> 1.35588 | I59: Trade 3 | J59: =round(M59/K59*100,0) -> 394 | K59: =K58*0.5 -> 101.525 | L59: =J59*K59/100 -> 400.0085 | M59: 400
C60: Number of Shares | D60: Price | E60: Value (USD) | F60: Size (GBP) | G60: SIZE ($) | I60: Trade 4 | L60: =J60*K60 -> 0
B61: Trade 1 | C61: =round(G61/D61,0) -> 123 | D61: 1.1 | E61: =D61*C61 -> 135.3 | F61: 100 | G61: =F61*F59 -> 135.588 | J61: =sum(J57:J60) -> 616 | L61: =sum(L57:L60) -> 1001.0365
B62: Trade 2 | C62: =round(G62/D62,0) -> 370 | D62: =D61*0.5 -> 0.55 | E62: =D62*C62 -> 203.5 | F62: 150 | G62: =F62*F59 -> 203.382
B63: Trade 3 | C63: =round(G63/D63,0) -> 1233 | D63: =D62*0.5 -> 0.275 | E63: =D63*C63 -> 339.075 | F63: 250 | G63: =F63*F59 -> 338.97 | K63: Average Price | L63: =L61/J61 -> 1.6250593
B64: Trade 4 | E64: =C64*D64 -> 0
C65: =sum(C61:C64) -> 1726 | E65: =sum(E61:E64) -> 677.875 | I65: MKS | J65: =IFERROR(__xludf.DUMMYFUNCTION("GOOGLEFINANCE(I65)"),406.1) -> 406.1 | K65: Position Size Limit | L65: 1000
J66: Number of Shares | K66: Price | L66: Value | M66: Size (GBP)
B67: =IFERROR(__xludf.DUMMYFUNCTION("GOOGLEFINANCE(B68,""NAME"")"),"IDEX Metals Corp") -> IDEX Metals Corp | F67: GBPUSD | I67: Trade 1 | J67: =round(M67/K67*100,0) -> 74 | K67: =J65 -> 406.1 | L67: =J67*K67/100 -> 300.514 | M67: 300
B68: IDEX | C68: =IFERROR(__xludf.DUMMYFUNCTION("GOOGLEFINANCE(B68)"),0.47) -> 0.47 | D68: Position Size Limit | E68: 500 | F68: =IFERROR(__xludf.DUMMYFUNCTION("GOOGLEFINANCE(""CURRENCY:GBPUSD"")"),1.35588) -> 1.35588 | I68: Trade 2 | J68: =round(M68/K68*100,0) -> 148 | K68: =K67*0.5 -> 203.05 | L68: =J68*K68/100 -> 300.514 | M68: 300
C69: Number of Shares | D69: Price | E69: Value (USD) | F69: Size (GBP) | G69: SIZE ($) | I69: Trade 3 | J69: =round(M69/K69*100,0) -> 394 | K69: =K68*0.5 -> 101.525 | L69: =J69*K69/100 -> 400.0085 | M69: 400
B70: Trade 1 | C70: =round(G70/D70,0) -> 123 | D70: 1.1 | E70: =D70*C70 -> 135.3 | F70: 100 | G70: =F70*F68 -> 135.588 | I70: Trade 4 | L70: =J70*K70 -> 0
B71: Trade 2 | C71: =round(G71/D71,0) -> 370 | D71: =D70*0.5 -> 0.55 | E71: =D71*C71 -> 203.5 | F71: 150 | G71: =F71*F68 -> 203.382 | J71: =sum(J67:J70) -> 616 | L71: =sum(L67:L70) -> 1001.0365
B72: Trade 3 | C72: =round(G72/D72,0) -> 1233 | D72: =D71*0.5 -> 0.275 | E72: =D72*C72 -> 339.075 | F72: 250 | G72: =F72*F68 -> 338.97
B73: Trade 4 | E73: =C73*D73 -> 0 | K73: Average Price | L73: =L71/J71 -> 1.6250593
C74: =sum(C70:C73) -> 1726 | E74: =sum(E70:E73) -> 677.875
I75: MKS | J75: =IFERROR(__xludf.DUMMYFUNCTION("GOOGLEFINANCE(I75)"),406.1) -> 406.1 | K75: Position Size Limit | L75: 1000
D76: Average Price | E76: =E74/C74 -> 0.39274334 | J76: Number of Shares | K76: Price | L76: Value | M76: Size (GBP)
I77: Trade 1 | J77: =round(M77/K77*100,0) -> 74 | K77: =J75 -> 406.1 | L77: =J77*K77/100 -> 300.514 | M77: 300
B78: =IFERROR(__xludf.DUMMYFUNCTION("GOOGLEFINANCE(B79,""NAME"")"),"IDEX Metals Corp") -> IDEX Metals Corp | F78: GBPUSD | I78: Trade 2 | J78: =round(M78/K78*100,0) -> 148 | K78: =K77*0.5 -> 203.05 | L78: =J78*K78/100 -> 300.514 | M78: 300
B79: IDEX | C79: =IFERROR(__xludf.DUMMYFUNCTION("GOOGLEFINANCE(B79)"),0.47) -> 0.47 | D79: Position Size Limit | E79: 500 | F79: =IFERROR(__xludf.DUMMYFUNCTION("GOOGLEFINANCE(""CURRENCY:GBPUSD"")"),1.35588) -> 1.35588 | I79: Trade 3 | J79: =round(M79/K79*100,0) -> 394 | K79: =K78*0.5 -> 101.525 | L79: =J79*K79/100 -> 400.0085 | M79: 400
C80: Number of Shares | D80: Price | E80: Value (USD) | F80: Size (GBP) | G80: SIZE ($) | I80: Trade 4 | L80: =J80*K80 -> 0
B81: Trade 1 | C81: =round(G81/D81,0) -> 123 | D81: 1.1 | E81: =D81*C81 -> 135.3 | F81: 100 | G81: =F81*F79 -> 135.588 | J81: =sum(J77:J80) -> 616 | L81: =sum(L77:L80) -> 1001.0365
B82: Trade 2 | C82: =round(G82/D82,0) -> 370 | D82: =D81*0.5 -> 0.55 | E82: =D82*C82 -> 203.5 | F82: 150 | G82: =F82*F79 -> 203.382
B83: Trade 3 | C83: =round(G83/D83,0) -> 1233 | D83: =D82*0.5 -> 0.275 | E83: =D83*C83 -> 339.075 | F83: 250 | G83: =F83*F79 -> 338.97 | K83: Average Price | L83: =L81/J81 -> 1.6250593
B84: Trade 4 | E84: =C84*D84 -> 0
C85: =sum(C81:C84) -> 1726 | E85: =sum(E81:E84) -> 677.875 | I85: MKS | J85: =IFERROR(__xludf.DUMMYFUNCTION("GOOGLEFINANCE(I85)"),406.1) -> 406.1 | K85: Position Size Limit | L85: 1000
J86: Number of Shares | K86: Price | L86: Value | M86: Size (GBP)
D87: Average Price | E87: =E85/C85 -> 0.39274334 | I87: Trade 1 | J87: =round(M87/K87*100,0) -> 74 | K87: =J85 -> 406.1 | L87: =J87*K87/100 -> 300.514 | M87: 300
I88: Trade 2 | J88: =round(M88/K88*100,0) -> 148 | K88: =K87*0.5 -> 203.05 | L88: =J88*K88/100 -> 300.514 | M88: 300
I89: Trade 3 | J89: =round(M89/K89*100,0) -> 394 | K89: =K88*0.5 -> 101.525 | L89: =J89*K89/100 -> 400.0085 | M89: 400
I90: Trade 4 | L90: =J90*K90 -> 0
J91: =sum(J87:J90) -> 616 | L91: =sum(L87:L90) -> 1001.0365
K93: Average Price | L93: =L91/J91 -> 1.6250593
K94: Average Price | L94: =L92/J92 -> #DIV/0!
I96: MKS | J96: =IFERROR(__xludf.DUMMYFUNCTION("GOOGLEFINANCE(I96)"),406.1) -> 406.1 | K96: Position Size Limit | L96: 1000
J97: Number of Shares | K97: Price | L97: Value | M97: Size (GBP)
I98: Trade 1 | J98: =round(M98/K98*100,0) -> 74 | K98: =J96 -> 406.1 | L98: =J98*K98/100 -> 300.514 | M98: 300
I99: Trade 2 | J99: =round(M99/K99*100,0) -> 148 | K99: =K98*0.5 -> 203.05 | L99: =J99*K99/100 -> 300.514 | M99: 300
I100: Trade 3 | J100: =round(M100/K100*100,0) -> 394 | K100: =K99*0.5 -> 101.525 | L100: =J100*K100/100 -> 400.0085 | M100: 400
I101: Trade 4 | L101: =J101*K101 -> 0
J102: =sum(J98:J101) -> 616 | L102: =sum(L98:L101) -> 1001.0365
K104: Average Price | L104: =L102/J102 -> 1.6250593
I106: MKS | J106: =IFERROR(__xludf.DUMMYFUNCTION("GOOGLEFINANCE(I106)"),406.1) -> 406.1 | K106: Position Size Limit | L106: 1000
J107: Number of Shares | K107: Price | L107: Value | M107: Size (GBP)
I108: Trade 1 | J108: =round(M108/K108*100,0) -> 74 | K108: =J106 -> 406.1 | L108: =J108*K108/100 -> 300.514 | M108: 300
I109: Trade 2 | J109: =round(M109/K109*100,0) -> 148 | K109: =K108*0.5 -> 203.05 | L109: =J109*K109/100 -> 300.514 | M109: 300
...

Sheet Virtual Portfolio
A1: Portfolio Size | B1: 10000 | C1: Budget per Stock | D1: 500 | E1: Min Entry Size | F1: 300 | G1: 2 ETFs/Reits - £1k each | H1: 8 Stocks at £1k each | I1: Amount Invested | J1: =sum(H:H) -> 43832.866 | K1: Invested Value | L1: =sum(I:I) -> 428.7033 | M1: Portfolio Return | N1: =(L1-J1)/B1 -> -4.3404163 | O1: Portfolio Cash | P1: =B1-J1 -> -33832.866 | Q1: =L1-J1+B1 -> -33404.163 | R1: Look out for Big red number in this column
A2: Master Watchlist | E2: 100 | F2: 150 | G2: 250 | H2: <=== How to spend the £1000
A3: Ticker | B3: Name | C3: Reason for Entry | D3: Current Price | E3: Trading 212/Freetrade entry price | F3: Average Entry Price | G3: Number of Shares | H3: Current Cost | I3: Current Value | J3: % Weight of Portfolio | K3: Current Return (%) | L3: 30 Day Trend Chart | M3: Ccy | N3: Daily Change (%) | O3: Change | P3: High | Q3: Low | R3: Range/ yest close | S3: Price/ year low | T3: Target Entry for Averaging | U3: Target Exit | V3: Trade Alert | W3: TRADE ALERT | X3: beta | Y3: low52 | Z3: high52 | AA3: volume avg | AB3: pe | AC3: datadelay | AD3: marketcap | AE3: Closeyest
A4: TED | B4: =IFERROR(__xludf.DUMMYFUNCTION("GOOGLEFINANCE(A4,""name"")"),"Terrascend Corp") -> Terrascend Corp | C4: Recovery | D4: =IFERROR(__xludf.DUMMYFUNCTION("GOOGLEFINANCE(A4)"),0.47) -> 0.47 | E4: 69 | F4: =IFERROR(__xludf.DUMMYFUNCTION("IF(M4=""USD"",E4/GOOGLEFINANCE(""CURRENCY:GBPUSD""),E4)"),69.0) -> 69 | G4: 725 | H4: =IFERROR(__xludf.DUMMYFUNCTION("if(isblank(A4)=TRUE,0,if(M4=""GBX"",E4*G4/100,IF(M4=""EUR"",E4*G4/GOOGLEFINANCE(""CURRENCY:GBPEUR""),E4*G4/GOOGLEFINANCE(""CURRENCY:GBPUSD""))))"),43718.40192963981) -> 43718.402 | I4: =IFERROR(__xludf.DUMMYFUNCTION("if(isblank(A4)=TRUE,0,if(M4=""GBX"",D4*G4/100,IF(M4=""EUR"",D4*G4/GOOGLEFINANCE(""CURRENCY:GBPEUR""),D4*G4/GOOGLEFINANCE(""CURRENCY:GBPUSD""))))"),297.7920131439233) -> 297.79201 | J4: =H4/$B$1 -> 4.3718402 | K4: =I4/H4-1 -> -0.99318841 | L4: =IFERROR(__xludf.DUMMYFUNCTION("SPARKLINE(GoogleFinance(A4, ""price"", TODAY()-30, TODAY()),{""color"",""blue"";""linewidth"",2}) "),"") | M4: =IFERROR(__xludf.DUMMYFUNCTION("GOOGLEFINANCE(A4,""currency"")"),"EUR") -> EUR | N4: =round(D4/AE4-1,4) -> 0 | O4: =IFERROR(__xludf.DUMMYFUNCTION("GOOGLEFINANCE(A4,""Change"")"),0.0) -> 0 | P4: =IFERROR(__xludf.DUMMYFUNCTION("GOOGLEFINANCE(A4,""High"")"),0.49) -> 0.49 | Q4: =IFERROR(__xludf.DUMMYFUNCTION("GOOGLEFINANCE(A4,""low"")"),0.47) -> 0.47 | R4: =IFERROR(__xludf.DUMMYFUNCTION("abs(P4-Q4)/GOOGLEFINANCE(A4,""closeyest"")"),0.04255319148936174) -> 0.042553191 | S4: =D4/Y4-1 -> 1.7647059 | T4: 34.5 | U4: 150 | W4: =IF(ISERROR(if(or(AND(Q4<=T4,T4<=P4),AND(Q4<=U4, U4<=P4)),"TRADE ALERT","")),"DATA UNAVAILABLE",if(or(AND(Q4<=T4,T4<=P4),T4>P4,AND(Q4<=U4, U4<=P4)),"TRADE ALERT"&" - Price level hit for "&A4&" currently at "&D4&" "&B4,"")) -> TRADE ALERT - Price level hit for TED currently at 0.47 Terrascend Corp | X4: =IFERROR(__xludf.DUMMYFUNCTION("GOOGLEFINANCE($A4,X$3)"),"#N/A") -> #N/A | Y4: =IFERROR(__xludf.DUMMYFUNCTION("GOOGLEFINANCE($A4,Y$3)"),0.17) -> 0.17 | Z4: =IFERROR(__xludf.DUMMYFUNCTION("GOOGLEFINANCE($A4,Z$3)"),1.09) -> 1.09 | AA4: =IFERROR(__xludf.DUMMYFUNCTION("GOOGLEFINANCE($A4,AA$3)"),"#N/A") -> #N/A | AB4: =IFERROR(__xludf.DUMMYFUNCTION("GOOGLEFINANCE($A4,AB$3)"),"#N/A") -> #N/A | AC4: =IFERROR(__xludf.DUMMYFUNCTION("GOOGLEFINANCE($A4,AC$3)"),15.0) -> 15 | AD4: =IFERROR(__xludf.DUMMYFUNCTION("GOOGLEFINANCE($A4,AD$3)"),3.01350132E8) -> 301350132 | AE4: =IFERROR(__xludf.DUMMYFUNCTION("GOOGLEFINANCE($A4,AE$3)"),0.47) -> 0.47
A5: MANU | B5: =IFERROR(__xludf.DUMMYFUNCTION("GOOGLEFINANCE(A5,""name"")"),"Manchester United PLC") -> Manchester United PLC | C5: UCL Boost | D5: =IFERROR(__xludf.DUMMYFUNCTION("GOOGLEFINANCE(A5)"),17.75) -> 17.75 | E5: 15.52 | F5: =IFERROR(__xludf.DUMMYFUNCTION("IF(M5=""USD"",E5/GOOGLEFINANCE(""CURRENCY:GBPUSD""),E5)"),11.446440687966486) -> 11.446441 | G5: 10 | H5: =IFERROR(__xludf.DUMMYFUNCTION("if(isblank(A5)=TRUE,0,if(M5=""GBX"",E5*G5/100,IF(M5=""EUR"",E5*G5/GOOGLEFINANCE(""CURRENCY:GBPEUR""),E5*G5/GOOGLEFINANCE(""CURRENCY:GBPUSD""))))"),114.46440687966486) -> 114.46441 | I5: =IFERROR(__xludf.DUMMYFUNCTION("if(isblank(A5)=TRUE,0,if(M5=""GBX"",D5*G5/100,IF(M5=""EUR"",D5*G5/GOOGLEFINANCE(""CURRENCY:GBPEUR""),D5*G5/GOOGLEFINANCE(""CURRENCY:GBPUSD""))))"),130.91129008466825) -> 130.91129 | J5: =H5/$B$1 -> 0.011446441 | K5: =I5/H5-1 -> 0.14368557 | L5: =IFERROR(__xludf.DUMMYFUNCTION("SPARKLINE(GoogleFinance(A5, ""price"", TODAY()-30, TODAY()),{""color"",""blue"";""linewidth"",2}) "),"") | M5: =IFERROR(__xludf.DUMMYFUNCTION("GOOGLEFINANCE(A5,""currency"")"),"USD") -> USD | N5: =round(D5/AE5-1,4) -> 0.0178 | O5: =IFERROR(__xludf.DUMMYFUNCTION("GOOGLEFINANCE(A5,""Change"")"),0.31) -> 0.31 | P5: =IFERROR(__xludf.DUMMYFUNCTION("GOOGLEFINANCE(A5,""High"")"),17.75) -> 17.75 | Q5: =IFERROR(__xludf.DUMMYFUNCTION("GOOGLEFINANCE(A5,""low"")"),17.34) -> 17.34 | R5: =IFERROR(__xludf.DUMMYFUNCTION("abs(P5-Q5)/GOOGLEFINANCE(A5,""closeyest"")"),0.02350917431192661) -> 0.023509174 | S5: =D5/Y5-1 -> 0.47302905 | T5: 7 | U5: 25 | W5: =IF(ISERROR(if(or(AND(Q5<=T5,T5<=P5),AND(Q5<=U5, U5<=P5)),"TRADE ALERT","")),"DATA UNAVAILABLE",if(or(AND(Q5<=T5,T5<=P5),T5>P5,AND(Q5<=U5, U5<=P5)),"TRADE ALERT"&" - Price level hit for "&A5&" currently at "&D5&" "&B5,"")) | X5: =IFERROR(__xludf.DUMMYFUNCTION("GOOGLEFINANCE($A5,X$3)"),0.54) -> 0.54 | Y5: =IFERROR(__xludf.DUMMYFUNCTION("GOOGLEFINANCE($A5,Y$3)"),12.05) -> 12.05 | Z5: =IFERROR(__xludf.DUMMYFUNCTION("GOOGLEFINANCE($A5,Z$3)"),19.65) -> 19.65 | AA5: =IFERROR(__xludf.DUMMYFUNCTION("GOOGLEFINANCE($A5,AA$3)"),"#N/A") -> #N/A | AB5: =IFERROR(__xludf.DUMMYFUNCTION("GOOGLEFINANCE($A5,AB$3)"),"#N/A") -> #N/A | AC5: =IFERROR(__xludf.DUMMYFUNCTION("GOOGLEFINANCE($A5,AC$3)"),0.0) -> 0 | AD5: =IFERROR(__xludf.DUMMYFUNCTION("GOOGLEFINANCE($A5,AD$3)"),3.055579075E9) -> 3055579075 | AE5: =IFERROR(__xludf.DUMMYFUNCTION("GOOGLEFINANCE($A5,AE$3)"),17.44) -> 17.44
B6: =IFERROR(__xludf.DUMMYFUNCTION("GOOGLEFINANCE(A6,""name"")"),"#N/A") -> #N/A | D6: =IFERROR(__xludf.DUMMYFUNCTION("GOOGLEFINANCE(A6)"),"#N/A") -> #N/A | F6: =IFERROR(__xludf.DUMMYFUNCTION("IF(M6=""USD"",E6/GOOGLEFINANCE(""CURRENCY:GBPUSD""),E6)"),"#N/A") -> #N/A | H6: =IFERROR(__xludf.DUMMYFUNCTION("if(isblank(A6)=TRUE,0,if(M6=""GBX"",E6*G6/100,IF(M6=""EUR"",E6*G6/GOOGLEFINANCE(""CURRENCY:GBPEUR""),E6*G6/GOOGLEFINANCE(""CURRENCY:GBPUSD""))))"),0.0) -> 0 | I6: =IFERROR(__xludf.DUMMYFUNCTION("if(isblank(A6)=TRUE,0,if(M6=""GBX"",D6*G6/100,IF(M6=""EUR"",D6*G6/GOOGLEFINANCE(""CURRENCY:GBPEUR""),D6*G6/GOOGLEFINANCE(""CURRENCY:GBPUSD""))))"),0.0) -> 0 | J6: =H6/$B$1 -> 0 | K6: =I6/H6-1 -> #DIV/0! | L6: =IFERROR(__xludf.DUMMYFUNCTION("SPARKLINE(GoogleFinance(A6, ""price"", TODAY()-30, TODAY()),{""color"",""blue"";""linewidth"",2}) "),"#N/A") -> #N/A | M6: =IFERROR(__xludf.DUMMYFUNCTION("GOOGLEFINANCE(A6,""currency"")"),"#N/A") -> #N/A | N6: =round(D6/AE6-1,4) -> #N/A | O6: =IFERROR(__xludf.DUMMYFUNCTION("GOOGLEFINANCE(A6,""Change"")"),"#N/A") -> #N/A | P6: =IFERROR(__xludf.DUMMYFUNCTION("GOOGLEFINANCE(A6,""High"")"),"#N/A") -> #N/A | Q6: =IFERROR(__xludf.DUMMYFUNCTION("GOOGLEFINANCE(A6,""low"")"),"#N/A") -> #N/A | R6: =IFERROR(__xludf.DUMMYFUNCTION("abs(P6-Q6)/GOOGLEFINANCE(A6,""closeyest"")"),"#N/A") -> #N/A | S6: =D6/Y6-1 -> #N/A | W6: =IF(ISERROR(if(or(AND(Q6<=T6,T6<=P6),AND(Q6<=U6, U6<=P6)),"TRADE ALERT","")),"DATA UNAVAILABLE",if(or(AND(Q6<=T6,T6<=P6),T6>P6,AND(Q6<=U6, U6<=P6)),"TRADE ALERT"&" - Price level hit for "&A6&" currently at "&D6&" "&B6,"")) -> DATA UNAVAILABLE | X6: =IFERROR(__xludf.DUMMYFUNCTION("GOOGLEFINANCE($A6,X$3)"),"#N/A") -> #N/A | Y6: =IFERROR(__xludf.DUMMYFUNCTION("GOOGLEFINANCE($A6,Y$3)"),"#N/A") -> #N/A | Z6: =IFERROR(__xludf.DUMMYFUNCTION("GOOGLEFINANCE($A6,Z$3)"),"#N/A") -> #N/A | AA6: =IFERROR(__xludf.DUMMYFUNCTION("GOOGLEFINANCE($A6,AA$3)"),"#N/A") -> #N/A | AB6: =IFERROR(__xludf.DUMMYFUNCTION("GOOGLEFINANCE($A6,AB$3)"),"#N/A") -> #N/A | AC6: =IFERROR(__xludf.DUMMYFUNCTION("GOOGLEFINANCE($A6,AC$3)"),"#N/A") -> #N/A | AD6: =IFERROR(__xludf.DUMMYFUNCTION("GOOGLEFINANCE($A6,AD$3)"),"#N/A") -> #N/A | AE6: =IFERROR(__xludf.DUMMYFUNCTION("GOOGLEFINANCE($A6,AE$3)"),"#N/A") -> #N/A
B7: =IFERROR(__xludf.DUMMYFUNCTION("GOOGLEFINANCE(A7,""name"")"),"#N/A") -> #N/A | D7: =IFERROR(__xludf.DUMMYFUNCTION("GOOGLEFINANCE(A7)"),"#N/A") -> #N/A | F7: =IFERROR(__xludf.DUMMYFUNCTION("IF(M7=""USD"",E7/GOOGLEFINANCE(""CURRENCY:GBPUSD""),E7)"),"#N/A") -> #N/A | H7: =IFERROR(__xludf.DUMMYFUNCTION("if(isblank(A7)=TRUE,0,if(M7=""GBX"",E7*G7/100,IF(M7=""EUR"",E7*G7/GOOGLEFINANCE(""CURRENCY:GBPEUR""),E7*G7/GOOGLEFINANCE(""CURRENCY:GBPUSD""))))"),0.0) -> 0 | I7: =IFERROR(__xludf.DUMMYFUNCTION("if(isblank(A7)=TRUE,0,if(M7=""GBX"",D7*G7/100,IF(M7=""EUR"",D7*G7/GOOGLEFINANCE(""CURRENCY:GBPEUR""),D7*G7/GOOGLEFINANCE(""CURRENCY:GBPUSD""))))"),0.0) -> 0 | J7: =H7/$B$1 -> 0 | K7: =I7/H7-1 -> #DIV/0! | L7: =IFERROR(__xludf.DUMMYFUNCTION("SPARKLINE(GoogleFinance(A7, ""price"", TODAY()-30, TODAY()),{""color"",""blue"";""linewidth"",2}) "),"#N/A") -> #N/A | M7: =IFERROR(__xludf.DUMMYFUNCTION("GOOGLEFINANCE(A7,""currency"")"),"#N/A") -> #N/A | N7: =round(D7/AE7-1,4) -> #N/A | O7: =IFERROR(__xludf.DUMMYFUNCTION("GOOGLEFINANCE(A7,""Change"")"),"#N/A") -> #N/A | P7: =IFERROR(__xludf.DUMMYFUNCTION("GOOGLEFINANCE(A7,""High"")"),"#N/A") -> #N/A | Q7: =IFERROR(__xludf.DUMMYFUNCTION("GOOGLEFINANCE(A7,""low"")"),"#N/A") -> #N/A | R7: =IFERROR(__xludf.DUMMYFUNCTION("abs(P7-Q7)/GOOGLEFINANCE(A7,""closeyest"")"),"#N/A") -> #N/A | S7: =D7/Y7-1 -> #N/A | W7: =IF(ISERROR(if(or(AND(Q7<=T7,T7<=P7),AND(Q7<=U7, U7<=P7)),"TRADE ALERT","")),"DATA UNAVAILABLE",if(or(AND(Q7<=T7,T7<=P7),T7>P7,AND(Q7<=U7, U7<=P7)),"TRADE ALERT"&" - Price level hit for "&A7&" currently at "&D7&" "&B7,"")) -> DATA UNAVAILABLE | X7: =IFERROR(__xludf.DUMMYFUNCTION("GOOGLEFINANCE($A7,X$3)"),"#N/A") -> #N/A | Y7: =IFERROR(__xludf.DUMMYFUNCTION("GOOGLEFINANCE($A7,Y$3)"),"#N/A") -> #N/A | Z7: =IFERROR(__xludf.DUMMYFUNCTION("GOOGLEFINANCE($A7,Z$3)"),"#N/A") -> #N/A | AA7: =IFERROR(__xludf.DUMMYFUNCTION("GOOGLEFINANCE($A7,AA$3)"),"#N/A") -> #N/A | AB7: =IFERROR(__xludf.DUMMYFUNCTION("GOOGLEFINANCE($A7,AB$3)"),"#N/A") -> #N/A | AC7: =IFERROR(__xludf.DUMMYFUNCTION("GOOGLEFINANCE($A7,AC$3)"),"#N/A") -> #N/A | AD7: =IFERROR(__xludf.DUMMYFUNCTION("GOOGLEFINANCE($A7,AD$3)"),"#N/A") -> #N/A | AE7: =IFERROR(__xludf.DUMMYFUNCTION("GOOGLEFINANCE($A7,AE$3)"),"#N/A") -> #N/A
B8: =IFERROR(__xludf.DUMMYFUNCTION("GOOGLEFINANCE(A8,""name"")"),"#N/A") -> #N/A | D8: =IFERROR(__xludf.DUMMYFUNCTION("GOOGLEFINANCE(A8)"),"#N/A") -> #N/A | F8: =IFERROR(__xludf.DUMMYFUNCTION("IF(M8=""USD"",E8/GOOGLEFINANCE(""CURRENCY:GBPUSD""),E8)"),"#N/A") -> #N/A | H8: =IFERROR(__xludf.DUMMYFUNCTION("if(isblank(A8)=TRUE,0,if(M8=""GBX"",E8*G8/100,IF(M8=""EUR"",E8*G8/GOOGLEFINANCE(""CURRENCY:GBPEUR""),E8*G8/GOOGLEFINANCE(""CURRENCY:GBPUSD""))))"),0.0) -> 0 | I8: =IFERROR(__xludf.DUMMYFUNCTION("if(isblank(A8)=TRUE,0,if(M8=""GBX"",D8*G8/100,IF(M8=""EUR"",D8*G8/GOOGLEFINANCE(""CURRENCY:GBPEUR""),D8*G8/GOOGLEFINANCE(""CURRENCY:GBPUSD""))))"),0.0) -> 0 | J8: =H8/$B$1 -> 0 | K8: =I8/H8-1 -> #DIV/0! | L8: =IFERROR(__xludf.DUMMYFUNCTION("SPARKLINE(GoogleFinance(A8, ""price"", TODAY()-30, TODAY()),{""color"",""blue"";""linewidth"",2}) "),"#N/A") -> #N/A | M8: =IFERROR(__xludf.DUMMYFUNCTION("GOOGLEFINANCE(A8,""currency"")"),"#N/A") -> #N/A | N8: =round(D8/AE8-1,4) -> #N/A | O8: =IFERROR(__xludf.DUMMYFUNCTION("GOOGLEFINANCE(A8,""Change"")"),"#N/A") -> #N/A | P8: =IFERROR(__xludf.DUMMYFUNCTION("GOOGLEFINANCE(A8,""High"")"),"#N/A") -> #N/A | Q8: =IFERROR(__xludf.DUMMYFUNCTION("GOOGLEFINANCE(A8,""low"")"),"#N/A") -> #N/A | R8: =IFERROR(__xludf.DUMMYFUNCTION("abs(P8-Q8)/GOOGLEFINANCE(A8,""closeyest"")"),"#N/A") -> #N/A | S8: =D8/Y8-1 -> #N/A | W8: =IF(ISERROR(if(or(AND(Q8<=T8,T8<=P8),AND(Q8<=U8, U8<=P8)),"TRADE ALERT","")),"DATA UNAVAILABLE",if(or(AND(Q8<=T8,T8<=P8),T8>P8,AND(Q8<=U8, U8<=P8)),"TRADE ALERT"&" - Price level hit for "&A8&" currently at "&D8&" "&B8,"")) -> DATA UNAVAILABLE | X8: =IFERROR(__xludf.DUMMYFUNCTION("GOOGLEFINANCE($A8,X$3)"),"#N/A") -> #N/A | Y8: =IFERROR(__xludf.DUMMYFUNCTION("GOOGLEFINANCE($A8,Y$3)"),"#N/A") -> #N/A | Z8: =IFERROR(__xludf.DUMMYFUNCTION("GOOGLEFINANCE($A8,Z$3)"),"#N/A") -> #N/A | AA8: =IFERROR(__xludf.DUMMYFUNCTION("GOOGLEFINANCE($A8,AA$3)"),"#N/A") -> #N/A | AB8: =IFERROR(__xludf.DUMMYFUNCTION("GOOGLEFINANCE($A8,AB$3)"),"#N/A") -> #N/A | AC8: =IFERROR(__xludf.DUMMYFUNCTION("GOOGLEFINANCE($A8,AC$3)"),"#N/A") -> #N/A | AD8: =IFERROR(__xludf.DUMMYFUNCTION("GOOGLEFINANCE($A8,AD$3)"),"#N/A") -> #N/A | AE8: =IFERROR(__xludf.DUMMYFUNCTION("GOOGLEFINANCE($A8,AE$3)"),"#N/A") -> #N/A
B9: =IFERROR(__xludf.DUMMYFUNCTION("GOOGLEFINANCE(A9,""name"")"),"#N/A") -> #N/A | D9: =IFERROR(__xludf.DUMMYFUNCTION("GOOGLEFINANCE(A9)"),"#N/A") -> #N/A | F9: =IFERROR(__xludf.DUMMYFUNCTION("IF(M9=""USD"",E9/GOOGLEFINANCE(""CURRENCY:GBPUSD""),E9)"),"#N/A") -> #N/A | H9: =IFERROR(__xludf.DUMMYFUNCTION("if(isblank(A9)=TRUE,0,if(M9=""GBX"",E9*G9/100,IF(M9=""EUR"",E9*G9/GOOGLEFINANCE(""CURRENCY:GBPEUR""),E9*G9/GOOGLEFINANCE(""CURRENCY:GBPUSD""))))"),0.0) -> 0 | I9: =IFERROR(__xludf.DUMMYFUNCTION("if(isblank(A9)=TRUE,0,if(M9=""GBX"",D9*G9/100,IF(M9=""EUR"",D9*G9/GOOGLEFINANCE(""CURRENCY:GBPEUR""),D9*G9/GOOGLEFINANCE(""CURRENCY:GBPUSD""))))"),0.0) -> 0 | J9: =H9/$B$1 -> 0 | K9: =I9/H9-1 -> #DIV/0! | L9: =IFERROR(__xludf.DUMMYFUNCTION("SPARKLINE(GoogleFinance(A9, ""price"", TODAY()-30, TODAY()),{""color"",""blue"";""linewidth"",2}) "),"#N/A") -> #N/A | M9: =IFERROR(__xludf.DUMMYFUNCTION("GOOGLEFINANCE(A9,""currency"")"),"#N/A") -> #N/A | N9: =round(D9/AE9-1,4) -> #N/A | O9: =IFERROR(__xludf.DUMMYFUNCTION("GOOGLEFINANCE(A9,""Change"")"),"#N/A") -> #N/A | P9: =IFERROR(__xludf.DUMMYFUNCTION("GOOGLEFINANCE(A9,""High"")"),"#N/A") -> #N/A | Q9: =IFERROR(__xludf.DUMMYFUNCTION("GOOGLEFINANCE(A9,""low"")"),"#N/A") -> #N/A | R9: =IFERROR(__xludf.DUMMYFUNCTION("abs(P9-Q9)/GOOGLEFINANCE(A9,""closeyest"")"),"#N/A") -> #N/A | S9: =D9/Y9-1 -> #N/A | W9: =IF(ISERROR(if(or(AND(Q9<=T9,T9<=P9),AND(Q9<=U9, U9<=P9)),"TRADE ALERT","")),"DATA UNAVAILABLE",if(or(AND(Q9<=T9,T9<=P9),T9>P9,AND(Q9<=U9, U9<=P9)),"TRADE ALERT"&" - Price level hit for "&A9&" currently at "&D9&" "&B9,"")) -> DATA UNAVAILABLE | X9: =IFERROR(__xludf.DUMMYFUNCTION("GOOGLEFINANCE($A9,X$3)"),"#N/A") -> #N/A | Y9: =IFERROR(__xludf.DUMMYFUNCTION("GOOGLEFINANCE($A9,Y$3)"),"#N/A") -> #N/A | Z9: =IFERROR(__xludf.DUMMYFUNCTION("GOOGLEFINANCE($A9,Z$3)"),"#N/A") -> #N/A | AA9: =IFERROR(__xludf.DUMMYFUNCTION("GOOGLEFINANCE($A9,AA$3)"),"#N/A") -> #N/A | AB9: =IFERROR(__xludf.DUMMYFUNCTION("GOOGLEFINANCE($A9,AB$3)"),"#N/A") -> #N/A | AC9: =IFERROR(__xludf.DUMMYFUNCTION("GOOGLEFINANCE($A9,AC$3)"),"#N/A") -> #N/A | AD9: =IFERROR(__xludf.DUMMYFUNCTION("GOOGLEFINANCE($A9,AD$3)"),"#N/A") -> #N/A | AE9: =IFERROR(__xludf.DUMMYFUNCTION("GOOGLEFINANCE($A9,AE$3)"),"#N/A") -> #N/A
B10: =IFERROR(__xludf.DUMMYFUNCTION("GOOGLEFINANCE(A10,""name"")"),"#N/A") -> #N/A | D10: =IFERROR(__xludf.DUMMYFUNCTION("GOOGLEFINANCE(A10)"),"#N/A") -> #N/A | F10: =IFERROR(__xludf.DUMMYFUNCTION("IF(M10=""USD"",E10/GOOGLEFINANCE(""CURRENCY:GBPUSD""),E10)"),"#N/A") -> #N/A | H10: =IFERROR(__xludf.DUMMYFUNCTION("if(isblank(A10)=TRUE,0,if(M10=""GBX"",E10*G10/100,IF(M10=""EUR"",E10*G10/GOOGLEFINANCE(""CURRENCY:GBPEUR""),E10*G10/GOOGLEFINANCE(""CURRENCY:GBPUSD""))))"),0.0) -> 0 | I10: =IFERROR(__xludf.DUMMYFUNCTION("if(isblank(A10)=TRUE,0,if(M10=""GBX"",D10*G10/100,IF(M10=""EUR"",D10*G10/GOOGLEFINANCE(""CURRENCY:GBPEUR""),D10*G10/GOOGLEFINANCE(""CURRENCY:GBPUSD""))))"),0.0) -> 0 | J10: =H10/$B$1 -> 0 | K10: =I10/H10-1 -> #DIV/0! | L10: =IFERROR(__xludf.DUMMYFUNCTION("SPARKLINE(GoogleFinance(A10, ""price"", TODAY()-30, TODAY()),{""color"",""blue"";""linewidth"",2}) "),"#N/A") -> #N/A | M10: =IFERROR(__xludf.DUMMYFUNCTION("GOOGLEFINANCE(A10,""currency"")"),"#N/A") -> #N/A | N10: =round(D10/AE10-1,4) -> #N/A | O10: =IFERROR(__xludf.DUMMYFUNCTION("GOOGLEFINANCE(A10,""Change"")"),"#N/A") -> #N/A | P10: =IFERROR(__xludf.DUMMYFUNCTION("GOOGLEFINANCE(A10,""High"")"),"#N/A") -> #N/A | Q10: =IFERROR(__xludf.DUMMYFUNCTION("GOOGLEFINANCE(A10,""low"")"),"#N/A") -> #N/A | R10: =IFERROR(__xludf.DUMMYFUNCTION("abs(P10-Q10)/GOOGLEFINANCE(A10,""closeyest"")"),"#N/A") -> #N/A | S10: =D10/Y10-1 -> #N/A | W10: =IF(ISERROR(if(or(AND(Q10<=T10,T10<=P10),AND(Q10<=U10, U10<=P10)),"TRADE ALERT","")),"DATA UNAVAILABLE",if(or(AND(Q10<=T10,T10<=P10),T10>P10,AND(Q10<=U10, U10<=P10)),"TRADE ALERT"&" - Price level hit for "&A10&" currently at "&D10&" "&B10,"")) -> DATA UNAVAILABLE | X10: =IFERROR(__xludf.DUMMYFUNCTION("GOOGLEFINANCE($A10,X$3)"),"#N/A") -> #N/A | Y10: =IFERROR(__xludf.DUMMYFUNCTION("GOOGLEFINANCE($A10,Y$3)"),"#N/A") -> #N/A | Z10: =IFERROR(__xludf.DUMMYFUNCTION("GOOGLEFINANCE($A10,Z$3)"),"#N/A") -> #N/A | AA10: =IFERROR(__xludf.DUMMYFUNCTION("GOOGLEFINANCE($A10,AA$3)"),"#N/A") -> #N/A | AB10: =IFERROR(__xludf.DUMMYFUNCTION("GOOGLEFINANCE($A10,AB$3)"),"#N/A") -> #N/A | AC10: =IFERROR(__xludf.DUMMYFUNCTION("GOOGLEFINANCE($A10,AC$3)"),"#N/A") -> #N/A | AD10: =IFERROR(__xludf.DUMMYFUNCTION("GOOGLEFINANCE($A10,AD$3)"),"#N/A") -> #N/A | AE10: =IFERROR(__xludf.DUMMYFUNCTION("GOOGLEFINANCE($A10,AE$3)"),"#N/A") -> #N/A
B11: =IFERROR(__xludf.DUMMYFUNCTION("GOOGLEFINANCE(A11,""name"")"),"#N/A") -> #N/A | D11: =IFERROR(__xludf.DUMMYFUNCTION("GOOGLEFINANCE(A11)"),"#N/A") -> #N/A | F11: =IFERROR(__xludf.DUMMYFUNCTION("IF(M11=""USD"",E11/GOOGLEFINANCE(""CURRENCY:GBPUSD""),E11)"),"#N/A") -> #N/A | H11: =IFERROR(__xludf.DUMMYFUNCTION("if(isblank(A11)=TRUE,0,if(M11=""GBX"",E11*G11/100,IF(M11=""EUR"",E11*G11/GOOGLEFINANCE(""CURRENCY:GBPEUR""),E11*G11/GOOGLEFINANCE(""CURRENCY:GBPUSD""))))"),0.0) -> 0 | I11: =IFERROR(__xludf.DUMMYFUNCTION("if(isblank(A11)=TRUE,0,if(M11=""GBX"",D11*G11/100,IF(M11=""EUR"",D11*G11/GOOGLEFINANCE(""CURRENCY:GBPEUR""),D11*G11/GOOGLEFINANCE(""CURRENCY:GBPUSD""))))"),0.0) -> 0 | J11: =H11/$B$1 -> 0 | K11: =I11/H11-1 -> #DIV/0! | L11: =IFERROR(__xludf.DUMMYFUNCTION("SPARKLINE(GoogleFinance(A11, ""price"", TODAY()-30, TODAY()),{""color"",""blue"";""linewidth"",2}) "),"#N/A") -> #N/A | M11: =IFERROR(__xludf.DUMMYFUNCTION("GOOGLEFINANCE(A11,""currency"")"),"#N/A") -> #N/A | N11: =round(D11/AE11-1,4) -> #N/A | O11: =IFERROR(__xludf.DUMMYFUNCTION("GOOGLEFINANCE(A11,""Change"")"),"#N/A") -> #N/A | P11: =IFERROR(__xludf.DUMMYFUNCTION("GOOGLEFINANCE(A11,""High"")"),"#N/A") -> #N/A | Q11: =IFERROR(__xludf.DUMMYFUNCTION("GOOGLEFINANCE(A11,""low"")"),"#N/A") -> #N/A | R11: =IFERROR(__xludf.DUMMYFUNCTION("abs(P11-Q11)/GOOGLEFINANCE(A11,""closeyest"")"),"#N/A") -> #N/A | S11: =D11/Y11-1 -> #N/A | W11: =IF(ISERROR(if(or(AND(Q11<=T11,T11<=P11),AND(Q11<=U11, U11<=P11)),"TRADE ALERT","")),"DATA UNAVAILABLE",if(or(AND(Q11<=T11,T11<=P11),T11>P11,AND(Q11<=U11, U11<=P11)),"TRADE ALERT"&" - Price level hit for "&A11&" currently at "&D11&" "&B11,"")) -> DATA UNAVAILABLE | X11: =IFERROR(__xludf.DUMMYFUNCTION("GOOGLEFINANCE($A11,X$3)"),"#N/A") -> #N/A | Y11: =IFERROR(__xludf.DUMMYFUNCTION("GOOGLEFINANCE($A11,Y$3)"),"#N/A") -> #N/A | Z11: =IFERROR(__xludf.DUMMYFUNCTION("GOOGLEFINANCE($A11,Z$3)"),"#N/A") -> #N/A | AA11: =IFERROR(__xludf.DUMMYFUNCTION("GOOGLEFINANCE($A11,AA$3)"),"#N/A") -> #N/A | AB11: =IFERROR(__xludf.DUMMYFUNCTION("GOOGLEFINANCE($A11,AB$3)"),"#N/A") -> #N/A | AC11: =IFERROR(__xludf.DUMMYFUNCTION("GOOGLEFINANCE($A11,AC$3)"),"#N/A") -> #N/A | AD11: =IFERROR(__xludf.DUMMYFUNCTION("GOOGLEFINANCE($A11,AD$3)"),"#N/A") -> #N/A | AE11: =IFERROR(__xludf.DUMMYFUNCTION("GOOGLEFINANCE($A11,AE$3)"),"#N/A") -> #N/A
B12: =IFERROR(__xludf.DUMMYFUNCTION("GOOGLEFINANCE(A12,""name"")"),"#N/A") -> #N/A | D12: =IFERROR(__xludf.DUMMYFUNCTION("GOOGLEFINANCE(A12)"),"#N/A") -> #N/A | F12: =IFERROR(__xludf.DUMMYFUNCTION("IF(M12=""USD"",E12/GOOGLEFINANCE(""CURRENCY:GBPUSD""),E12)"),"#N/A") -> #N/A | H12: =IFERROR(__xludf.DUMMYFUNCTION("if(isblank(A12)=TRUE,0,if(M12=""GBX"",E12*G12/100,IF(M12=""EUR"",E12*G12/GOOGLEFINANCE(""CURRENCY:GBPEUR""),E12*G12/GOOGLEFINANCE(""CURRENCY:GBPUSD""))))"),0.0) -> 0 | I12: =IFERROR(__xludf.DUMMYFUNCTION("if(isblank(A12)=TRUE,0,if(M12=""GBX"",D12*G12/100,IF(M12=""EUR"",D12*G12/GOOGLEFINANCE(""CURRENCY:GBPEUR""),D12*G12/GOOGLEFINANCE(""CURRENCY:GBPUSD""))))"),0.0) -> 0 | J12: =H12/$B$1 -> 0 | K12: =I12/H12-1 -> #DIV/0! | L12: =IFERROR(__xludf.DUMMYFUNCTION("SPARKLINE(GoogleFinance(A12, ""price"", TODAY()-30, TODAY()),{""color"",""blue"";""linewidth"",2}) "),"#N/A") -> #N/A | M12: =IFERROR(__xludf.DUMMYFUNCTION("GOOGLEFINANCE(A12,""currency"")"),"#N/A") -> #N/A | N12: =round(D12/AE12-1,4) -> #N/A | O12: =IFERROR(__xludf.DUMMYFUNCTION("GOOGLEFINANCE(A12,""Change"")"),"#N/A") -> #N/A | P12: =IFERROR(__xludf.DUMMYFUNCTION("GOOGLEFINANCE(A12,""High"")"),"#N/A") -> #N/A | Q12: =IFERROR(__xludf.DUMMYFUNCTION("GOOGLEFINANCE(A12,""low"")"),"#N/A") -> #N/A | R12: =IFERROR(__xludf.DUMMYFUNCTION("abs(P12-Q12)/GOOGLEFINANCE(A12,""closeyest"")"),"#N/A") -> #N/A | S12: =D12/Y12-1 -> #N/A | W12: =IF(ISERROR(if(or(AND(Q12<=T12,T12<=P12),AND(Q12<=U12, U12<=P12)),"TRADE ALERT","")),"DATA UNAVAILABLE",if(or(AND(Q12<=T12,T12<=P12),T12>P12,AND(Q12<=U12, U12<=P12)),"TRADE ALERT"&" - Price level hit for "&A12&" currently at "&D12&" "&B12,"")) -> DATA UNAVAILABLE | X12: =IFERROR(__xludf.DUMMYFUNCTION("GOOGLEFINANCE($A12,X$3)"),"#N/A") -> #N/A | Y12: =IFERROR(__xludf.DUMMYFUNCTION("GOOGLEFINANCE($A12,Y$3)"),"#N/A") -> #N/A | Z12: =IFERROR(__xludf.DUMMYFUNCTION("GOOGLEFINANCE($A12,Z$3)"),"#N/A") -> #N/A | AA12: =IFERROR(__xludf.DUMMYFUNCTION("GOOGLEFINANCE($A12,AA$3)"),"#N/A") -> #N/A | AB12: =IFERROR(__xludf.DUMMYFUNCTION("GOOGLEFINANCE($A12,AB$3)"),"#N/A") -> #N/A | AC12: =IFERROR(__xludf.DUMMYFUNCTION("GOOGLEFINANCE($A12,AC$3)"),"#N/A") -> #N/A | AD12: =IFERROR(__xludf.DUMMYFUNCTION("GOOGLEFINANCE($A12,AD$3)"),"#N/A") -> #N/A | AE12: =IFERROR(__xludf.DUMMYFUNCTION("GOOGLEFINANCE($A12,AE$3)"),"#N/A") -> #N/A
B13: =IFERROR(__xludf.DUMMYFUNCTION("GOOGLEFINANCE(A13,""name"")"),"#N/A") -> #N/A | D13: =IFERROR(__xludf.DUMMYFUNCTION("GOOGLEFINANCE(A13)"),"#N/A") -> #N/A | F13: =IFERROR(__xludf.DUMMYFUNCTION("IF(M13=""USD"",E13/GOOGLEFINANCE(""CURRENCY:GBPUSD""),E13)"),"#N/A") -> #N/A | H13: =IFERROR(__xludf.DUMMYFUNCTION("if(isblank(A13)=TRUE,0,if(M13=""GBX"",E13*G13/100,IF(M13=""EUR"",E13*G13/GOOGLEFINANCE(""CURRENCY:GBPEUR""),E13*G13/GOOGLEFINANCE(""CURRENCY:GBPUSD""))))"),0.0) -> 0 | I13: =IFERROR(__xludf.DUMMYFUNCTION("if(isblank(A13)=TRUE,0,if(M13=""GBX"",D13*G13/100,IF(M13=""EUR"",D13*G13/GOOGLEFINANCE(""CURRENCY:GBPEUR""),D13*G13/GOOGLEFINANCE(""CURRENCY:GBPUSD""))))"),0.0) -> 0 | J13: =H13/$B$1 -> 0 | K13: =I13/H13-1 -> #DIV/0! | L13: =IFERROR(__xludf.DUMMYFUNCTION("SPARKLINE(GoogleFinance(A13, ""price"", TODAY()-30, TODAY()),{""color"",""blue"";""linewidth"",2}) "),"#N/A") -> #N/A | M13: =IFERROR(__xludf.DUMMYFUNCTION("GOOGLEFINANCE(A13,""currency"")"),"#N/A") -> #N/A | N13: =round(D13/AE13-1,4) -> #N/A | O13: =IFERROR(__xludf.DUMMYFUNCTION("GOOGLEFINANCE(A13,""Change"")"),"#N/A") -> #N/A | P13: =IFERROR(__xludf.DUMMYFUNCTION("GOOGLEFINANCE(A13,""High"")"),"#N/A") -> #N/A | Q13: =IFERROR(__xludf.DUMMYFUNCTION("GOOGLEFINANCE(A13,""low"")"),"#N/A") -> #N/A | R13: =IFERROR(__xludf.DUMMYFUNCTION("abs(P13-Q13)/GOOGLEFINANCE(A13,""closeyest"")"),"#N/A") -> #N/A | S13: =D13/Y13-1 -> #N/A | W13: =IF(ISERROR(if(or(AND(Q13<=T13,T13<=P13),AND(Q13<=U13, U13<=P13)),"TRADE ALERT","")),"DATA UNAVAILABLE",if(or(AND(Q13<=T13,T13<=P13),T13>P13,AND(Q13<=U13, U13<=P13)),"TRADE ALERT"&" - Price level hit for "&A13&" currently at "&D13&" "&B13,"")) -> DATA UNAVAILABLE | X13: =IFERROR(__xludf.DUMMYFUNCTION("GOOGLEFINANCE($A13,X$3)"),"#N/A") -> #N/A | Y13: =IFERROR(__xludf.DUMMYFUNCTION("GOOGLEFINANCE($A13,Y$3)"),"#N/A") -> #N/A | Z13: =IFERROR(__xludf.DUMMYFUNCTION("GOOGLEFINANCE($A13,Z$3)"),"#N/A") -> #N/A | AA13: =IFERROR(__xludf.DUMMYFUNCTION("GOOGLEFINANCE($A13,AA$3)"),"#N/A") -> #N/A | AB13: =IFERROR(__xludf.DUMMYFUNCTION("GOOGLEFINANCE($A13,AB$3)"),"#N/A") -> #N/A | AC13: =IFERROR(__xludf.DUMMYFUNCTION("GOOGLEFINANCE($A13,AC$3)"),"#N/A") -> #N/A | AD13: =IFERROR(__xludf.DUMMYFUNCTION("GOOGLEFINANCE($A13,AD$3)"),"#N/A") -> #N/A | AE13: =IFERROR(__xludf.DUMMYFUNCTION("GOOGLEFINANCE($A13,AE$3)"),"#N/A") -> #N/A
B14: =IFERROR(__xludf.DUMMYFUNCTION("GOOGLEFINANCE(A14,""name"")"),"#N/A") -> #N/A | D14: =IFERROR(__xludf.DUMMYFUNCTION("GOOGLEFINANCE(A14)"),"#N/A") -> #N/A | F14: =IFERROR(__xludf.DUMMYFUNCTION("IF(M14=""USD"",E14/GOOGLEFINANCE(""CURRENCY:GBPUSD""),E14)"),"#N/A") -> #N/A | H14: =IFERROR(__xludf.DUMMYFUNCTION("if(isblank(A14)=TRUE,0,if(M14=""GBX"",E14*G14/100,IF(M14=""EUR"",E14*G14/GOOGLEFINANCE(""CURRENCY:GBPEUR""),E14*G14/GOOGLEFINANCE(""CURRENCY:GBPUSD""))))"),0.0) -> 0 | I14: =IFERROR(__xludf.DUMMYFUNCTION("if(isblank(A14)=TRUE,0,if(M14=""GBX"",D14*G14/100,IF(M14=""EUR"",D14*G14/GOOGLEFINANCE(""CURRENCY:GBPEUR""),D14*G14/GOOGLEFINANCE(""CURRENCY:GBPUSD""))))"),0.0) -> 0 | J14: =H14/$B$1 -> 0 | K14: =I14/H14-1 -> #DIV/0! | L14: =IFERROR(__xludf.DUMMYFUNCTION("SPARKLINE(GoogleFinance(A14, ""price"", TODAY()-30, TODAY()),{""color"",""blue"";""linewidth"",2}) "),"#N/A") -> #N/A | M14: =IFERROR(__xludf.DUMMYFUNCTION("GOOGLEFINANCE(A14,""currency"")"),"#N/A") -> #N/A | N14: =round(D14/AE14-1,4) -> #N/A | O14: =IFERROR(__xludf.DUMMYFUNCTION("GOOGLEFINANCE(A14,""Change"")"),"#N/A") -> #N/A | P14: =IFERROR(__xludf.DUMMYFUNCTION("GOOGLEFINANCE(A14,""High"")"),"#N/A") -> #N/A | Q14: =IFERROR(__xludf.DUMMYFUNCTION("GOOGLEFINANCE(A14,""low"")"),"#N/A") -> #N/A | R14: =IFERROR(__xludf.DUMMYFUNCTION("abs(P14-Q14)/GOOGLEFINANCE(A14,""closeyest"")"),"#N/A") -> #N/A | S14: =D14/Y14-1 -> #N/A | W14: =IF(ISERROR(if(or(AND(Q14<=T14,T14<=P14),AND(Q14<=U14, U14<=P14)),"TRADE ALERT","")),"DATA UNAVAILABLE",if(or(AND(Q14<=T14,T14<=P14),T14>P14,AND(Q14<=U14, U14<=P14)),"TRADE ALERT"&" - Price level hit for "&A14&" currently at "&D14&" "&B14,"")) -> DATA UNAVAILABLE | X14: =IFERROR(__xludf.DUMMYFUNCTION("GOOGLEFINANCE($A14,X$3)"),"#N/A") -> #N/A | Y14: =IFERROR(__xludf.DUMMYFUNCTION("GOOGLEFINANCE($A14,Y$3)"),"#N/A") -> #N/A | Z14: =IFERROR(__xludf.DUMMYFUNCTION("GOOGLEFINANCE($A14,Z$3)"),"#N/A") -> #N/A | AA14: =IFERROR(__xludf.DUMMYFUNCTION("GOOGLEFINANCE($A14,AA$3)"),"#N/A") -> #N/A | AB14: =IFERROR(__xludf.DUMMYFUNCTION("GOOGLEFINANCE($A14,AB$3)"),"#N/A") -> #N/A | AC14: =IFERROR(__xludf.DUMMYFUNCTION("GOOGLEFINANCE($A14,AC$3)"),"#N/A") -> #N/A | AD14: =IFERROR(__xludf.DUMMYFUNCTION("GOOGLEFINANCE($A14,AD$3)"),"#N/A") -> #N/A | AE14: =IFERROR(__xludf.DUMMYFUNCTION("GOOGLEFINANCE($A14,AE$3)"),"#N/A") -> #N/A
B15: =IFERROR(__xludf.DUMMYFUNCTION("GOOGLEFINANCE(A15,""name"")"),"#N/A") -> #N/A | D15: =IFERROR(__xludf.DUMMYFUNCTION("GOOGLEFINANCE(A15)"),"#N/A") -> #N/A | F15: =IFERROR(__xludf.DUMMYFUNCTION("IF(M15=""USD"",E15/GOOGLEFINANCE(""CURRENCY:GBPUSD""),E15)"),"#N/A") -> #N/A | H15: =IFERROR(__xludf.DUMMYFUNCTION("if(isblank(A15)=TRUE,0,if(M15=""GBX"",E15*G15/100,IF(M15=""EUR"",E15*G15/GOOGLEFINANCE(""CURRENCY:GBPEUR""),E15*G15/GOOGLEFINANCE(""CURRENCY:GBPUSD""))))"),0.0) -> 0 | I15: =IFERROR(__xludf.DUMMYFUNCTION("if(isblank(A15)=TRUE,0,if(M15=""GBX"",D15*G15/100,IF(M15=""EUR"",D15*G15/GOOGLEFINANCE(""CURRENCY:GBPEUR""),D15*G15/GOOGLEFINANCE(""CURRENCY:GBPUSD""))))"),0.0) -> 0 | J15: =H15/$B$1 -> 0 | K15: =I15/H15-1 -> #DIV/0! | L15: =IFERROR(__xludf.DUMMYFUNCTION("SPARKLINE(GoogleFinance(A15, ""price"", TODAY()-30, TODAY()),{""color"",""blue"";""linewidth"",2}) "),"#N/A") -> #N/A | M15: =IFERROR(__xludf.DUMMYFUNCTION("GOOGLEFINANCE(A15,""currency"")"),"#N/A") -> #N/A | N15: =round(D15/AE15-1,4) -> #N/A | O15: =IFERROR(__xludf.DUMMYFUNCTION("GOOGLEFINANCE(A15,""Change"")"),"#N/A") -> #N/A | P15: =IFERROR(__xludf.DUMMYFUNCTION("GOOGLEFINANCE(A15,""High"")"),"#N/A") -> #N/A | Q15: =IFERROR(__xludf.DUMMYFUNCTION("GOOGLEFINANCE(A15,""low"")"),"#N/A") -> #N/A | R15: =IFERROR(__xludf.DUMMYFUNCTION("abs(P15-Q15)/GOOGLEFINANCE(A15,""closeyest"")"),"#N/A") -> #N/A | S15: =D15/Y15-1 -> #N/A | W15: =IF(ISERROR(if(or(AND(Q15<=T15,T15<=P15),AND(Q15<=U15, U15<=P15)),"TRADE ALERT","")),"DATA UNAVAILABLE",if(or(AND(Q15<=T15,T15<=P15),T15>P15,AND(Q15<=U15, U15<=P15)),"TRADE ALERT"&" - Price level hit for "&A15&" currently at "&D15&" "&B15,"")) -> DATA UNAVAILABLE | X15: =IFERROR(__xludf.DUMMYFUNCTION("GOOGLEFINANCE($A15,X$3)"),"#N/A") -> #N/A | Y15: =IFERROR(__xludf.DUMMYFUNCTION("GOOGLEFINANCE($A15,Y$3)"),"#N/A") -> #N/A | Z15: =IFERROR(__xludf.DUMMYFUNCTION("GOOGLEFINANCE($A15,Z$3)"),"#N/A") -> #N/A | AA15: =IFERROR(__xludf.DUMMYFUNCTION("GOOGLEFINANCE($A15,AA$3)"),"#N/A") -> #N/A | AB15: =IFERROR(__xludf.DUMMYFUNCTION("GOOGLEFINANCE($A15,AB$3)"),"#N/A") -> #N/A | AC15: =IFERROR(__xludf.DUMMYFUNCTION("GOOGLEFINANCE($A15,AC$3)"),"#N/A") -> #N/A | AD15: =IFERROR(__xludf.DUMMYFUNCTION("GOOGLEFINANCE($A15,AD$3)"),"#N/A") -> #N/A | AE15: =IFERROR(__xludf.DUMMYFUNCTION("GOOGLEFINANCE($A15,AE$3)"),"#N/A") -> #N/A
B16: =IFERROR(__xludf.DUMMYFUNCTION("GOOGLEFINANCE(A16,""name"")"),"#N/A") -> #N/A | D16: =IFERROR(__xludf.DUMMYFUNCTION("GOOGLEFINANCE(A16)"),"#N/A") -> #N/A | F16: =IFERROR(__xludf.DUMMYFUNCTION("IF(M16=""USD"",E16/GOOGLEFINANCE(""CURRENCY:GBPUSD""),E16)"),"#N/A") -> #N/A | H16: =IFERROR(__xludf.DUMMYFUNCTION("if(isblank(A16)=TRUE,0,if(M16=""GBX"",E16*G16/100,IF(M16=""EUR"",E16*G16/GOOGLEFINANCE(""CURRENCY:GBPEUR""),E16*G16/GOOGLEFINANCE(""CURRENCY:GBPUSD""))))"),0.0) -> 0 | I16: =IFERROR(__xludf.DUMMYFUNCTION("if(isblank(A16)=TRUE,0,if(M16=""GBX"",D16*G16/100,IF(M16=""EUR"",D16*G16/GOOGLEFINANCE(""CURRENCY:GBPEUR""),D16*G16/GOOGLEFINANCE(""CURRENCY:GBPUSD""))))"),0.0) -> 0 | J16: =H16/$B$1 -> 0 | K16: =I16/H16-1 -> #DIV/0! | L16: =IFERROR(__xludf.DUMMYFUNCTION("SPARKLINE(GoogleFinance(A16, ""price"", TODAY()-30, TODAY()),{""color"",""blue"";""linewidth"",2}) "),"#N/A") -> #N/A | M16: =IFERROR(__xludf.DUMMYFUNCTION("GOOGLEFINANCE(A16,""currency"")"),"#N/A") -> #N/A | N16: =round(D16/AE16-1,4) -> #N/A | O16: =IFERROR(__xludf.DUMMYFUNCTION("GOOGLEFINANCE(A16,""Change"")"),"#N/A") -> #N/A | P16: =IFERROR(__xludf.DUMMYFUNCTION("GOOGLEFINANCE(A16,""High"")"),"#N/A") -> #N/A | Q16: =IFERROR(__xludf.DUMMYFUNCTION("GOOGLEFINANCE(A16,""low"")"),"#N/A") -> #N/A | R16: =IFERROR(__xludf.DUMMYFUNCTION("abs(P16-Q16)/GOOGLEFINANCE(A16,""closeyest"")"),"#N/A") -> #N/A | S16: =D16/Y16-1 -> #N/A | W16: =IF(ISERROR(if(or(AND(Q16<=T16,T16<=P16),AND(Q16<=U16, U16<=P16)),"TRADE ALERT","")),"DATA UNAVAILABLE",if(or(AND(Q16<=T16,T16<=P16),T16>P16,AND(Q16<=U16, U16<=P16)),"TRADE ALERT"&" - Price level hit for "&A16&" currently at "&D16&" "&B16,"")) -> DATA UNAVAILABLE | X16: =IFERROR(__xludf.DUMMYFUNCTION("GOOGLEFINANCE($A16,X$3)"),"#N/A") -> #N/A | Y16: =IFERROR(__xludf.DUMMYFUNCTION("GOOGLEFINANCE($A16,Y$3)"),"#N/A") -> #N/A | Z16: =IFERROR(__xludf.DUMMYFUNCTION("GOOGLEFINANCE($A16,Z$3)"),"#N/A") -> #N/A | AA16: =IFERROR(__xludf.DUMMYFUNCTION("GOOGLEFINANCE($A16,AA$3)"),"#N/A") -> #N/A | AB16: =IFERROR(__xludf.DUMMYFUNCTION("GOOGLEFINANCE($A16,AB$3)"),"#N/A") -> #N/A | AC16: =IFERROR(__xludf.DUMMYFUNCTION("GOOGLEFINANCE($A16,AC$3)"),"#N/A") -> #N/A | AD16: =IFERROR(__xludf.DUMMYFUNCTION("GOOGLEFINANCE($A16,AD$3)"),"#N/A") -> #N/A | AE16: =IFERROR(__xludf.DUMMYFUNCTION("GOOGLEFINANCE($A16,AE$3)"),"#N/A") -> #N/A
B17: =IFERROR(__xludf.DUMMYFUNCTION("GOOGLEFINANCE(A17,""name"")"),"#N/A") -> #N/A | D17: =IFERROR(__xludf.DUMMYFUNCTION("GOOGLEFINANCE(A17)"),"#N/A") -> #N/A | F17: =IFERROR(__xludf.DUMMYFUNCTION("IF(M17=""USD"",E17/GOOGLEFINANCE(""CURRENCY:GBPUSD""),E17)"),"#N/A") -> #N/A | H17: =IFERROR(__xludf.DUMMYFUNCTION("if(isblank(A17)=TRUE,0,if(M17=""GBX"",E17*G17/100,IF(M17=""EUR"",E17*G17/GOOGLEFINANCE(""CURRENCY:GBPEUR""),E17*G17/GOOGLEFINANCE(""CURRENCY:GBPUSD""))))"),0.0) -> 0 | I17: =IFERROR(__xludf.DUMMYFUNCTION("if(isblank(A17)=TRUE,0,if(M17=""GBX"",D17*G17/100,IF(M17=""EUR"",D17*G17/GOOGLEFINANCE(""CURRENCY:GBPEUR""),D17*G17/GOOGLEFINANCE(""CURRENCY:GBPUSD""))))"),0.0) -> 0 | J17: =H17/$B$1 -> 0 | K17: =I17/H17-1 -> #DIV/0! | L17: =IFERROR(__xludf.DUMMYFUNCTION("SPARKLINE(GoogleFinance(A17, ""price"", TODAY()-30, TODAY()),{""color"",""blue"";""linewidth"",2}) "),"#N/A") -> #N/A | M17: =IFERROR(__xludf.DUMMYFUNCTION("GOOGLEFINANCE(A17,""currency"")"),"#N/A") -> #N/A | N17: =round(D17/AE17-1,4) -> #N/A | O17: =IFERROR(__xludf.DUMMYFUNCTION("GOOGLEFINANCE(A17,""Change"")"),"#N/A") -> #N/A | P17: =IFERROR(__xludf.DUMMYFUNCTION("GOOGLEFINANCE(A17,""High"")"),"#N/A") -> #N/A | Q17: =IFERROR(__xludf.DUMMYFUNCTION("GOOGLEFINANCE(A17,""low"")"),"#N/A") -> #N/A | R17: =IFERROR(__xludf.DUMMYFUNCTION("abs(P17-Q17)/GOOGLEFINANCE(A17,""closeyest"")"),"#N/A") -> #N/A | S17: =D17/Y17-1 -> #N/A | W17: =IF(ISERROR(if(or(AND(Q17<=T17,T17<=P17),AND(Q17<=U17, U17<=P17)),"TRADE ALERT","")),"DATA UNAVAILABLE",if(or(AND(Q17<=T17,T17<=P17),T17>P17,AND(Q17<=U17, U17<=P17)),"TRADE ALERT"&" - Price level hit for "&A17&" currently at "&D17&" "&B17,"")) -> DATA UNAVAILABLE | X17: =IFERROR(__xludf.DUMMYFUNCTION("GOOGLEFINANCE($A17,X$3)"),"#N/A") -> #N/A | Y17: =IFERROR(__xludf.DUMMYFUNCTION("GOOGLEFINANCE($A17,Y$3)"),"#N/A") -> #N/A | Z17: =IFERROR(__xludf.DUMMYFUNCTION("GOOGLEFINANCE($A17,Z$3)"),"#N/A") -> #N/A | AA17: =IFERROR(__xludf.DUMMYFUNCTION("GOOGLEFINANCE($A17,AA$3)"),"#N/A") -> #N/A | AB17: =IFERROR(__xludf.DUMMYFUNCTION("GOOGLEFINANCE($A17,AB$3)"),"#N/A") -> #N/A | AC17: =IFERROR(__xludf.DUMMYFUNCTION("GOOGLEFINANCE($A17,AC$3)"),"#N/A") -> #N/A | AD17: =IFERROR(__xludf.DUMMYFUNCTION("GOOGLEFINANCE($A17,AD$3)"),"#N/A") -> #N/A | AE17: =IFERROR(__xludf.DUMMYFUNCTION("GOOGLEFINANCE($A17,AE$3)"),"#N/A") -> #N/A
B18: =IFERROR(__xludf.DUMMYFUNCTION("GOOGLEFINANCE(A18,""name"")"),"#N/A") -> #N/A | D18: =IFERROR(__xludf.DUMMYFUNCTION("GOOGLEFINANCE(A18)"),"#N/A") -> #N/A | F18: =IFERROR(__xludf.DUMMYFUNCTION("IF(M18=""USD"",E18/GOOGLEFINANCE(""CURRENCY:GBPUSD""),E18)"),"#N/A") -> #N/A | H18: =IFERROR(__xludf.DUMMYFUNCTION("if(isblank(A18)=TRUE,0,if(M18=""GBX"",E18*G18/100,IF(M18=""EUR"",E18*G18/GOOGLEFINANCE(""CURRENCY:GBPEUR""),E18*G18/GOOGLEFINANCE(""CURRENCY:GBPUSD""))))"),0.0) -> 0 | I18: =IFERROR(__xludf.DUMMYFUNCTION("if(isblank(A18)=TRUE,0,if(M18=""GBX"",D18*G18/100,IF(M18=""EUR"",D18*G18/GOOGLEFINANCE(""CURRENCY:GBPEUR""),D18*G18/GOOGLEFINANCE(""CURRENCY:GBPUSD""))))"),0.0) -> 0 | J18: =H18/$B$1 -> 0 | K18: =I18/H18-1 -> #DIV/0! | L18: =IFERROR(__xludf.DUMMYFUNCTION("SPARKLINE(GoogleFinance(A18, ""price"", TODAY()-30, TODAY()),{""color"",""blue"";""linewidth"",2}) "),"#N/A") -> #N/A | M18: =IFERROR(__xludf.DUMMYFUNCTION("GOOGLEFINANCE(A18,""currency"")"),"#N/A") -> #N/A | N18: =round(D18/AE18-1,4) -> #N/A | O18: =IFERROR(__xludf.DUMMYFUNCTION("GOOGLEFINANCE(A18,""Change"")"),"#N/A") -> #N/A | P18: =IFERROR(__xludf.DUMMYFUNCTION("GOOGLEFINANCE(A18,""High"")"),"#N/A") -> #N/A | Q18: =IFERROR(__xludf.DUMMYFUNCTION("GOOGLEFINANCE(A18,""low"")"),"#N/A") -> #N/A | R18: =IFERROR(__xludf.DUMMYFUNCTION("abs(P18-Q18)/GOOGLEFINANCE(A18,""closeyest"")"),"#N/A") -> #N/A | S18: =D18/Y18-1 -> #N/A | W18: =IF(ISERROR(if(or(AND(Q18<=T18,T18<=P18),AND(Q18<=U18, U18<=P18)),"TRADE ALERT","")),"DATA UNAVAILABLE",if(or(AND(Q18<=T18,T18<=P18),T18>P18,AND(Q18<=U18, U18<=P18)),"TRADE ALERT"&" - Price level hit for "&A18&" currently at "&D18&" "&B18,"")) -> DATA UNAVAILABLE | X18: =IFERROR(__xludf.DUMMYFUNCTION("GOOGLEFINANCE($A18,X$3)"),"#N/A") -> #N/A | Y18: =IFERROR(__xludf.DUMMYFUNCTION("GOOGLEFINANCE($A18,Y$3)"),"#N/A") -> #N/A | Z18: =IFERROR(__xludf.DUMMYFUNCTION("GOOGLEFINANCE($A18,Z$3)"),"#N/A") -> #N/A | AA18: =IFERROR(__xludf.DUMMYFUNCTION("GOOGLEFINANCE($A18,AA$3)"),"#N/A") -> #N/A | AB18: =IFERROR(__xludf.DUMMYFUNCTION("GOOGLEFINANCE($A18,AB$3)"),"#N/A") -> #N/A | AC18: =IFERROR(__xludf.DUMMYFUNCTION("GOOGLEFINANCE($A18,AC$3)"),"#N/A") -> #N/A | AD18: =IFERROR(__xludf.DUMMYFUNCTION("GOOGLEFINANCE($A18,AD$3)"),"#N/A") -> #N/A | AE18: =IFERROR(__xludf.DUMMYFUNCTION("GOOGLEFINANCE($A18,AE$3)"),"#N/A") -> #N/A
B19: =IFERROR(__xludf.DUMMYFUNCTION("GOOGLEFINANCE(A19,""name"")"),"#N/A") -> #N/A | D19: =IFERROR(__xludf.DUMMYFUNCTION("GOOGLEFINANCE(A19)"),"#N/A") -> #N/A | F19: =IFERROR(__xludf.DUMMYFUNCTION("IF(M19=""USD"",E19/GOOGLEFINANCE(""CURRENCY:GBPUSD""),E19)"),"#N/A") -> #N/A | H19: =IFERROR(__xludf.DUMMYFUNCTION("if(isblank(A19)=TRUE,0,if(M19=""GBX"",E19*G19/100,IF(M19=""EUR"",E19*G19/GOOGLEFINANCE(""CURRENCY:GBPEUR""),E19*G19/GOOGLEFINANCE(""CURRENCY:GBPUSD""))))"),0.0) -> 0 | I19: =IFERROR(__xludf.DUMMYFUNCTION("if(isblank(A19)=TRUE,0,if(M19=""GBX"",D19*G19/100,IF(M19=""EUR"",D19*G19/GOOGLEFINANCE(""CURRENCY:GBPEUR""),D19*G19/GOOGLEFINANCE(""CURRENCY:GBPUSD""))))"),0.0) -> 0 | J19: =H19/$B$1 -> 0 | K19: =I19/H19-1 -> #DIV/0! | L19: =IFERROR(__xludf.DUMMYFUNCTION("SPARKLINE(GoogleFinance(A19, ""price"", TODAY()-30, TODAY()),{""color"",""blue"";""linewidth"",2}) "),"#N/A") -> #N/A | M19: =IFERROR(__xludf.DUMMYFUNCTION("GOOGLEFINANCE(A19,""currency"")"),"#N/A") -> #N/A | N19: =round(D19/AE19-1,4) -> #N/A | O19: =IFERROR(__xludf.DUMMYFUNCTION("GOOGLEFINANCE(A19,""Change"")"),"#N/A") -> #N/A | P19: =IFERROR(__xludf.DUMMYFUNCTION("GOOGLEFINANCE(A19,""High"")"),"#N/A") -> #N/A | Q19: =IFERROR(__xludf.DUMMYFUNCTION("GOOGLEFINANCE(A19,""low"")"),"#N/A") -> #N/A | R19: =IFERROR(__xludf.DUMMYFUNCTION("abs(P19-Q19)/GOOGLEFINANCE(A19,""closeyest"")"),"#N/A") -> #N/A | S19: =D19/Y19-1 -> #N/A | W19: =IF(ISERROR(if(or(AND(Q19<=T19,T19<=P19),AND(Q19<=U19, U19<=P19)),"TRADE ALERT","")),"DATA UNAVAILABLE",if(or(AND(Q19<=T19,T19<=P19),T19>P19,AND(Q19<=U19, U19<=P19)),"TRADE ALERT"&" - Price level hit for "&A19&" currently at "&D19&" "&B19,"")) -> DATA UNAVAILABLE | X19: =IFERROR(__xludf.DUMMYFUNCTION("GOOGLEFINANCE($A19,X$3)"),"#N/A") -> #N/A | Y19: =IFERROR(__xludf.DUMMYFUNCTION("GOOGLEFINANCE($A19,Y$3)"),"#N/A") -> #N/A | Z19: =IFERROR(__xludf.DUMMYFUNCTION("GOOGLEFINANCE($A19,Z$3)"),"#N/A") -> #N/A | AA19: =IFERROR(__xludf.DUMMYFUNCTION("GOOGLEFINANCE($A19,AA$3)"),"#N/A") -> #N/A | AB19: =IFERROR(__xludf.DUMMYFUNCTION("GOOGLEFINANCE($A19,AB$3)"),"#N/A") -> #N/A | AC19: =IFERROR(__xludf.DUMMYFUNCTION("GOOGLEFINANCE($A19,AC$3)"),"#N/A") -> #N/A | AD19: =IFERROR(__xludf.DUMMYFUNCTION("GOOGLEFINANCE($A19,AD$3)"),"#N/A") -> #N/A | AE19: =IFERROR(__xludf.DUMMYFUNCTION("GOOGLEFINANCE($A19,AE$3)"),"#N/A") -> #N/A
B20: =IFERROR(__xludf.DUMMYFUNCTION("GOOGLEFINANCE(A20,""name"")"),"#N/A") -> #N/A | D20: =IFERROR(__xludf.DUMMYFUNCTION("GOOGLEFINANCE(A20)"),"#N/A") -> #N/A | F20: =IFERROR(__xludf.DUMMYFUNCTION("IF(M20=""USD"",E20/GOOGLEFINANCE(""CURRENCY:GBPUSD""),E20)"),"#N/A") -> #N/A | H20: =IFERROR(__xludf.DUMMYFUNCTION("if(isblank(A20)=TRUE,0,if(M20=""GBX"",E20*G20/100,IF(M20=""EUR"",E20*G20/GOOGLEFINANCE(""CURRENCY:GBPEUR""),E20*G20/GOOGLEFINANCE(""CURRENCY:GBPUSD""))))"),0.0) -> 0 | I20: =IFERROR(__xludf.DUMMYFUNCTION("if(isblank(A20)=TRUE,0,if(M20=""GBX"",D20*G20/100,IF(M20=""EUR"",D20*G20/GOOGLEFINANCE(""CURRENCY:GBPEUR""),D20*G20/GOOGLEFINANCE(""CURRENCY:GBPUSD""))))"),0.0) -> 0 | J20: =H20/$B$1 -> 0 | K20: =I20/H20-1 -> #DIV/0! | L20: =IFERROR(__xludf.DUMMYFUNCTION("SPARKLINE(GoogleFinance(A20, ""price"", TODAY()-30, TODAY()),{""color"",""blue"";""linewidth"",2}) "),"#N/A") -> #N/A | M20: =IFERROR(__xludf.DUMMYFUNCTION("GOOGLEFINANCE(A20,""currency"")"),"#N/A") -> #N/A | N20: =round(D20/AE20-1,4) -> #N/A | O20: =IFERROR(__xludf.DUMMYFUNCTION("GOOGLEFINANCE(A20,""Change"")"),"#N/A") -> #N/A | P20: =IFERROR(__xludf.DUMMYFUNCTION("GOOGLEFINANCE(A20,""High"")"),"#N/A") -> #N/A | Q20: =IFERROR(__xludf.DUMMYFUNCTION("GOOGLEFINANCE(A20,""low"")"),"#N/A") -> #N/A | R20: =IFERROR(__xludf.DUMMYFUNCTION("abs(P20-Q20)/GOOGLEFINANCE(A20,""closeyest"")"),"#N/A") -> #N/A | S20: =D20/Y20-1 -> #N/A | W20: =IF(ISERROR(if(or(AND(Q20<=T20,T20<=P20),AND(Q20<=U20, U20<=P20)),"TRADE ALERT","")),"DATA UNAVAILABLE",if(or(AND(Q20<=T20,T20<=P20),T20>P20,AND(Q20<=U20, U20<=P20)),"TRADE ALERT"&" - Price level hit for "&A20&" currently at "&D20&" "&B20,"")) -> DATA UNAVAILABLE | X20: =IFERROR(__xludf.DUMMYFUNCTION("GOOGLEFINANCE($A20,X$3)"),"#N/A") -> #N/A | Y20: =IFERROR(__xludf.DUMMYFUNCTION("GOOGLEFINANCE($A20,Y$3)"),"#N/A") -> #N/A | Z20: =IFERROR(__xludf.DUMMYFUNCTION("GOOGLEFINANCE($A20,Z$3)"),"#N/A") -> #N/A | AA20: =IFERROR(__xludf.DUMMYFUNCTION("GOOGLEFINANCE($A20,AA$3)"),"#N/A") -> #N/A | AB20: =IFERROR(__xludf.DUMMYFUNCTION("GOOGLEFINANCE($A20,AB$3)"),"#N/A") -> #N/A | AC20: =IFERROR(__xludf.DUMMYFUNCTION("GOOGLEFINANCE($A20,AC$3)"),"#N/A") -> #N/A | AD20: =IFERROR(__xludf.DUMMYFUNCTION("GOOGLEFINANCE($A20,AD$3)"),"#N/A") -> #N/A | AE20: =IFERROR(__xludf.DUMMYFUNCTION("GOOGLEFINANCE($A20,AE$3)"),"#N/A") -> #N/A
B21: =IFERROR(__xludf.DUMMYFUNCTION("GOOGLEFINANCE(A21,""name"")"),"#N/A") -> #N/A | D21: =IFERROR(__xludf.DUMMYFUNCTION("GOOGLEFINANCE(A21)"),"#N/A") -> #N/A | F21: =IFERROR(__xludf.DUMMYFUNCTION("IF(M21=""USD"",E21/GOOGLEFINANCE(""CURRENCY:GBPUSD""),E21)"),"#N/A") -> #N/A | H21: =IFERROR(__xludf.DUMMYFUNCTION("if(isblank(A21)=TRUE,0,if(M21=""GBX"",E21*G21/100,IF(M21=""EUR"",E21*G21/GOOGLEFINANCE(""CURRENCY:GBPEUR""),E21*G21/GOOGLEFINANCE(""CURRENCY:GBPUSD""))))"),0.0) -> 0 | I21: =IFERROR(__xludf.DUMMYFUNCTION("if(isblank(A21)=TRUE,0,if(M21=""GBX"",D21*G21/100,IF(M21=""EUR"",D21*G21/GOOGLEFINANCE(""CURRENCY:GBPEUR""),D21*G21/GOOGLEFINANCE(""CURRENCY:GBPUSD""))))"),0.0) -> 0 | J21: =H21/$B$1 -> 0 | K21: =I21/H21-1 -> #DIV/0! | L21: =IFERROR(__xludf.DUMMYFUNCTION("SPARKLINE(GoogleFinance(A21, ""price"", TODAY()-30, TODAY()),{""color"",""blue"";""linewidth"",2}) "),"#N/A") -> #N/A | M21: =IFERROR(__xludf.DUMMYFUNCTION("GOOGLEFINANCE(A21,""currency"")"),"#N/A") -> #N/A | N21: =round(D21/AE21-1,4) -> #N/A | O21: =IFERROR(__xludf.DUMMYFUNCTION("GOOGLEFINANCE(A21,""Change"")"),"#N/A") -> #N/A | P21: =IFERROR(__xludf.DUMMYFUNCTION("GOOGLEFINANCE(A21,""High"")"),"#N/A") -> #N/A | Q21: =IFERROR(__xludf.DUMMYFUNCTION("GOOGLEFINANCE(A21,""low"")"),"#N/A") -> #N/A | R21: =IFERROR(__xludf.DUMMYFUNCTION("abs(P21-Q21)/GOOGLEFINANCE(A21,""closeyest"")"),"#N/A") -> #N/A | S21: =D21/Y21-1 -> #N/A | W21: =IF(ISERROR(if(or(AND(Q21<=T21,T21<=P21),AND(Q21<=U21, U21<=P21)),"TRADE ALERT","")),"DATA UNAVAILABLE",if(or(AND(Q21<=T21,T21<=P21),T21>P21,AND(Q21<=U21, U21<=P21)),"TRADE ALERT"&" - Price level hit for "&A21&" currently at "&D21&" "&B21,"")) -> DATA UNAVAILABLE | X21: =IFERROR(__xludf.DUMMYFUNCTION("GOOGLEFINANCE($A21,X$3)"),"#N/A") -> #N/A | Y21: =IFERROR(__xludf.DUMMYFUNCTION("GOOGLEFINANCE($A21,Y$3)"),"#N/A") -> #N/A | Z21: =IFERROR(__xludf.DUMMYFUNCTION("GOOGLEFINANCE($A21,Z$3)"),"#N/A") -> #N/A | AA21: =IFERROR(__xludf.DUMMYFUNCTION("GOOGLEFINANCE($A21,AA$3)"),"#N/A") -> #N/A | AB21: =IFERROR(__xludf.DUMMYFUNCTION("GOOGLEFINANCE($A21,AB$3)"),"#N/A") -> #N/A | AC21: =IFERROR(__xludf.DUMMYFUNCTION("GOOGLEFINANCE($A21,AC$3)"),"#N/A") -> #N/A | AD21: =IFERROR(__xludf.DUMMYFUNCTION("GOOGLEFINANCE($A21,AD$3)"),"#N/A") -> #N/A | AE21: =IFERROR(__xludf.DUMMYFUNCTION("GOOGLEFINANCE($A21,AE$3)"),"#N/A") -> #N/A
B22: =IFERROR(__xludf.DUMMYFUNCTION("GOOGLEFINANCE(A22,""name"")"),"#N/A") -> #N/A | D22: =IFERROR(__xludf.DUMMYFUNCTION("GOOGLEFINANCE(A22)"),"#N/A") -> #N/A | F22: =IFERROR(__xludf.DUMMYFUNCTION("IF(M22=""USD"",E22/GOOGLEFINANCE(""CURRENCY:GBPUSD""),E22)"),"#N/A") -> #N/A | H22: =IFERROR(__xludf.DUMMYFUNCTION("if(isblank(A22)=TRUE,0,if(M22=""GBX"",E22*G22/100,IF(M22=""EUR"",E22*G22/GOOGLEFINANCE(""CURRENCY:GBPEUR""),E22*G22/GOOGLEFINANCE(""CURRENCY:GBPUSD""))))"),0.0) -> 0 | I22: =IFERROR(__xludf.DUMMYFUNCTION("if(isblank(A22)=TRUE,0,if(M22=""GBX"",D22*G22/100,IF(M22=""EUR"",D22*G22/GOOGLEFINANCE(""CURRENCY:GBPEUR""),D22*G22/GOOGLEFINANCE(""CURRENCY:GBPUSD""))))"),0.0) -> 0 | J22: =H22/$B$1 -> 0 | K22: =I22/H22-1 -> #DIV/0! | L22: =IFERROR(__xludf.DUMMYFUNCTION("SPARKLINE(GoogleFinance(A22, ""price"", TODAY()-30, TODAY()),{""color"",""blue"";""linewidth"",2}) "),"#N/A") -> #N/A | M22: =IFERROR(__xludf.DUMMYFUNCTION("GOOGLEFINANCE(A22,""currency"")"),"#N/A") -> #N/A | N22: =round(D22/AE22-1,4) -> #N/A | O22: =IFERROR(__xludf.DUMMYFUNCTION("GOOGLEFINANCE(A22,""Change"")"),"#N/A") -> #N/A | P22: =IFERROR(__xludf.DUMMYFUNCTION("GOOGLEFINANCE(A22,""High"")"),"#N/A") -> #N/A | Q22: =IFERROR(__xludf.DUMMYFUNCTION("GOOGLEFINANCE(A22,""low"")"),"#N/A") -> #N/A | R22: =IFERROR(__xludf.DUMMYFUNCTION("abs(P22-Q22)/GOOGLEFINANCE(A22,""closeyest"")"),"#N/A") -> #N/A | S22: =D22/Y22-1 -> #N/A | W22: =IF(ISERROR(if(or(AND(Q22<=T22,T22<=P22),AND(Q22<=U22, U22<=P22)),"TRADE ALERT","")),"DATA UNAVAILABLE",if(or(AND(Q22<=T22,T22<=P22),T22>P22,AND(Q22<=U22, U22<=P22)),"TRADE ALERT"&" - Price level hit for "&A22&" currently at "&D22&" "&B22,"")) -> DATA UNAVAILABLE | X22: =IFERROR(__xludf.DUMMYFUNCTION("GOOGLEFINANCE($A22,X$3)"),"#N/A") -> #N/A | Y22: =IFERROR(__xludf.DUMMYFUNCTION("GOOGLEFINANCE($A22,Y$3)"),"#N/A") -> #N/A | Z22: =IFERROR(__xludf.DUMMYFUNCTION("GOOGLEFINANCE($A22,Z$3)"),"#N/A") -> #N/A | AA22: =IFERROR(__xludf.DUMMYFUNCTION("GOOGLEFINANCE($A22,AA$3)"),"#N/A") -> #N/A | AB22: =IFERROR(__xludf.DUMMYFUNCTION("GOOGLEFINANCE($A22,AB$3)"),"#N/A") -> #N/A | AC22: =IFERROR(__xludf.DUMMYFUNCTION("GOOGLEFINANCE($A22,AC$3)"),"#N/A") -> #N/A | AD22: =IFERROR(__xludf.DUMMYFUNCTION("GOOGLEFINANCE($A22,AD$3)"),"#N/A") -> #N/A | AE22: =IFERROR(__xludf.DUMMYFUNCTION("GOOGLEFINANCE($A22,AE$3)"),"#N/A") -> #N/A
B23: =IFERROR(__xludf.DUMMYFUNCTION("GOOGLEFINANCE(A23,""name"")"),"#N/A") -> #N/A | D23: =IFERROR(__xludf.DUMMYFUNCTION("GOOGLEFINANCE(A23)"),"#N/A") -> #N/A | F23: =IFERROR(__xludf.DUMMYFUNCTION("IF(M23=""USD"",E23/GOOGLEFINANCE(""CURRENCY:GBPUSD""),E23)"),"#N/A") -> #N/A | H23: =IFERROR(__xludf.DUMMYFUNCTION("if(isblank(A23)=TRUE,0,if(M23=""GBX"",E23*G23/100,IF(M23=""EUR"",E23*G23/GOOGLEFINANCE(""CURRENCY:GBPEUR""),E23*G23/GOOGLEFINANCE(""CURRENCY:GBPUSD""))))"),0.0) -> 0 | I23: =IFERROR(__xludf.DUMMYFUNCTION("if(isblank(A23)=TRUE,0,if(M23=""GBX"",D23*G23/100,IF(M23=""EUR"",D23*G23/GOOGLEFINANCE(""CURRENCY:GBPEUR""),D23*G23/GOOGLEFINANCE(""CURRENCY:GBPUSD""))))"),0.0) -> 0 | J23: =H23/$B$1 -> 0 | K23: =I23/H23-1 -> #DIV/0! | L23: =IFERROR(__xludf.DUMMYFUNCTION("SPARKLINE(GoogleFinance(A23, ""price"", TODAY()-30, TODAY()),{""color"",""blue"";""linewidth"",2}) "),"#N/A") -> #N/A | M23: =IFERROR(__xludf.DUMMYFUNCTION("GOOGLEFINANCE(A23,""currency"")"),"#N/A") -> #N/A | N23: =round(D23/AE23-1,4) -> #N/A | O23: =IFERROR(__xludf.DUMMYFUNCTION("GOOGLEFINANCE(A23,""Change"")"),"#N/A") -> #N/A | P23: =IFERROR(__xludf.DUMMYFUNCTION("GOOGLEFINANCE(A23,""High"")"),"#N/A") -> #N/A | Q23: =IFERROR(__xludf.DUMMYFUNCTION("GOOGLEFINANCE(A23,""low"")"),"#N/A") -> #N/A | R23: =IFERROR(__xludf.DUMMYFUNCTION("abs(P23-Q23)/GOOGLEFINANCE(A23,""closeyest"")"),"#N/A") -> #N/A | S23: =D23/Y23-1 -> #N/A | W23: =IF(ISERROR(if(or(AND(Q23<=T23,T23<=P23),AND(Q23<=U23, U23<=P23)),"TRADE ALERT","")),"DATA UNAVAILABLE",if(or(AND(Q23<=T23,T23<=P23),T23>P23,AND(Q23<=U23, U23<=P23)),"TRADE ALERT"&" - Price level hit for "&A23&" currently at "&D23&" "&B23,"")) -> DATA UNAVAILABLE | X23: =IFERROR(__xludf.DUMMYFUNCTION("GOOGLEFINANCE($A23,X$3)"),"#N/A") -> #N/A | Y23: =IFERROR(__xludf.DUMMYFUNCTION("GOOGLEFINANCE($A23,Y$3)"),"#N/A") -> #N/A | Z23: =IFERROR(__xludf.DUMMYFUNCTION("GOOGLEFINANCE($A23,Z$3)"),"#N/A") -> #N/A | AA23: =IFERROR(__xludf.DUMMYFUNCTION("GOOGLEFINANCE($A23,AA$3)"),"#N/A") -> #N/A | AB23: =IFERROR(__xludf.DUMMYFUNCTION("GOOGLEFINANCE($A23,AB$3)"),"#N/A") -> #N/A | AC23: =IFERROR(__xludf.DUMMYFUNCTION("GOOGLEFINANCE($A23,AC$3)"),"#N/A") -> #N/A | AD23: =IFERROR(__xludf.DUMMYFUNCTION("GOOGLEFINANCE($A23,AD$3)"),"#N/A") -> #N/A | AE23: =IFERROR(__xludf.DUMMYFUNCTION("GOOGLEFINANCE($A23,AE$3)"),"#N/A") -> #N/A
B24: =IFERROR(__xludf.DUMMYFUNCTION("GOOGLEFINANCE(A24,""name"")"),"#N/A") -> #N/A | D24: =IFERROR(__xludf.DUMMYFUNCTION("GOOGLEFINANCE(A24)"),"#N/A") -> #N/A | F24: =IFERROR(__xludf.DUMMYFUNCTION("IF(M24=""USD"",E24/GOOGLEFINANCE(""CURRENCY:GBPUSD""),E24)"),"#N/A") -> #N/A | H24: =IFERROR(__xludf.DUMMYFUNCTION("if(isblank(A24)=TRUE,0,if(M24=""GBX"",E24*G24/100,IF(M24=""EUR"",E24*G24/GOOGLEFINANCE(""CURRENCY:GBPEUR""),E24*G24/GOOGLEFINANCE(""CURRENCY:GBPUSD""))))"),0.0) -> 0 | I24: =IFERROR(__xludf.DUMMYFUNCTION("if(isblank(A24)=TRUE,0,if(M24=""GBX"",D24*G24/100,IF(M24=""EUR"",D24*G24/GOOGLEFINANCE(""CURRENCY:GBPEUR""),D24*G24/GOOGLEFINANCE(""CURRENCY:GBPUSD""))))"),0.0) -> 0 | J24: =H24/$B$1 -> 0 | K24: =I24/H24-1 -> #DIV/0! | L24: =IFERROR(__xludf.DUMMYFUNCTION("SPARKLINE(GoogleFinance(A24, ""price"", TODAY()-30, TODAY()),{""color"",""blue"";""linewidth"",2}) "),"#N/A") -> #N/A | M24: =IFERROR(__xludf.DUMMYFUNCTION("GOOGLEFINANCE(A24,""currency"")"),"#N/A") -> #N/A | N24: =round(D24/AE24-1,4) -> #N/A | O24: =IFERROR(__xludf.DUMMYFUNCTION("GOOGLEFINANCE(A24,""Change"")"),"#N/A") -> #N/A | P24: =IFERROR(__xludf.DUMMYFUNCTION("GOOGLEFINANCE(A24,""High"")"),"#N/A") -> #N/A | Q24: =IFERROR(__xludf.DUMMYFUNCTION("GOOGLEFINANCE(A24,""low"")"),"#N/A") -> #N/A | R24: =IFERROR(__xludf.DUMMYFUNCTION("abs(P24-Q24)/GOOGLEFINANCE(A24,""closeyest"")"),"#N/A") -> #N/A | S24: =D24/Y24-1 -> #N/A | W24: =IF(ISERROR(if(or(AND(Q24<=T24,T24<=P24),AND(Q24<=U24, U24<=P24)),"TRADE ALERT","")),"DATA UNAVAILABLE",if(or(AND(Q24<=T24,T24<=P24),T24>P24,AND(Q24<=U24, U24<=P24)),"TRADE ALERT"&" - Price level hit for "&A24&" currently at "&D24&" "&B24,"")) -> DATA UNAVAILABLE | X24: =IFERROR(__xludf.DUMMYFUNCTION("GOOGLEFINANCE($A24,X$3)"),"#N/A") -> #N/A | Y24: =IFERROR(__xludf.DUMMYFUNCTION("GOOGLEFINANCE($A24,Y$3)"),"#N/A") -> #N/A | Z24: =IFERROR(__xludf.DUMMYFUNCTION("GOOGLEFINANCE($A24,Z$3)"),"#N/A") -> #N/A | AA24: =IFERROR(__xludf.DUMMYFUNCTION("GOOGLEFINANCE($A24,AA$3)"),"#N/A") -> #N/A | AB24: =IFERROR(__xludf.DUMMYFUNCTION("GOOGLEFINANCE($A24,AB$3)"),"#N/A") -> #N/A | AC24: =IFERROR(__xludf.DUMMYFUNCTION("GOOGLEFINANCE($A24,AC$3)"),"#N/A") -> #N/A | AD24: =IFERROR(__xludf.DUMMYFUNCTION("GOOGLEFINANCE($A24,AD$3)"),"#N/A") -> #N/A | AE24: =IFERROR(__xludf.DUMMYFUNCTION("GOOGLEFINANCE($A24,AE$3)"),"#N/A") -> #N/A
B25: =IFERROR(__xludf.DUMMYFUNCTION("GOOGLEFINANCE(A25,""name"")"),"#N/A") -> #N/A | D25: =IFERROR(__xludf.DUMMYFUNCTION("GOOGLEFINANCE(A25)"),"#N/A") -> #N/A | F25: =IFERROR(__xludf.DUMMYFUNCTION("IF(M25=""USD"",E25/GOOGLEFINANCE(""CURRENCY:GBPUSD""),E25)"),"#N/A") -> #N/A | H25: =IFERROR(__xludf.DUMMYFUNCTION("if(isblank(A25)=TRUE,0,if(M25=""GBX"",E25*G25/100,IF(M25=""EUR"",E25*G25/GOOGLEFINANCE(""CURRENCY:GBPEUR""),E25*G25/GOOGLEFINANCE(""CURRENCY:GBPUSD""))))"),0.0) -> 0 | I25: =IFERROR(__xludf.DUMMYFUNCTION("if(isblank(A25)=TRUE,0,if(M25=""GBX"",D25*G25/100,IF(M25=""EUR"",D25*G25/GOOGLEFINANCE(""CURRENCY:GBPEUR""),D25*G25/GOOGLEFINANCE(""CURRENCY:GBPUSD""))))"),0.0) -> 0 | J25: =H25/$B$1 -> 0 | K25: =I25/H25-1 -> #DIV/0! | L25: =IFERROR(__xludf.DUMMYFUNCTION("SPARKLINE(GoogleFinance(A25, ""price"", TODAY()-30, TODAY()),{""color"",""blue"";""linewidth"",2}) "),"#N/A") -> #N/A | M25: =IFERROR(__xludf.DUMMYFUNCTION("GOOGLEFINANCE(A25,""currency"")"),"#N/A") -> #N/A | N25: =round(D25/AE25-1,4) -> #N/A | O25: =IFERROR(__xludf.DUMMYFUNCTION("GOOGLEFINANCE(A25,""Change"")"),"#N/A") -> #N/A | P25: =IFERROR(__xludf.DUMMYFUNCTION("GOOGLEFINANCE(A25,""High"")"),"#N/A") -> #N/A | Q25: =IFERROR(__xludf.DUMMYFUNCTION("GOOGLEFINANCE(A25,""low"")"),"#N/A") -> #N/A | R25: =IFERROR(__xludf.DUMMYFUNCTION("abs(P25-Q25)/GOOGLEFINANCE(A25,""closeyest"")"),"#N/A") -> #N/A | S25: =D25/Y25-1 -> #N/A | W25: =IF(ISERROR(if(or(AND(Q25<=T25,T25<=P25),AND(Q25<=U25, U25<=P25)),"TRADE ALERT","")),"DATA UNAVAILABLE",if(or(AND(Q25<=T25,T25<=P25),T25>P25,AND(Q25<=U25, U25<=P25)),"TRADE ALERT"&" - Price level hit for "&A25&" currently at "&D25&" "&B25,"")) -> DATA UNAVAILABLE | X25: =IFERROR(__xludf.DUMMYFUNCTION("GOOGLEFINANCE($A25,X$3)"),"#N/A") -> #N/A | Y25: =IFERROR(__xludf.DUMMYFUNCTION("GOOGLEFINANCE($A25,Y$3)"),"#N/A") -> #N/A | Z25: =IFERROR(__xludf.DUMMYFUNCTION("GOOGLEFINANCE($A25,Z$3)"),"#N/A") -> #N/A | AA25: =IFERROR(__xludf.DUMMYFUNCTION("GOOGLEFINANCE($A25,AA$3)"),"#N/A") -> #N/A | AB25: =IFERROR(__xludf.DUMMYFUNCTION("GOOGLEFINANCE($A25,AB$3)"),"#N/A") -> #N/A | AC25: =IFERROR(__xludf.DUMMYFUNCTION("GOOGLEFINANCE($A25,AC$3)"),"#N/A") -> #N/A | AD25: =IFERROR(__xludf.DUMMYFUNCTION("GOOGLEFINANCE($A25,AD$3)"),"#N/A") -> #N/A | AE25: =IFERROR(__xludf.DUMMYFUNCTION("GOOGLEFINANCE($A25,AE$3)"),"#N/A") -> #N/A
B26: =IFERROR(__xludf.DUMMYFUNCTION("GOOGLEFINANCE(A26,""name"")"),"#N/A") -> #N/A | D26: =IFERROR(__xludf.DUMMYFUNCTION("GOOGLEFINANCE(A26)"),"#N/A") -> #N/A | F26: =IFERROR(__xludf.DUMMYFUNCTION("IF(M26=""USD"",E26/GOOGLEFINANCE(""CURRENCY:GBPUSD""),E26)"),"#N/A") -> #N/A | H26: =IFERROR(__xludf.DUMMYFUNCTION("if(isblank(A26)=TRUE,0,if(M26=""GBX"",E26*G26/100,IF(M26=""EUR"",E26*G26/GOOGLEFINANCE(""CURRENCY:GBPEUR""),E26*G26/GOOGLEFINANCE(""CURRENCY:GBPUSD""))))"),0.0) -> 0 | I26: =IFERROR(__xludf.DUMMYFUNCTION("if(isblank(A26)=TRUE,0,if(M26=""GBX"",D26*G26/100,IF(M26=""EUR"",D26*G26/GOOGLEFINANCE(""CURRENCY:GBPEUR""),D26*G26/GOOGLEFINANCE(""CURRENCY:GBPUSD""))))"),0.0) -> 0 | J26: =H26/$B$1 -> 0 | K26: =I26/H26-1 -> #DIV/0! | L26: =IFERROR(__xludf.DUMMYFUNCTION("SPARKLINE(GoogleFinance(A26, ""price"", TODAY()-30, TODAY()),{""color"",""blue"";""linewidth"",2}) "),"#N/A") -> #N/A | M26: =IFERROR(__xludf.DUMMYFUNCTION("GOOGLEFINANCE(A26,""currency"")"),"#N/A") -> #N/A | N26: =round(D26/AE26-1,4) -> #N/A | O26: =IFERROR(__xludf.DUMMYFUNCTION("GOOGLEFINANCE(A26,""Change"")"),"#N/A") -> #N/A | P26: =IFERROR(__xludf.DUMMYFUNCTION("GOOGLEFINANCE(A26,""High"")"),"#N/A") -> #N/A | Q26: =IFERROR(__xludf.DUMMYFUNCTION("GOOGLEFINANCE(A26,""low"")"),"#N/A") -> #N/A | R26: =IFERROR(__xludf.DUMMYFUNCTION("abs(P26-Q26)/GOOGLEFINANCE(A26,""closeyest"")"),"#N/A") -> #N/A | S26: =D26/Y26-1 -> #N/A | W26: =IF(ISERROR(if(or(AND(Q26<=T26,T26<=P26),AND(Q26<=U26, U26<=P26)),"TRADE ALERT","")),"DATA UNAVAILABLE",if(or(AND(Q26<=T26,T26<=P26),T26>P26,AND(Q26<=U26, U26<=P26)),"TRADE ALERT"&" - Price level hit for "&A26&" currently at "&D26&" "&B26,"")) -> DATA UNAVAILABLE | X26: =IFERROR(__xludf.DUMMYFUNCTION("GOOGLEFINANCE($A26,X$3)"),"#N/A") -> #N/A | Y26: =IFERROR(__xludf.DUMMYFUNCTION("GOOGLEFINANCE($A26,Y$3)"),"#N/A") -> #N/A | Z26: =IFERROR(__xludf.DUMMYFUNCTION("GOOGLEFINANCE($A26,Z$3)"),"#N/A") -> #N/A | AA26: =IFERROR(__xludf.DUMMYFUNCTION("GOOGLEFINANCE($A26,AA$3)"),"#N/A") -> #N/A | AB26: =IFERROR(__xludf.DUMMYFUNCTION("GOOGLEFINANCE($A26,AB$3)"),"#N/A") -> #N/A | AC26: =IFERROR(__xludf.DUMMYFUNCTION("GOOGLEFINANCE($A26,AC$3)"),"#N/A") -> #N/A | AD26: =IFERROR(__xludf.DUMMYFUNCTION("GOOGLEFINANCE($A26,AD$3)"),"#N/A") -> #N/A | AE26: =IFERROR(__xludf.DUMMYFUNCTION("GOOGLEFINANCE($A26,AE$3)"),"#N/A") -> #N/A
B27: =IFERROR(__xludf.DUMMYFUNCTION("GOOGLEFINANCE(A27,""name"")"),"#N/A") -> #N/A | D27: =IFERROR(__xludf.DUMMYFUNCTION("GOOGLEFINANCE(A27)"),"#N/A") -> #N/A | F27: =IFERROR(__xludf.DUMMYFUNCTION("IF(M27=""USD"",E27/GOOGLEFINANCE(""CURRENCY:GBPUSD""),E27)"),"#N/A") -> #N/A | H27: =IFERROR(__xludf.DUMMYFUNCTION("if(isblank(A27)=TRUE,0,if(M27=""GBX"",E27*G27/100,IF(M27=""EUR"",E27*G27/GOOGLEFINANCE(""CURRENCY:GBPEUR""),E27*G27/GOOGLEFINANCE(""CURRENCY:GBPUSD""))))"),0.0) -> 0 | I27: =IFERROR(__xludf.DUMMYFUNCTION("if(isblank(A27)=TRUE,0,if(M27=""GBX"",D27*G27/100,IF(M27=""EUR"",D27*G27/GOOGLEFINANCE(""CURRENCY:GBPEUR""),D27*G27/GOOGLEFINANCE(""CURRENCY:GBPUSD""))))"),0.0) -> 0 | J27: =H27/$B$1 -> 0 | K27: =I27/H27-1 -> #DIV/0! | L27: =IFERROR(__xludf.DUMMYFUNCTION("SPARKLINE(GoogleFinance(A27, ""price"", TODAY()-30, TODAY()),{""color"",""blue"";""linewidth"",2}) "),"#N/A") -> #N/A | M27: =IFERROR(__xludf.DUMMYFUNCTION("GOOGLEFINANCE(A27,""currency"")"),"#N/A") -> #N/A | N27: =round(D27/AE27-1,4) -> #N/A | O27: =IFERROR(__xludf.DUMMYFUNCTION("GOOGLEFINANCE(A27,""Change"")"),"#N/A") -> #N/A | P27: =IFERROR(__xludf.DUMMYFUNCTION("GOOGLEFINANCE(A27,""High"")"),"#N/A") -> #N/A | Q27: =IFERROR(__xludf.DUMMYFUNCTION("GOOGLEFINANCE(A27,""low"")"),"#N/A") -> #N/A | R27: =IFERROR(__xludf.DUMMYFUNCTION("abs(P27-Q27)/GOOGLEFINANCE(A27,""closeyest"")"),"#N/A") -> #N/A | S27: =D27/Y27-1 -> #N/A | W27: =IF(ISERROR(if(or(AND(Q27<=T27,T27<=P27),AND(Q27<=U27, U27<=P27)),"TRADE ALERT","")),"DATA UNAVAILABLE",if(or(AND(Q27<=T27,T27<=P27),T27>P27,AND(Q27<=U27, U27<=P27)),"TRADE ALERT"&" - Price level hit for "&A27&" currently at "&D27&" "&B27,"")) -> DATA UNAVAILABLE | X27: =IFERROR(__xludf.DUMMYFUNCTION("GOOGLEFINANCE($A27,X$3)"),"#N/A") -> #N/A | Y27: =IFERROR(__xludf.DUMMYFUNCTION("GOOGLEFINANCE($A27,Y$3)"),"#N/A") -> #N/A | Z27: =IFERROR(__xludf.DUMMYFUNCTION("GOOGLEFINANCE($A27,Z$3)"),"#N/A") -> #N/A | AA27: =IFERROR(__xludf.DUMMYFUNCTION("GOOGLEFINANCE($A27,AA$3)"),"#N/A") -> #N/A | AB27: =IFERROR(__xludf.DUMMYFUNCTION("GOOGLEFINANCE($A27,AB$3)"),"#N/A") -> #N/A | AC27: =IFERROR(__xludf.DUMMYFUNCTION("GOOGLEFINANCE($A27,AC$3)"),"#N/A") -> #N/A | AD27: =IFERROR(__xludf.DUMMYFUNCTION("GOOGLEFINANCE($A27,AD$3)"),"#N/A") -> #N/A | AE27: =IFERROR(__xludf.DUMMYFUNCTION("GOOGLEFINANCE($A27,AE$3)"),"#N/A") -> #N/A
B28: =IFERROR(__xludf.DUMMYFUNCTION("GOOGLEFINANCE(A28,""name"")"),"#N/A") -> #N/A | D28: =IFERROR(__xludf.DUMMYFUNCTION("GOOGLEFINANCE(A28)"),"#N/A") -> #N/A | F28: =IFERROR(__xludf.DUMMYFUNCTION("IF(M28=""USD"",E28/GOOGLEFINANCE(""CURRENCY:GBPUSD""),E28)"),"#N/A") -> #N/A | H28: =IFERROR(__xludf.DUMMYFUNCTION("if(isblank(A28)=TRUE,0,if(M28=""GBX"",E28*G28/100,IF(M28=""EUR"",E28*G28/GOOGLEFINANCE(""CURRENCY:GBPEUR""),E28*G28/GOOGLEFINANCE(""CURRENCY:GBPUSD""))))"),0.0) -> 0 | I28: =IFERROR(__xludf.DUMMYFUNCTION("if(isblank(A28)=TRUE,0,if(M28=""GBX"",D28*G28/100,IF(M28=""EUR"",D28*G28/GOOGLEFINANCE(""CURRENCY:GBPEUR""),D28*G28/GOOGLEFINANCE(""CURRENCY:GBPUSD""))))"),0.0) -> 0 | J28: =H28/$B$1 -> 0 | K28: =I28/H28-1 -> #DIV/0! | L28: =IFERROR(__xludf.DUMMYFUNCTION("SPARKLINE(GoogleFinance(A28, ""price"", TODAY()-30, TODAY()),{""color"",""blue"";""linewidth"",2}) "),"#N/A") -> #N/A | M28: =IFERROR(__xludf.DUMMYFUNCTION("GOOGLEFINANCE(A28,""currency"")"),"#N/A") -> #N/A | N28: =round(D28/AE28-1,4) -> #N/A | O28: =IFERROR(__xludf.DUMMYFUNCTION("GOOGLEFINANCE(A28,""Change"")"),"#N/A") -> #N/A | P28: =IFERROR(__xludf.DUMMYFUNCTION("GOOGLEFINANCE(A28,""High"")"),"#N/A") -> #N/A | Q28: =IFERROR(__xludf.DUMMYFUNCTION("GOOGLEFINANCE(A28,""low"")"),"#N/A") -> #N/A | R28: =IFERROR(__xludf.DUMMYFUNCTION("abs(P28-Q28)/GOOGLEFINANCE(A28,""closeyest"")"),"#N/A") -> #N/A | S28: =D28/Y28-1 -> #N/A | W28: =IF(ISERROR(if(or(AND(Q28<=T28,T28<=P28),AND(Q28<=U28, U28<=P28)),"TRADE ALERT","")),"DATA UNAVAILABLE",if(or(AND(Q28<=T28,T28<=P28),T28>P28,AND(Q28<=U28, U28<=P28)),"TRADE ALERT"&" - Price level hit for "&A28&" currently at "&D28&" "&B28,"")) -> DATA UNAVAILABLE | X28: =IFERROR(__xludf.DUMMYFUNCTION("GOOGLEFINANCE($A28,X$3)"),"#N/A") -> #N/A | Y28: =IFERROR(__xludf.DUMMYFUNCTION("GOOGLEFINANCE($A28,Y$3)"),"#N/A") -> #N/A | Z28: =IFERROR(__xludf.DUMMYFUNCTION("GOOGLEFINANCE($A28,Z$3)"),"#N/A") -> #N/A | AA28: =IFERROR(__xludf.DUMMYFUNCTION("GOOGLEFINANCE($A28,AA$3)"),"#N/A") -> #N/A | AB28: =IFERROR(__xludf.DUMMYFUNCTION("GOOGLEFINANCE($A28,AB$3)"),"#N/A") -> #N/A | AC28: =IFERROR(__xludf.DUMMYFUNCTION("GOOGLEFINANCE($A28,AC$3)"),"#N/A") -> #N/A | AD28: =IFERROR(__xludf.DUMMYFUNCTION("GOOGLEFINANCE($A28,AD$3)"),"#N/A") -> #N/A | AE28: =IFERROR(__xludf.DUMMYFUNCTION("GOOGLEFINANCE($A28,AE$3)"),"#N/A") -> #N/A
B29: =IFERROR(__xludf.DUMMYFUNCTION("GOOGLEFINANCE(A29,""name"")"),"#N/A") -> #N/A | D29: =IFERROR(__xludf.DUMMYFUNCTION("GOOGLEFINANCE(A29)"),"#N/A") -> #N/A | F29: =IFERROR(__xludf.DUMMYFUNCTION("IF(M29=""USD"",E29/GOOGLEFINANCE(""CURRENCY:GBPUSD""),E29)"),"#N/A") -> #N/A | H29: =IFERROR(__xludf.DUMMYFUNCTION("if(isblank(A29)=TRUE,0,if(M29=""GBX"",E29*G29/100,IF(M29=""EUR"",E29*G29/GOOGLEFINANCE(""CURRENCY:GBPEUR""),E29*G29/GOOGLEFINANCE(""CURRENCY:GBPUSD""))))"),0.0) -> 0 | I29: =IFERROR(__xludf.DUMMYFUNCTION("if(isblank(A29)=TRUE,0,if(M29=""GBX"",D29*G29/100,IF(M29=""EUR"",D29*G29/GOOGLEFINANCE(""CURRENCY:GBPEUR""),D29*G29/GOOGLEFINANCE(""CURRENCY:GBPUSD""))))"),0.0) -> 0 | J29: =H29/$B$1 -> 0 | K29: =I29/H29-1 -> #DIV/0! | L29: =IFERROR(__xludf.DUMMYFUNCTION("SPARKLINE(GoogleFinance(A29, ""price"", TODAY()-30, TODAY()),{""color"",""blue"";""linewidth"",2}) "),"#N/A") -> #N/A | M29: =IFERROR(__xludf.DUMMYFUNCTION("GOOGLEFINANCE(A29,""currency"")"),"#N/A") -> #N/A | N29: =round(D29/AE29-1,4) -> #N/A | O29: =IFERROR(__xludf.DUMMYFUNCTION("GOOGLEFINANCE(A29,""Change"")"),"#N/A") -> #N/A | P29: =IFERROR(__xludf.DUMMYFUNCTION("GOOGLEFINANCE(A29,""High"")"),"#N/A") -> #N/A | Q29: =IFERROR(__xludf.DUMMYFUNCTION("GOOGLEFINANCE(A29,""low"")"),"#N/A") -> #N/A | R29: =IFERROR(__xludf.DUMMYFUNCTION("abs(P29-Q29)/GOOGLEFINANCE(A29,""closeyest"")"),"#N/A") -> #N/A | S29: =D29/Y29-1 -> #N/A | W29: =IF(ISERROR(if(or(AND(Q29<=T29,T29<=P29),AND(Q29<=U29, U29<=P29)),"TRADE ALERT","")),"DATA UNAVAILABLE",if(or(AND(Q29<=T29,T29<=P29),T29>P29,AND(Q29<=U29, U29<=P29)),"TRADE ALERT"&" - Price level hit for "&A29&" currently at "&D29&" "&B29,"")) -> DATA UNAVAILABLE | X29: =IFERROR(__xludf.DUMMYFUNCTION("GOOGLEFINANCE($A29,X$3)"),"#N/A") -> #N/A | Y29: =IFERROR(__xludf.DUMMYFUNCTION("GOOGLEFINANCE($A29,Y$3)"),"#N/A") -> #N/A | Z29: =IFERROR(__xludf.DUMMYFUNCTION("GOOGLEFINANCE($A29,Z$3)"),"#N/A") -> #N/A | AA29: =IFERROR(__xludf.DUMMYFUNCTION("GOOGLEFINANCE($A29,AA$3)"),"#N/A") -> #N/A | AB29: =IFERROR(__xludf.DUMMYFUNCTION("GOOGLEFINANCE($A29,AB$3)"),"#N/A") -> #N/A | AC29: =IFERROR(__xludf.DUMMYFUNCTION("GOOGLEFINANCE($A29,AC$3)"),"#N/A") -> #N/A | AD29: =IFERROR(__xludf.DUMMYFUNCTION("GOOGLEFINANCE($A29,AD$3)"),"#N/A") -> #N/A | AE29: =IFERROR(__xludf.DUMMYFUNCTION("GOOGLEFINANCE($A29,AE$3)"),"#N/A") -> #N/A
B30: =IFERROR(__xludf.DUMMYFUNCTION("GOOGLEFINANCE(A30,""name"")"),"#N/A") -> #N/A | D30: =IFERROR(__xludf.DUMMYFUNCTION("GOOGLEFINANCE(A30)"),"#N/A") -> #N/A | F30: =IFERROR(__xludf.DUMMYFUNCTION("IF(M30=""USD"",E30/GOOGLEFINANCE(""CURRENCY:GBPUSD""),E30)"),"#N/A") -> #N/A | H30: =IFERROR(__xludf.DUMMYFUNCTION("if(isblank(A30)=TRUE,0,if(M30=""GBX"",E30*G30/100,IF(M30=""EUR"",E30*G30/GOOGLEFINANCE(""CURRENCY:GBPEUR""),E30*G30/GOOGLEFINANCE(""CURRENCY:GBPUSD""))))"),0.0) -> 0 | I30: =IFERROR(__xludf.DUMMYFUNCTION("if(isblank(A30)=TRUE,0,if(M30=""GBX"",D30*G30/100,IF(M30=""EUR"",D30*G30/GOOGLEFINANCE(""CURRENCY:GBPEUR""),D30*G30/GOOGLEFINANCE(""CURRENCY:GBPUSD""))))"),0.0) -> 0 | J30: =H30/$B$1 -> 0 | K30: =I30/H30-1 -> #DIV/0! | L30: =IFERROR(__xludf.DUMMYFUNCTION("SPARKLINE(GoogleFinance(A30, ""price"", TODAY()-30, TODAY()),{""color"",""blue"";""linewidth"",2}) "),"#N/A") -> #N/A | M30: =IFERROR(__xludf.DUMMYFUNCTION("GOOGLEFINANCE(A30,""currency"")"),"#N/A") -> #N/A | N30: =round(D30/AE30-1,4) -> #N/A | O30: =IFERROR(__xludf.DUMMYFUNCTION("GOOGLEFINANCE(A30,""Change"")"),"#N/A") -> #N/A | P30: =IFERROR(__xludf.DUMMYFUNCTION("GOOGLEFINANCE(A30,""High"")"),"#N/A") -> #N/A | Q30: =IFERROR(__xludf.DUMMYFUNCTION("GOOGLEFINANCE(A30,""low"")"),"#N/A") -> #N/A | R30: =IFERROR(__xludf.DUMMYFUNCTION("abs(P30-Q30)/GOOGLEFINANCE(A30,""closeyest"")"),"#N/A") -> #N/A | S30: =D30/Y30-1 -> #N/A | W30: =IF(ISERROR(if(or(AND(Q30<=T30,T30<=P30),AND(Q30<=U30, U30<=P30)),"TRADE ALERT","")),"DATA UNAVAILABLE",if(or(AND(Q30<=T30,T30<=P30),T30>P30,AND(Q30<=U30, U30<=P30)),"TRADE ALERT"&" - Price level hit for "&A30&" currently at "&D30&" "&B30,"")) -> DATA UNAVAILABLE | X30: =IFERROR(__xludf.DUMMYFUNCTION("GOOGLEFINANCE($A30,X$3)"),"#N/A") -> #N/A | Y30: =IFERROR(__xludf.DUMMYFUNCTION("GOOGLEFINANCE($A30,Y$3)"),"#N/A") -> #N/A | Z30: =IFERROR(__xludf.DUMMYFUNCTION("GOOGLEFINANCE($A30,Z$3)"),"#N/A") -> #N/A | AA30: =IFERROR(__xludf.DUMMYFUNCTION("GOOGLEFINANCE($A30,AA$3)"),"#N/A") -> #N/A | AB30: =IFERROR(__xludf.DUMMYFUNCTION("GOOGLEFINANCE($A30,AB$3)"),"#N/A") -> #N/A | AC30: =IFERROR(__xludf.DUMMYFUNCTION("GOOGLEFINANCE($A30,AC$3)"),"#N/A") -> #N/A | AD30: =IFERROR(__xludf.DUMMYFUNCTION("GOOGLEFINANCE($A30,AD$3)"),"#N/A") -> #N/A | AE30: =IFERROR(__xludf.DUMMYFUNCTION("GOOGLEFINANCE($A30,AE$3)"),"#N/A") -> #N/A
B31: =IFERROR(__xludf.DUMMYFUNCTION("GOOGLEFINANCE(A31,""name"")"),"#N/A") -> #N/A | D31: =IFERROR(__xludf.DUMMYFUNCTION("GOOGLEFINANCE(A31)"),"#N/A") -> #N/A | F31: =IFERROR(__xludf.DUMMYFUNCTION("IF(M31=""USD"",E31/GOOGLEFINANCE(""CURRENCY:GBPUSD""),E31)"),"#N/A") -> #N/A | H31: =IFERROR(__xludf.DUMMYFUNCTION("if(isblank(A31)=TRUE,0,if(M31=""GBX"",E31*G31/100,IF(M31=""EUR"",E31*G31/GOOGLEFINANCE(""CURRENCY:GBPEUR""),E31*G31/GOOGLEFINANCE(""CURRENCY:GBPUSD""))))"),0.0) -> 0 | I31: =IFERROR(__xludf.DUMMYFUNCTION("if(isblank(A31)=TRUE,0,if(M31=""GBX"",D31*G31/100,IF(M31=""EUR"",D31*G31/GOOGLEFINANCE(""CURRENCY:GBPEUR""),D31*G31/GOOGLEFINANCE(""CURRENCY:GBPUSD""))))"),0.0) -> 0 | J31: =H31/$B$1 -> 0 | K31: =I31/H31-1 -> #DIV/0! | L31: =IFERROR(__xludf.DUMMYFUNCTION("SPARKLINE(GoogleFinance(A31, ""price"", TODAY()-30, TODAY()),{""color"",""blue"";""linewidth"",2}) "),"#N/A") -> #N/A | M31: =IFERROR(__xludf.DUMMYFUNCTION("GOOGLEFINANCE(A31,""currency"")"),"#N/A") -> #N/A | N31: =round(D31/AE31-1,4) -> #N/A | O31: =IFERROR(__xludf.DUMMYFUNCTION("GOOGLEFINANCE(A31,""Change"")"),"#N/A") -> #N/A | P31: =IFERROR(__xludf.DUMMYFUNCTION("GOOGLEFINANCE(A31,""High"")"),"#N/A") -> #N/A | Q31: =IFERROR(__xludf.DUMMYFUNCTION("GOOGLEFINANCE(A31,""low"")"),"#N/A") -> #N/A | R31: =IFERROR(__xludf.DUMMYFUNCTION("abs(P31-Q31)/GOOGLEFINANCE(A31,""closeyest"")"),"#N/A") -> #N/A | S31: =D31/Y31-1 -> #N/A | W31: =IF(ISERROR(if(or(AND(Q31<=T31,T31<=P31),AND(Q31<=U31, U31<=P31)),"TRADE ALERT","")),"DATA UNAVAILABLE",if(or(AND(Q31<=T31,T31<=P31),T31>P31,AND(Q31<=U31, U31<=P31)),"TRADE ALERT"&" - Price level hit for "&A31&" currently at "&D31&" "&B31,"")) -> DATA UNAVAILABLE | X31: =IFERROR(__xludf.DUMMYFUNCTION("GOOGLEFINANCE($A31,X$3)"),"#N/A") -> #N/A | Y31: =IFERROR(__xludf.DUMMYFUNCTION("GOOGLEFINANCE($A31,Y$3)"),"#N/A") -> #N/A | Z31: =IFERROR(__xludf.DUMMYFUNCTION("GOOGLEFINANCE($A31,Z$3)"),"#N/A") -> #N/A | AA31: =IFERROR(__xludf.DUMMYFUNCTION("GOOGLEFINANCE($A31,AA$3)"),"#N/A") -> #N/A | AB31: =IFERROR(__xludf.DUMMYFUNCTION("GOOGLEFINANCE($A31,AB$3)"),"#N/A") -> #N/A | AC31: =IFERROR(__xludf.DUMMYFUNCTION("GOOGLEFINANCE($A31,AC$3)"),"#N/A") -> #N/A | AD31: =IFERROR(__xludf.DUMMYFUNCTION("GOOGLEFINANCE($A31,AD$3)"),"#N/A") -> #N/A | AE31: =IFERROR(__xludf.DUMMYFUNCTION("GOOGLEFINANCE($A31,AE$3)"),"#N/A") -> #N/A
A32: Watchlist Favourites | C32: Watch Reason
A33: SNAP | B33: =IFERROR(__xludf.DUMMYFUNCTION("GOOGLEFINANCE(A33,""name"")"),"Snap Inc") -> Snap Inc | D33: =IFERROR(__xludf.DUMMYFUNCTION("GOOGLEFINANCE(A33)"),4.75) -> 4.75 | K33: =(D33-E33)/E33 -> #DIV/0! | L33: =IFERROR(__xludf.DUMMYFUNCTION("SPARKLINE(GoogleFinance(A33, ""price"", TODAY()-30, TODAY()),{""color"",""blue"";""linewidth"",2}) "),"") | M33: =IFERROR(__xludf.DUMMYFUNCTION("GOOGLEFINANCE(A33,""currency"")"),"USD") -> USD | N33: =round(D33/AE33-1,4) -> -0.0166 | O33: =IFERROR(__xludf.DUMMYFUNCTION("GOOGLEFINANCE(A33,""Change"")"),-0.09) -> -0.09 | P33: =IFERROR(__xludf.DUMMYFUNCTION("GOOGLEFINANCE(A33,""High"")"),4.87) -> 4.87 | Q33: =IFERROR(__xludf.DUMMYFUNCTION("GOOGLEFINANCE(A33,""low"")"),4.66) -> 4.66 | R33: =IFERROR(__xludf.DUMMYFUNCTION("abs(P33-Q33)/GOOGLEFINANCE(A33,""closeyest"")"),0.04347826086956521) -> 0.043478261 | S33: =D33/Y33-1 -> 0.019313305 | T33: 15 | U33: 50 | W33: =IF(ISERROR(if(or(AND(Q33<=T33,T33<=P33),AND(Q33<=U33, U33<=P33)),"TRADE ALERT","")),"DATA UNAVAILABLE",if(or(AND(Q33<=T33,T33<=P33),T33>P33,AND(Q33<=U33, U33<=P33)),"TRADE ALERT"&" - Price level hit for "&A33&" currently at "&D33&" "&B33,"")) -> TRADE ALERT - Price level hit for SNAP currently at 4.75 Snap Inc | X33: =IFERROR(__xludf.DUMMYFUNCTION("GOOGLEFINANCE($A33,X$3)"),0.83) -> 0.83 | Y33: =IFERROR(__xludf.DUMMYFUNCTION("GOOGLEFINANCE($A33,Y$3)"),4.66) -> 4.66 | Z33: =IFERROR(__xludf.DUMMYFUNCTION("GOOGLEFINANCE($A33,Z$3)"),11.05) -> 11.05 | AA33: =IFERROR(__xludf.DUMMYFUNCTION("GOOGLEFINANCE($A33,AA$3)"),"#N/A") -> #N/A | AB33: =IFERROR(__xludf.DUMMYFUNCTION("GOOGLEFINANCE($A33,AB$3)"),"#N/A") -> #N/A | AC33: =IFERROR(__xludf.DUMMYFUNCTION("GOOGLEFINANCE($A33,AC$3)"),0.0) -> 0 | AD33: =IFERROR(__xludf.DUMMYFUNCTION("GOOGLEFINANCE($A33,AD$3)"),8.014072301E9) -> 8014072301 | AE33: =IFERROR(__xludf.DUMMYFUNCTION("GOOGLEFINANCE($A33,AE$3)"),4.83) -> 4.83
A34: CWBR | B34: =IFERROR(__xludf.DUMMYFUNCTION("GOOGLEFINANCE(A34,""name"")"),"#N/A") -> #N/A | D34: =IFERROR(__xludf.DUMMYFUNCTION("GOOGLEFINANCE(A34)"),"#N/A") -> #N/A | K34: =(D34-E34)/E34 -> #N/A | L34: =IFERROR(__xludf.DUMMYFUNCTION("SPARKLINE(GoogleFinance(A34, ""price"", TODAY()-30, TODAY()),{""color"",""blue"";""linewidth"",2}) "),"#N/A") -> #N/A | M34: =IFERROR(__xludf.DUMMYFUNCTION("GOOGLEFINANCE(A34,""currency"")"),"#N/A") -> #N/A | N34: =round(D34/AE34-1,4) -> #N/A | O34: =IFERROR(__xludf.DUMMYFUNCTION("GOOGLEFINANCE(A34,""Change"")"),"#N/A") -> #N/A | P34: =IFERROR(__xludf.DUMMYFUNCTION("GOOGLEFINANCE(A34,""High"")"),"#N/A") -> #N/A | Q34: =IFERROR(__xludf.DUMMYFUNCTION("GOOGLEFINANCE(A34,""low"")"),"#N/A") -> #N/A | R34: =IFERROR(__xludf.DUMMYFUNCTION("abs(P34-Q34)/GOOGLEFINANCE(A34,""closeyest"")"),"#N/A") -> #N/A | S34: =D34/Y34-1 -> #N/A | T34: 1.5 | W34: =IF(ISERROR(if(or(AND(Q34<=T34,T34<=P34),AND(Q34<=U34, U34<=P34)),"TRADE ALERT","")),"DATA UNAVAILABLE",if(or(AND(Q34<=T34,T34<=P34),T34>P34,AND(Q34<=U34, U34<=P34)),"TRADE ALERT"&" - Price level hit for "&A34&" currently at "&D34&" "&B34,"")) -> DATA UNAVAILABLE | X34: =IFERROR(__xludf.DUMMYFUNCTION("GOOGLEFINANCE($A34,X$3)"),"#N/A") -> #N/A | Y34: =IFERROR(__xludf.DUMMYFUNCTION("GOOGLEFINANCE($A34,Y$3)"),"#N/A") -> #N/A | Z34: =IFERROR(__xludf.DUMMYFUNCTION("GOOGLEFINANCE($A34,Z$3)"),"#N/A") -> #N/A | AA34: =IFERROR(__xludf.DUMMYFUNCTION("GOOGLEFINANCE($A34,AA$3)"),"#N/A") -> #N/A | AB34: =IFERROR(__xludf.DUMMYFUNCTION("GOOGLEFINANCE($A34,AB$3)"),"#N/A") -> #N/A | AC34: =IFERROR(__xludf.DUMMYFUNCTION("GOOGLEFINANCE($A34,AC$3)"),"#N/A") -> #N/A | AD34: =IFERROR(__xludf.DUMMYFUNCTION("GOOGLEFINANCE($A34,AD$3)"),"#N/A") -> #N/A | AE34: =IFERROR(__xludf.DUMMYFUNCTION("GOOGLEFINANCE($A34,AE$3)"),"#N/A") -> #N/A
A35: HZD | B35: =IFERROR(__xludf.DUMMYFUNCTION("GOOGLEFINANCE(A35,""name"")"),"#N/A") -> #N/A | D35: =IFERROR(__xludf.DUMMYFUNCTION("GOOGLEFINANCE(A35)"),"#N/A") -> #N/A | K35: =(D35-E35)/E35 -> #N/A | L35: =IFERROR(__xludf.DUMMYFUNCTION("SPARKLINE(GoogleFinance(A35, ""price"", TODAY()-30, TODAY()),{""color"",""blue"";""linewidth"",2}) "),"#N/A") -> #N/A | M35: =IFERROR(__xludf.DUMMYFUNCTION("GOOGLEFINANCE(A35,""currency"")"),"#N/A") -> #N/A | N35: =round(D35/AE35-1,4) -> #N/A | O35: =IFERROR(__xludf.DUMMYFUNCTION("GOOGLEFINANCE(A35,""Change"")"),"#N/A") -> #N/A | P35: =IFERROR(__xludf.DUMMYFUNCTION("GOOGLEFINANCE(A35,""High"")"),"#N/A") -> #N/A | Q35: =IFERROR(__xludf.DUMMYFUNCTION("GOOGLEFINANCE(A35,""low"")"),"#N/A") -> #N/A | R35: =IFERROR(__xludf.DUMMYFUNCTION("abs(P35-Q35)/GOOGLEFINANCE(A35,""closeyest"")"),"#N/A") -> #N/A | S35: =D35/Y35-1 -> #N/A | T35: 105 | W35: =IF(ISERROR(if(or(AND(Q35<=T35,T35<=P35),AND(Q35<=U35, U35<=P35)),"TRADE ALERT","")),"DATA UNAVAILABLE",if(or(AND(Q35<=T35,T35<=P35),T35>P35,AND(Q35<=U35, U35<=P35)),"TRADE ALERT"&" - Price level hit for "&A35&" currently at "&D35&" "&B35,"")) -> DATA UNAVAILABLE | X35: =IFERROR(__xludf.DUMMYFUNCTION("GOOGLEFINANCE($A35,X$3)"),"#N/A") -> #N/A | Y35: =IFERROR(__xludf.DUMMYFUNCTION("GOOGLEFINANCE($A35,Y$3)"),"#N/A") -> #N/A | Z35: =IFERROR(__xludf.DUMMYFUNCTION("GOOGLEFINANCE($A35,Z$3)"),"#N/A") -> #N/A | AA35: =IFERROR(__xludf.DUMMYFUNCTION("GOOGLEFINANCE($A35,AA$3)"),"#N/A") -> #N/A | AB35: =IFERROR(__xludf.DUMMYFUNCTION("GOOGLEFINANCE($A35,AB$3)"),"#N/A") -> #N/A | AC35: =IFERROR(__xludf.DUMMYFUNCTION("GOOGLEFINANCE($A35,AC$3)"),"#N/A") -> #N/A | AD35: =IFERROR(__xludf.DUMMYFUNCTION("GOOGLEFINANCE($A35,AD$3)"),"#N/A") -> #N/A | AE35: =IFERROR(__xludf.DUMMYFUNCTION("GOOGLEFINANCE($A35,AE$3)"),"#N/A") -> #N/A
A36: MANU | B36: =IFERROR(__xludf.DUMMYFUNCTION("GOOGLEFINANCE(A36,""name"")"),"Manchester United PLC") -> Manchester United PLC | D36: =IFERROR(__xludf.DUMMYFUNCTION("GOOGLEFINANCE(A36)"),17.75) -> 17.75 | K36: =(D36-E36)/E36 -> #DIV/0! | L36: =IFERROR(__xludf.DUMMYFUNCTION("SPARKLINE(GoogleFinance(A36, ""price"", TODAY()-30, TODAY()),{""color"",""blue"";""linewidth"",2}) "),"") | M36: =IFERROR(__xludf.DUMMYFUNCTION("GOOGLEFINANCE(A36,""currency"")"),"USD") -> USD | N36: =round(D36/AE36-1,4) -> 0.0178 | O36: =IFERROR(__xludf.DUMMYFUNCTION("GOOGLEFINANCE(A36,""Change"")"),0.31) -> 0.31 | P36: =IFERROR(__xludf.DUMMYFUNCTION("GOOGLEFINANCE(A36,""High"")"),17.75) -> 17.75 | Q36: =IFERROR(__xludf.DUMMYFUNCTION("GOOGLEFINANCE(A36,""low"")"),17.34) -> 17.34 | R36: =IFERROR(__xludf.DUMMYFUNCTION("abs(P36-Q36)/GOOGLEFINANCE(A36,""closeyest"")"),0.02350917431192661) -> 0.023509174 | S36: =D36/Y36-1 -> 0.47302905 | T36: 15 | W36: =IF(ISERROR(if(or(AND(Q36<=T36,T36<=P36),AND(Q36<=U36, U36<=P36)),"TRADE ALERT","")),"DATA UNAVAILABLE",if(or(AND(Q36<=T36,T36<=P36),T36>P36,AND(Q36<=U36, U36<=P36)),"TRADE ALERT"&" - Price level hit for "&A36&" currently at "&D36&" "&B36,"")) | X36: =IFERROR(__xludf.DUMMYFUNCTION("GOOGLEFINANCE($A36,X$3)"),0.54) -> 0.54 | Y36: =IFERROR(__xludf.DUMMYFUNCTION("GOOGLEFINANCE($A36,Y$3)"),12.05) -> 12.05 | Z36: =IFERROR(__xludf.DUMMYFUNCTION("GOOGLEFINANCE($A36,Z$3)"),19.65) -> 19.65 | AA36: =IFERROR(__xludf.DUMMYFUNCTION("GOOGLEFINANCE($A36,AA$3)"),"#N/A") -> #N/A | AB36: =IFERROR(__xludf.DUMMYFUNCTION("GOOGLEFINANCE($A36,AB$3)"),"#N/A") -> #N/A | AC36: =IFERROR(__xludf.DUMMYFUNCTION("GOOGLEFINANCE($A36,AC$3)"),0.0) -> 0 | AD36: =IFERROR(__xludf.DUMMYFUNCTION("GOOGLEFINANCE($A36,AD$3)"),3.055579075E9) -> 3055579075 | AE36: =IFERROR(__xludf.DUMMYFUNCTION("GOOGLEFINANCE($A36,AE$3)"),17.44) -> 17.44
A37: TIT | B37: =IFERROR(__xludf.DUMMYFUNCTION("GOOGLEFINANCE(A37,""name"")"),"Telecom Italia SpA") -> Telecom Italia SpA | D37: =IFERROR(__xludf.DUMMYFUNCTION("GOOGLEFINANCE(A37)"),0.66) -> 0.66 | K37: =(D37-E37)/E37 -> #DIV/0! | L37: =IFERROR(__xludf.DUMMYFUNCTION("SPARKLINE(GoogleFinance(A37, ""price"", TODAY()-30, TODAY()),{""color"",""blue"";""linewidth"",2}) "),"") | M37: =IFERROR(__xludf.DUMMYFUNCTION("GOOGLEFINANCE(A37,""currency"")"),"EUR") -> EUR | N37: =round(D37/AE37-1,4) -> 0.0313 | O37: =IFERROR(__xludf.DUMMYFUNCTION("GOOGLEFINANCE(A37,""Change"")"),0.02) -> 0.02 | P37: =IFERROR(__xludf.DUMMYFUNCTION("GOOGLEFINANCE(A37,""High"")"),0.66) -> 0.66 | Q37: =IFERROR(__xludf.DUMMYFUNCTION("GOOGLEFINANCE(A37,""low"")"),0.64) -> 0.64 | R37: =IFERROR(__xludf.DUMMYFUNCTION("abs(P37-Q37)/GOOGLEFINANCE(A37,""closeyest"")"),0.03125000000000003) -> 0.03125 | S37: =D37/Y37-1 -> 1.64 | T37: 0.35 | W37: =IF(ISERROR(if(or(AND(Q37<=T37,T37<=P37),AND(Q37<=U37, U37<=P37)),"TRADE ALERT","")),"DATA UNAVAILABLE",if(or(AND(Q37<=T37,T37<=P37),T37>P37,AND(Q37<=U37, U37<=P37)),"TRADE ALERT"&" - Price level hit for "&A37&" currently at "&D37&" "&B37,"")) | X37: =IFERROR(__xludf.DUMMYFUNCTION("GOOGLEFINANCE($A37,X$3)"),"#N/A") -> #N/A | Y37: =IFERROR(__xludf.DUMMYFUNCTION("GOOGLEFINANCE($A37,Y$3)"),0.25) -> 0.25 | Z37: =IFERROR(__xludf.DUMMYFUNCTION("GOOGLEFINANCE($A37,Z$3)"),0.66) -> 0.66 | AA37: =IFERROR(__xludf.DUMMYFUNCTION("GOOGLEFINANCE($A37,AA$3)"),"#N/A") -> #N/A | AB37: =IFERROR(__xludf.DUMMYFUNCTION("GOOGLEFINANCE($A37,AB$3)"),"#N/A") -> #N/A | AC37: =IFERROR(__xludf.DUMMYFUNCTION("GOOGLEFINANCE($A37,AC$3)"),0.0) -> 0 | AD37: =IFERROR(__xludf.DUMMYFUNCTION("GOOGLEFINANCE($A37,AD$3)"),1.7066289426E10) -> 17066289426 | AE37: =IFERROR(__xludf.DUMMYFUNCTION("GOOGLEFINANCE($A37,AE$3)"),0.64) -> 0.64
A38: OMG | B38: =IFERROR(__xludf.DUMMYFUNCTION("GOOGLEFINANCE(A38,""name"")"),"Omai Gold Mines Corp") -> Omai Gold Mines Corp | D38: =IFERROR(__xludf.DUMMYFUNCTION("GOOGLEFINANCE(A38)"),1.99) -> 1.99 | K38: =(D38-E38)/E38 -> #DIV/0! | L38: =IFERROR(__xludf.DUMMYFUNCTION("SPARKLINE(GoogleFinance(A38, ""price"", TODAY()-30, TODAY()),{""color"",""blue"";""linewidth"",2}) "),"") | M38: =IFERROR(__xludf.DUMMYFUNCTION("GOOGLEFINANCE(A38,""currency"")"),"CAD") -> CAD | N38: =round(D38/AE38-1,4) -> -0.0293 | O38: =IFERROR(__xludf.DUMMYFUNCTION("GOOGLEFINANCE(A38,""Change"")"),-0.06) -> -0.06 | P38: =IFERROR(__xludf.DUMMYFUNCTION("GOOGLEFINANCE(A38,""High"")"),2.06) -> 2.06 | Q38: =IFERROR(__xludf.DUMMYFUNCTION("GOOGLEFINANCE(A38,""low"")"),1.91) -> 1.91 | R38: =IFERROR(__xludf.DUMMYFUNCTION("abs(P38-Q38)/GOOGLEFINANCE(A38,""closeyest"")"),0.07317073170731714) -> 0.073170732 | S38: =D38/Y38-1 -> 5.4193548 | T38: 80 | W38: =IF(ISERROR(if(or(AND(Q38<=T38,T38<=P38),AND(Q38<=U38, U38<=P38)),"TRADE ALERT","")),"DATA UNAVAILABLE",if(or(AND(Q38<=T38,T38<=P38),T38>P38,AND(Q38<=U38, U38<=P38)),"TRADE ALERT"&" - Price level hit for "&A38&" currently at "&D38&" "&B38,"")) -> TRADE ALERT - Price level hit for OMG currently at 1.99 Omai Gold Mines Corp | X38: =IFERROR(__xludf.DUMMYFUNCTION("GOOGLEFINANCE($A38,X$3)"),1.71) -> 1.71 | Y38: =IFERROR(__xludf.DUMMYFUNCTION("GOOGLEFINANCE($A38,Y$3)"),0.31) -> 0.31 | Z38: =IFERROR(__xludf.DUMMYFUNCTION("GOOGLEFINANCE($A38,Z$3)"),2.18) -> 2.18 | AA38: =IFERROR(__xludf.DUMMYFUNCTION("GOOGLEFINANCE($A38,AA$3)"),"#N/A") -> #N/A | AB38: =IFERROR(__xludf.DUMMYFUNCTION("GOOGLEFINANCE($A38,AB$3)"),"#N/A") -> #N/A | AC38: =IFERROR(__xludf.DUMMYFUNCTION("GOOGLEFINANCE($A38,AC$3)"),15.0) -> 15 | AD38: =IFERROR(__xludf.DUMMYFUNCTION("GOOGLEFINANCE($A38,AD$3)"),1.340140631E9) -> 1340140631 | AE38: =IFERROR(__xludf.DUMMYFUNCTION("GOOGLEFINANCE($A38,AE$3)"),2.05) -> 2.05
A39: GNUS | B39: =IFERROR(__xludf.DUMMYFUNCTION("GOOGLEFINANCE(A39,""name"")"),"#N/A") -> #N/A | D39: =IFERROR(__xludf.DUMMYFUNCTION("GOOGLEFINANCE(A39)"),"#N/A") -> #N/A | K39: =(D39-E39)/E39 -> #N/A | L39: =IFERROR(__xludf.DUMMYFUNCTION("SPARKLINE(GoogleFinance(A39, ""price"", TODAY()-30, TODAY()),{""color"",""blue"";""linewidth"",2}) "),"#N/A") -> #N/A | M39: =IFERROR(__xludf.DUMMYFUNCTION("GOOGLEFINANCE(A39,""currency"")"),"#N/A") -> #N/A | N39: =round(D39/AE39-1,4) -> #N/A | O39: =IFERROR(__xludf.DUMMYFUNCTION("GOOGLEFINANCE(A39,""Change"")"),"#N/A") -> #N/A | P39: =IFERROR(__xludf.DUMMYFUNCTION("GOOGLEFINANCE(A39,""High"")"),"#N/A") -> #N/A | Q39: =IFERROR(__xludf.DUMMYFUNCTION("GOOGLEFINANCE(A39,""low"")"),"#N/A") -> #N/A | R39: =IFERROR(__xludf.DUMMYFUNCTION("abs(P39-Q39)/GOOGLEFINANCE(A39,""closeyest"")"),"#N/A") -> #N/A | S39: =D39/Y39-1 -> #N/A | T39: 2.5 | W39: =IF(ISERROR(if(or(AND(Q39<=T39,T39<=P39),AND(Q39<=U39, U39<=P39)),"TRADE ALERT","")),"DATA UNAVAILABLE",if(or(AND(Q39<=T39,T39<=P39),T39>P39,AND(Q39<=U39, U39<=P39)),"TRADE ALERT"&" - Price level hit for "&A39&" currently at "&D39&" "&B39,"")) -> DATA UNAVAILABLE | X39: =IFERROR(__xludf.DUMMYFUNCTION("GOOGLEFINANCE($A39,X$3)"),"#N/A") -> #N/A | Y39: =IFERROR(__xludf.DUMMYFUNCTION("GOOGLEFINANCE($A39,Y$3)"),"#N/A") -> #N/A | Z39: =IFERROR(__xludf.DUMMYFUNCTION("GOOGLEFINANCE($A39,Z$3)"),"#N/A") -> #N/A | AA39: =IFERROR(__xludf.DUMMYFUNCTION("GOOGLEFINANCE($A39,AA$3)"),"#N/A") -> #N/A | AB39: =IFERROR(__xludf.DUMMYFUNCTION("GOOGLEFINANCE($A39,AB$3)"),"#N/A") -> #N/A | AC39: =IFERROR(__xludf.DUMMYFUNCTION("GOOGLEFINANCE($A39,AC$3)"),"#N/A") -> #N/A | AD39: =IFERROR(__xludf.DUMMYFUNCTION("GOOGLEFINANCE($A39,AD$3)"),"#N/A") -> #N/A | AE39: =IFERROR(__xludf.DUMMYFUNCTION("GOOGLEFINANCE($A39,AE$3)"),"#N/A") -> #N/A
A40: CPE | B40: =IFERROR(__xludf.DUMMYFUNCTION("GOOGLEFINANCE(A40,""name"")"),"Callon Petroleum Ord Shs") -> Callon Petroleum Ord Shs | D40: =IFERROR(__xludf.DUMMYFUNCTION("GOOGLEFINANCE(A40)"),0.0) -> 0 | K40: =(D40-E40)/E40 -> #DIV/0! | L40: =IFERROR(__xludf.DUMMYFUNCTION("SPARKLINE(GoogleFinance(A40, ""price"", TODAY()-30, TODAY()),{""color"",""blue"";""linewidth"",2}) "),"#N/A") -> #N/A | M40: =IFERROR(__xludf.DUMMYFUNCTION("GOOGLEFINANCE(A40,""currency"")"),"MXN") -> MXN | N40: =round(D40/AE40-1,4) -> -1 | O40: =IFERROR(__xludf.DUMMYFUNCTION("GOOGLEFINANCE(A40,""Change"")"),-557.0) -> -557 | P40: =IFERROR(__xludf.DUMMYFUNCTION("GOOGLEFINANCE(A40,""High"")"),"#N/A") -> #N/A | Q40: =IFERROR(__xludf.DUMMYFUNCTION("GOOGLEFINANCE(A40,""low"")"),"#N/A") -> #N/A | R40: =IFERROR(__xludf.DUMMYFUNCTION("abs(P40-Q40)/GOOGLEFINANCE(A40,""closeyest"")"),"#N/A") -> #N/A | S40: =D40/Y40-1 -> -1 | T40: 1 | W40: =IF(ISERROR(if(or(AND(Q40<=T40,T40<=P40),AND(Q40<=U40, U40<=P40)),"TRADE ALERT","")),"DATA UNAVAILABLE",if(or(AND(Q40<=T40,T40<=P40),T40>P40,AND(Q40<=U40, U40<=P40)),"TRADE ALERT"&" - Price level hit for "&A40&" currently at "&D40&" "&B40,"")) -> DATA UNAVAILABLE | X40: =IFERROR(__xludf.DUMMYFUNCTION("GOOGLEFINANCE($A40,X$3)"),"#N/A") -> #N/A | Y40: =IFERROR(__xludf.DUMMYFUNCTION("GOOGLEFINANCE($A40,Y$3)"),557.0) -> 557 | Z40: =IFERROR(__xludf.DUMMYFUNCTION("GOOGLEFINANCE($A40,Z$3)"),557.0) -> 557 | AA40: =IFERROR(__xludf.DUMMYFUNCTION("GOOGLEFINANCE($A40,AA$3)"),"#N/A") -> #N/A | AB40: =IFERROR(__xludf.DUMMYFUNCTION("GOOGLEFINANCE($A40,AB$3)"),"#N/A") -> #N/A | AC40: =IFERROR(__xludf.DUMMYFUNCTION("GOOGLEFINANCE($A40,AC$3)"),20.0) -> 20 | AD40: =IFERROR(__xludf.DUMMYFUNCTION("GOOGLEFINANCE($A40,AD$3)"),"#N/A") -> #N/A | AE40: =IFERROR(__xludf.DUMMYFUNCTION("GOOGLEFINANCE($A40,AE$3)"),557.0) -> 557
